Workbook
Name JULIANROA: CLIENTES!$A$30
Name ROAJULIAN: CLIENTES!$A$30
Name VERA_LUIS__ELECTROVERA: "JULIANROA"

Sheet CLIENTES
B1: MONTO PENDIENTE | C1: CELULAR
A2: AGUILAR FELIPE (BULLA) | B2: =VALUE('AGUILAR FELIPE (BULLA)'!J2) -> 538000
A3: AGUILAR FELIPE (BULLA) LICAN | B3: $
A4: BAHAMONDEZ JORGE | B4: =VALUE('BAHAMONDEZ JORGE'!J2) -> 0
A5: BARRIA MIGUEL | B5: =VALUE('BARRIA MIGUEL'!J2) -> 3000
A6: CANALES JOSE LUIS (MACACO) | B6: =VALUE('CANALES JOSE LUIS'!J2) -> 0
A7: CARDENAS GABRIEL | B7: =VALUE('CARDENAS GABRIEL'!J2) -> 58000 | C7: 15000
A8: CEA RAUL | B8: =VALUE('CEA RAUL'!J2) -> 164000
A9: COMIGUAL HUGO | B9: =VALUE('COMIGUAL HUGO'!J2) -> 87500
A10: DEL RIO LORCA EMERSON | B10: =VALUE('DEL RIO LORCA EMERSON'!J2) -> 130000
A11: DELGADO PATRICIO (RAPIDO Y FUR) | B11: =VALUE('DELGADO PATRICIO (RAPIDO Y FUR)'!J2) -> 0
A12: FOLLERT CARDENAS JOSE | B12: =VALUE('FOLLERT CARDENAS JOSE'!J2) -> 0
A13: FUENTES HECTOR | B13: =VALUE('FUENTES HECTOR'!J2) -> 0
A14: GALLARDO ARMANDO | B14: =VALUE('GALLARDO ARMANDO'!J2) -> 0
A15: GONZALEZ NELSON | B15: =VALUE('GONZALEZ NELSON'!J2) -> 25000
A16: GUERRERO RODRIGO | B16: =VALUE('GUERRERO RODRIGO'!J2) -> 0
A17: HANZ AGUILAR | B17: =VALUE('AGUILAR HANZ'!J2) -> 189000
A18: HECTOR HERNNADEZ (FALABELLA) | B18: =VALUE('HERNANDEZ HECTOR (FALABELLA)'!J2) -> 0
A19: HENRIQUES JORGE (HUEVO) | B19: =VALUE('HENRIQUES JORGE (HUEVO)'!J2) -> 12000
A20: HINOSTROZA MOISES (LA CUMBRE) | B20: =VALUE('HINOSTROZA MOISES (LA CUMBRE)'!J2) -> 0 | C20: 478500
A21: LORCA EMERSON | B21: 0
A22: MALDONADO MOISES
A23: MANUEL ROA | B23: =VALUE('ROA MANUEL'!J2) -> 356000
A24: MARCO BAHAMONDEZ (SUBOFICIAL) | B24: =VALUE('BAHAMONDEZ MARCO (SUBOFICIAL)'!J2) -> 201500
A25: MARTINEZ EDUARDO (FUSCHLOCHER) | B25: =VALUE('MARTINEZ EDUARDO (FUSCHLOCHER)'!J2) -> 0
A26: MAURICIO VALENZUELA(MALO PAL SEXO) | B26: 187500 | C26: saldo y repuestos yaris repuestos platina | E26: abono 08/04/2022 | F26: bateria 70 amperes stp $70000 12/08/2022 | G26: TOTAL$197500 ABONO $60000 9/07/2023
A27: MENARES MAIKOL (GRUA) | B27: =VALUE('MENARES MAIKOL (GRUA)'!J2) -> 110000
A28: MONTES WALTER (LOCO EDY) | B28: =VALUE('MONTES WALTER (LOCO EDY)'!J2) -> 159000
A29: MOTOR EXPRESS | B29: =VALUE('MOTOR EXPRESS'!J2) -> 898400
A30: PEDRO CARRASCO (ZORRO) | B30: =VALUE('CARRASCO PEDRO (ZORRO)'!J2) -> 28000
A31: PEREZ SADY
A32: PINGÜINO MAURI | B32: =VALUE('PINGUINO MAURI'!J2) -> 0
A33: PINUER OMAR | B33: =VALUE('PINUER OMAR'!J2) -> 126000
A34: PORTALES CRISTIAN | B34: =VALUE('PORTALES CRISTIAN'!J2) -> 1244000
A35: PUSCHEL PABLO | B35: =VALUE('PUSCHEL PABLO'!J2) -> 0 | C35: ALSACIA | E35: 580000
A36: QUEZADA RICHARD | B36: =VALUE('QUEZADA RICHARD'!J2) -> 0
A37: REYES ANDRES (PIRLO) | B37: =VALUE('REYES ANDRES (PIRLO)'!J2) -> 0
A38: RICARDO 5L | B38: =VALUE('RICARDO 5L'!J2) -> 0
A39: ROA JULIAN | B39: =VALUE('ROA JULIAN'!J2) -> 0
A40: ROBLES LUIS | B40: 0
A41: ROGEL MARCOS | B41: =VALUE('ROGEL MARCOS'!J2) -> 393500
A42: ROSAS ALVARO | B42: =VALUE('ROSAS ALVARO'!J2) -> 0
A43: ROSAS SERGIO (DON CHECHO) | B43: =VALUE('ROSAS SERGIO (DON CHECHO)'!J2) -> 0
A44: RUIZ JOAQUIN (CHISPA) | B44: =VALUE('RUIZ JOAQUIN (CHISPA)'!J2) -> 5500
A45: SEBASTIAN CONTRERAS | B45: =VALUE('CONTRERAS SEBASTIAN (PAREJAJUST'!J2) -> 38000 | C45: 989617361
A46: SOBARZO RODOLFO | B46: =VALUE('SOBARZO RODOLFO'!J2) -> 0
A47: SR. VELASQUEZ MECANICO | B47: =VALUE('VELASQUEZ MECANICO'!J2) -> 0
A48: T Y P | B48: =VALUE('T Y P'!J2) -> 0
A49: TIO CHINO LESPAI | B49: 0
A50: TOLEDO IVAN (EL TERRIBLE) | B50: =VALUE('TOLEDO IVAN (EL TERRIBLE)'!J2) -> 0
A51: VENEGAS EFRAIN BERNABE | B51: =VALUE('VENEGAS EFRAIN BERNABE'!J2) -> 0
A52: VERA LUIS (ELECTROVERA) | B52: =VALUE('VERA LUIS (ELECTROVERA)'!J2) -> 47000
A53: LOAIZA JOSE (FRANKE) | C53: SALDO SAIL | D53: 942492963
A54: CHICO JULIO | B54: 12000 | C54: embrague d21 | E54: 44582
A55: PAPA DE GUILLE | B55: 0 | C55: SALDO BANDEJA HOMOCINETICA | E55: 44600
A56: SEGOVIA GUILLERMO | B56: 0 | C56: SALDO BATERIA | E56: 44623
A57: FERNANDEZ NICASIO (TIO CABALLO) | B57: 0 | C57: JGO EMPAT 2,3 | E57: 44641
A58: TIO CABALLO | B58: 0 | C58: saldo bateria | E58: 44645
A59: PAREDES JUAN (PERRITO) | B59: 0 | C59: pagado | D59: 44652 | E59: 44645
A60: PALMA ROSAS JUAN (VITOY) | B60: 0
A61: CORONADO LORENA | B61: 0 | C61: ABONO 150.000+18000+100000 | E61: 44669 | F61: 44687
A62: MAESTRO GODOY CACHITO | B62: =VALUE('MAESTRO GODOY CACHITO'!J2) -> 15000 | C62: SELLO DE VALVULA BALENO | E62: 44670 | G62: presupuesto nº 4788 | H62: 230000 | I62: 15000
A63: NAGIAN BERNARDO | B63: =VALUE('NAGIAN BERNARDO '!J2) -> 0 | E63: 44715
A64: TIO OMAR | B64: 0 | E64: 44740
A65: AROS MARCIA | B65: =VALUE('AROS MARCIA'!J2) -> 0 | C65: SALDO BANDEJA | E65: 44746
A66: TOSKA | B66: =VALUE(TOSKA!J2) -> 0 | C66: para camion jefa | E66: 44772
A67: ROBERTO VILLARROEL | B67: 48500 | C67: BATERIA 55 AMPERES Y SENSOR OXIGENO | E67: 45096 | F67: tercera luz ampolleta emp tapa valvula 07/08/2023 | G67: ABONO $50.000 29/08
A68: HUALA CARLOS
A69: PLANTILLA | B69: =VALUE(PLANTILLA!J2) -> 0
A70: HUGO NILIAN | B70: 125000 | C70: PLUMILLA Y BATERIA | E70: 44810
A71: BONY | B71: 150000 | C71: aceite porter-afi d21 FOCO ESQ. D21 | E71: 45432 | F71: acite 28500 15w/40
A72: soldador | C72: 35000 bomba bujias | F72: 20000 jgo empa tapa radiador $4500
A73: javier nilian | B73: 34000 | E73: 44859
A74: CARLOS SEND | B74: 80000 | C74: CENTRIFUGO $60000+ BUJIAS $20,000 +15000 | F74: diferencia disco y pastilla $38000 21/11/2023
A75: jose ortiz | B75: 0 | E75: 44872
A76: MARCELO CARRILLO | B76: 75000 | E76: 44888
A77: auromotriz mackenna | B77: 0 | E77: 44890
A78: victor | B78: 0 | C78: diferencia jgo empa. H100 + metal biela std | E78: 44904 | F78: LISTO 24/01/23
A79: MARCELO HUISCAÑANCO | B79: 0 | C79: DIFERENCIA BATERIA 90 AMP | E79: 44918 | F79: ABONO $40000 01/03/2023
A80: ROCO | B80: 0 | C80: SAIL 1,4 | E80: 45610 | F80: abono $45000 11/12/2024
A81: FABIAN UTRERAS (EL AGUILA) | B81: 0 | C81: BATERIA | E81: 44943
A82: JOVANI TIO CHINO | B82: 22000 | C82: manilla
A83: COLEGIO RENE SORIANO BORQUEZ | B83: 0 | C83: BATERIA 90 AMPERES | F83: facturado 06/03/2023
A84: HUEITRA | B84: 13000 | C84: saldo piola empaquetadura | E84: 45392 | G84: DEUDA ANTERIOR LIBRO $107,000
A85: JULIAN GUARDA | B85: 70000 | C85: BOBINA BOMBA AGUA PLATINO Y CONDENSADOR | E85: 45000
A86: VICTOR VALDERAS | B86: 25000+37000+10000+22000 | C86: PROMo limpia+promo+B | E86: 45611
A87: VICTOR RAPIDO Y FURIOSO | B87: 10000 | C87: ROTULA NAVARA | E87: 45175
A88: MICHEL NAVARA | B88: 252000 | C88: pistola y limpiainyector | E88: 45054 | F88: abono $50,000 30/05 | G88: BOBINA+BUJIAS RENAULT $160.000 +SALDO PISTOLA $142.000
A89: JORGE CEA HERMANO RAUL CEA | B89: 0 | C89: PLUMILLA Y TAPA RADIADOR | E89: 45056 | F89: 950348114 FONO | G89: listo 15/09/2023
A90: ALEMBERTH MORALES | B90: 13000+65000 | C90: turbo+BATERIA 55 | E90: 45362 | F90: abono $40.000 17/05/2024 | G90: abono al turbo $40,000 15/07/2024
A91: vecino fruteria sra Marta | B91: 50000 | C91: cambio por pastilla freno quasquai
A92: JAIME DON SADY | B92: 0 | C92: SALDO L300 | E92: 45397 | G92: DEDUDA ANTERIOR LIBRO $62,000
A93: PAPA DE ENRIQUE ANGULO | B93: 0 | C93: SALDO ROTULA | E93: 45118
A94: JEREZ (CHUECO BUS NORTE) | B94: 10000 | C94: bateria morning | E94: 45636
A95: CARDENAS TORNERO (CHICO TIO CHOCHE) | C95: SALDO BATERIA 480CCA | E95: 45138
A96: ALVARO CARRILLO | B96: 73000 | C96: SALDO KIT EMBRAGUE | E96: 45168
A97: SRA NELLY FURGON | B97: 0 | E97: 45175
A98: CRISTIAN SANTANA (PAILA) | B98: 0 | C98: SALDO CULATA | E98: 45189
A99: CESAR CARDENAS | B99: 0 | C99: ALTO | E99: 45212
A100: VICTOR GUTTIERREZ (TIO PABLO) | B100: 0 | E100: 45212
...

Sheet PLANTILLA
A1: FECHA | B1: REPUESTO | C1: PRECIO | D1: CONDICION | E1: FACTURA | F1: VENDEDOR | H1: FACTURA | I1: DEUDA | J1: TOTAL DEUDA
C2: 0 | H2: =IF(E:E="NO FACTURADO","PENDIENTE","AL DIA") -> AL DIA | I2: =IF(D2="PENDIENTE",C2,0) -> 0 | J2: =SUM(I:I) -> 0 | K2: MENU
I3: =IF(D3="PENDIENTE",C3,0) -> 0
I4: =IF(D4="PENDIENTE",C4,0) -> 0
I5: =IF(D5="PENDIENTE",C5,0) -> 0
I6: =IF(D6="PENDIENTE",C6,0) -> 0
I7: =IF(D7="PENDIENTE",C7,0) -> 0
I8: =IF(D8="PENDIENTE",C8,0) -> 0
I9: =IF(D9="PENDIENTE",C9,0) -> 0
I10: =IF(D10="PENDIENTE",C10,0) -> 0
I11: =IF(D11="PENDIENTE",C11,0) -> 0
I12: =IF(D12="PENDIENTE",C12,0) -> 0
I13: =IF(D13="PENDIENTE",C13,0) -> 0
I14: =IF(D14="PENDIENTE",C14,0) -> 0
... I37: =IF(D37="PENDIENTE",C37,0) -> 0

Sheet PEDRO NEGRONI 
A1: FECHA | B1: REPUESTO | C1: PRECIO | D1: CONDICION | E1: FACTURA | F1: VENDEDOR | H1: FACTURA | I1: DEUDA | J1: TOTAL DEUDA
C2: 0 | H2: =IF(E:E="NO FACTURADO","PENDIENTE","AL DIA") -> AL DIA | I2: =IF(D2="PENDIENTE",C2,0) -> 0 | J2: =SUM(I:I) -> 8000 | K2: MENU
A3: 45618 | B3: aceite y filtro | C3: 8000 | D3: pendiente | E3: saldo aceite | I3: =IF(D3="PENDIENTE",C3,0) -> 8000
I4: =IF(D4="PENDIENTE",C4,0) -> 0
I5: =IF(D5="PENDIENTE",C5,0) -> 0
I6: =IF(D6="PENDIENTE",C6,0) -> 0
I7: =IF(D7="PENDIENTE",C7,0) -> 0
I8: =IF(D8="PENDIENTE",C8,0) -> 0
I9: =IF(D9="PENDIENTE",C9,0) -> 0
I10: =IF(D10="PENDIENTE",C10,0) -> 0
I11: =IF(D11="PENDIENTE",C11,0) -> 0
I12: =IF(D12="PENDIENTE",C12,0) -> 0
I13: =IF(D13="PENDIENTE",C13,0) -> 0
I14: =IF(D14="PENDIENTE",C14,0) -> 0
I15: =IF(D15="PENDIENTE",C15,0) -> 0
... I37: =IF(D37="PENDIENTE",C37,0) -> 0

Sheet JORGE CEA HERMANO RAUL CEA
A1: FECHA | B1: REPUESTO | C1: PRECIO | D1: CONDICION | E1: FACTURA | F1: VENDEDOR | H1: FACTURA | I1: DEUDA | J1: TOTAL DEUDA
C2: 0 | H2: =IF(E:E="NO FACTURADO","PENDIENTE","AL DIA") -> AL DIA | I2: =IF(D2="PENDIENTE",C2,0) -> 0 | J2: =SUM(I:I) -> 0 | K2: MENU
I3: =IF(D3="PENDIENTE",C3,0) -> 0
I4: =IF(D4="PENDIENTE",C4,0) -> 0
I5: =IF(D5="PENDIENTE",C5,0) -> 0
I6: =IF(D6="PENDIENTE",C6,0) -> 0
I7: =IF(D7="PENDIENTE",C7,0) -> 0
I8: =IF(D8="PENDIENTE",C8,0) -> 0
I9: =IF(D9="PENDIENTE",C9,0) -> 0
I10: =IF(D10="PENDIENTE",C10,0) -> 0
I11: =IF(D11="PENDIENTE",C11,0) -> 0
I12: =IF(D12="PENDIENTE",C12,0) -> 0
I13: =IF(D13="PENDIENTE",C13,0) -> 0
I14: =IF(D14="PENDIENTE",C14,0) -> 0
... I37: =IF(D37="PENDIENTE",C37,0) -> 0

Sheet ALEMBERTH MORALES
A1: FECHA | B1: REPUESTO | C1: PRECIO | D1: CONDICION | E1: FACTURA | F1: VENDEDOR | H1: FACTURA | I1: DEUDA | J1: TOTAL DEUDA
C2: 0 | H2: =IF(E:E="NO FACTURADO","PENDIENTE","AL DIA") -> AL DIA | I2: =IF(D2="PENDIENTE",C2,0) -> 0 | J2: =SUM(I:I) -> 0 | K2: MENU
I3: =IF(D3="PENDIENTE",C3,0) -> 0
I4: =IF(D4="PENDIENTE",C4,0) -> 0
I5: =IF(D5="PENDIENTE",C5,0) -> 0
I6: =IF(D6="PENDIENTE",C6,0) -> 0
I7: =IF(D7="PENDIENTE",C7,0) -> 0
I8: =IF(D8="PENDIENTE",C8,0) -> 0
I9: =IF(D9="PENDIENTE",C9,0) -> 0
I10: =IF(D10="PENDIENTE",C10,0) -> 0
I11: =IF(D11="PENDIENTE",C11,0) -> 0
I12: =IF(D12="PENDIENTE",C12,0) -> 0
I13: =IF(D13="PENDIENTE",C13,0) -> 0
I14: =IF(D14="PENDIENTE",C14,0) -> 0
... I37: =IF(D37="PENDIENTE",C37,0) -> 0

Sheet vecino fruteria sra Marta 
A1: FECHA | B1: REPUESTO | C1: PRECIO | D1: CONDICION | E1: FACTURA | F1: VENDEDOR | H1: FACTURA | I1: DEUDA | J1: TOTAL DEUDA
C2: 0 | H2: =IF(E:E="NO FACTURADO","PENDIENTE","AL DIA") -> AL DIA | I2: =IF(D2="PENDIENTE",C2,0) -> 0 | J2: =SUM(I:I) -> 0 | K2: MENU
I3: =IF(D3="PENDIENTE",C3,0) -> 0
I4: =IF(D4="PENDIENTE",C4,0) -> 0
I5: =IF(D5="PENDIENTE",C5,0) -> 0
I6: =IF(D6="PENDIENTE",C6,0) -> 0
I7: =IF(D7="PENDIENTE",C7,0) -> 0
I8: =IF(D8="PENDIENTE",C8,0) -> 0
I9: =IF(D9="PENDIENTE",C9,0) -> 0
I10: =IF(D10="PENDIENTE",C10,0) -> 0
I11: =IF(D11="PENDIENTE",C11,0) -> 0
I12: =IF(D12="PENDIENTE",C12,0) -> 0
I13: =IF(D13="PENDIENTE",C13,0) -> 0
I14: =IF(D14="PENDIENTE",C14,0) -> 0
... I37: =IF(D37="PENDIENTE",C37,0) -> 0

Sheet JAIME DON SADY
A1: FECHA | B1: REPUESTO | C1: PRECIO | D1: CONDICION | E1: FACTURA | F1: VENDEDOR | H1: FACTURA | I1: DEUDA | J1: TOTAL DEUDA
C2: 0 | H2: =IF(E:E="NO FACTURADO","PENDIENTE","AL DIA") -> AL DIA | I2: =IF(D2="PENDIENTE",C2,0) -> 0 | J2: =SUM(I:I) -> 0 | K2: MENU
I3: =IF(D3="PENDIENTE",C3,0) -> 0
I4: =IF(D4="PENDIENTE",C4,0) -> 0
I5: =IF(D5="PENDIENTE",C5,0) -> 0
I6: =IF(D6="PENDIENTE",C6,0) -> 0
I7: =IF(D7="PENDIENTE",C7,0) -> 0
I8: =IF(D8="PENDIENTE",C8,0) -> 0
I9: =IF(D9="PENDIENTE",C9,0) -> 0
I10: =IF(D10="PENDIENTE",C10,0) -> 0
I11: =IF(D11="PENDIENTE",C11,0) -> 0
I12: =IF(D12="PENDIENTE",C12,0) -> 0
I13: =IF(D13="PENDIENTE",C13,0) -> 0
I14: =IF(D14="PENDIENTE",C14,0) -> 0
... I37: =IF(D37="PENDIENTE",C37,0) -> 0

Sheet PAPA DE ENRIQUE ANGULO
A1: FECHA | B1: REPUESTO | C1: PRECIO | D1: CONDICION | E1: FACTURA | F1: VENDEDOR | H1: FACTURA | I1: DEUDA | J1: TOTAL DEUDA
C2: 0 | H2: =IF(E:E="NO FACTURADO","PENDIENTE","AL DIA") -> AL DIA | I2: =IF(D2="PENDIENTE",C2,0) -> 0 | J2: =SUM(I:I) -> 0 | K2: MENU
I3: =IF(D3="PENDIENTE",C3,0) -> 0
I4: =IF(D4="PENDIENTE",C4,0) -> 0
I5: =IF(D5="PENDIENTE",C5,0) -> 0
I6: =IF(D6="PENDIENTE",C6,0) -> 0
I7: =IF(D7="PENDIENTE",C7,0) -> 0
I8: =IF(D8="PENDIENTE",C8,0) -> 0
I9: =IF(D9="PENDIENTE",C9,0) -> 0
I10: =IF(D10="PENDIENTE",C10,0) -> 0
I11: =IF(D11="PENDIENTE",C11,0) -> 0
I12: =IF(D12="PENDIENTE",C12,0) -> 0
I13: =IF(D13="PENDIENTE",C13,0) -> 0
I14: =IF(D14="PENDIENTE",C14,0) -> 0
... I37: =IF(D37="PENDIENTE",C37,0) -> 0

Sheet JEREZ (CHUECO BUS NORTE)
A1: FECHA | B1: REPUESTO | C1: PRECIO | D1: CONDICION | E1: FACTURA | F1: VENDEDOR | H1: FACTURA | I1: DEUDA | J1: TOTAL DEUDA
C2: 0 | H2: =IF(E:E="NO FACTURADO","PENDIENTE","AL DIA") -> AL DIA | I2: =IF(D2="PENDIENTE",C2,0) -> 0 | J2: =SUM(I:I) -> 0 | K2: MENU
I3: =IF(D3="PENDIENTE",C3,0) -> 0
I4: =IF(D4="PENDIENTE",C4,0) -> 0
I5: =IF(D5="PENDIENTE",C5,0) -> 0
I6: =IF(D6="PENDIENTE",C6,0) -> 0
I7: =IF(D7="PENDIENTE",C7,0) -> 0
I8: =IF(D8="PENDIENTE",C8,0) -> 0
I9: =IF(D9="PENDIENTE",C9,0) -> 0
I10: =IF(D10="PENDIENTE",C10,0) -> 0
I11: =IF(D11="PENDIENTE",C11,0) -> 0
I12: =IF(D12="PENDIENTE",C12,0) -> 0
I13: =IF(D13="PENDIENTE",C13,0) -> 0
I14: =IF(D14="PENDIENTE",C14,0) -> 0
... I37: =IF(D37="PENDIENTE",C37,0) -> 0

Sheet CARDENAS TORNERO (CHICO TIO CHO
A1: FECHA | B1: REPUESTO | C1: PRECIO | D1: CONDICION | E1: FACTURA | F1: VENDEDOR | H1: FACTURA | I1: DEUDA | J1: TOTAL DEUDA
C2: 0 | H2: =IF(E:E="NO FACTURADO","PENDIENTE","AL DIA") -> AL DIA | I2: =IF(D2="PENDIENTE",C2,0) -> 0 | J2: =SUM(I:I) -> 0 | K2: MENU
I3: =IF(D3="PENDIENTE",C3,0) -> 0
I4: =IF(D4="PENDIENTE",C4,0) -> 0
I5: =IF(D5="PENDIENTE",C5,0) -> 0
I6: =IF(D6="PENDIENTE",C6,0) -> 0
I7: =IF(D7="PENDIENTE",C7,0) -> 0
I8: =IF(D8="PENDIENTE",C8,0) -> 0
I9: =IF(D9="PENDIENTE",C9,0) -> 0
I10: =IF(D10="PENDIENTE",C10,0) -> 0
I11: =IF(D11="PENDIENTE",C11,0) -> 0
I12: =IF(D12="PENDIENTE",C12,0) -> 0
I13: =IF(D13="PENDIENTE",C13,0) -> 0
I14: =IF(D14="PENDIENTE",C14,0) -> 0
... I37: =IF(D37="PENDIENTE",C37,0) -> 0

Sheet ALVARO CARRILLO
A1: FECHA | B1: REPUESTO | C1: PRECIO | D1: CONDICION | E1: FACTURA | F1: VENDEDOR | H1: FACTURA | I1: DEUDA | J1: TOTAL DEUDA
C2: 0 | H2: =IF(E:E="NO FACTURADO","PENDIENTE","AL DIA") -> AL DIA | I2: =IF(D2="PENDIENTE",C2,0) -> 0 | J2: =SUM(I:I) -> 0 | K2: MENU
I3: =IF(D3="PENDIENTE",C3,0) -> 0
I4: =IF(D4="PENDIENTE",C4,0) -> 0
I5: =IF(D5="PENDIENTE",C5,0) -> 0
I6: =IF(D6="PENDIENTE",C6,0) -> 0
I7: =IF(D7="PENDIENTE",C7,0) -> 0
I8: =IF(D8="PENDIENTE",C8,0) -> 0
I9: =IF(D9="PENDIENTE",C9,0) -> 0
I10: =IF(D10="PENDIENTE",C10,0) -> 0
I11: =IF(D11="PENDIENTE",C11,0) -> 0
I12: =IF(D12="PENDIENTE",C12,0) -> 0
I13: =IF(D13="PENDIENTE",C13,0) -> 0
I14: =IF(D14="PENDIENTE",C14,0) -> 0
... I37: =IF(D37="PENDIENTE",C37,0) -> 0

Sheet SRA NELLY FURGON
A1: FECHA | B1: REPUESTO | C1: PRECIO | D1: CONDICION | E1: FACTURA | F1: VENDEDOR | H1: FACTURA | I1: DEUDA | J1: TOTAL DEUDA
C2: 0 | H2: =IF(E:E="NO FACTURADO","PENDIENTE","AL DIA") -> AL DIA | I2: =IF(D2="PENDIENTE",C2,0) -> 0 | J2: =SUM(I:I) -> 0 | K2: MENU
I3: =IF(D3="PENDIENTE",C3,0) -> 0
I4: =IF(D4="PENDIENTE",C4,0) -> 0
I5: =IF(D5="PENDIENTE",C5,0) -> 0
I6: =IF(D6="PENDIENTE",C6,0) -> 0
I7: =IF(D7="PENDIENTE",C7,0) -> 0
I8: =IF(D8="PENDIENTE",C8,0) -> 0
I9: =IF(D9="PENDIENTE",C9,0) -> 0
I10: =IF(D10="PENDIENTE",C10,0) -> 0
I11: =IF(D11="PENDIENTE",C11,0) -> 0
I12: =IF(D12="PENDIENTE",C12,0) -> 0
I13: =IF(D13="PENDIENTE",C13,0) -> 0
I14: =IF(D14="PENDIENTE",C14,0) -> 0
... I37: =IF(D37="PENDIENTE",C37,0) -> 0

Sheet CRISTIAN SANTANA (PAILA)
A1: FECHA | B1: REPUESTO | C1: PRECIO | D1: CONDICION | E1: FACTURA | F1: VENDEDOR | H1: FACTURA | I1: DEUDA | J1: TOTAL DEUDA
C2: 0 | H2: =IF(E:E="NO FACTURADO","PENDIENTE","AL DIA") -> AL DIA | I2: =IF(D2="PENDIENTE",C2,0) -> 0 | J2: =SUM(I:I) -> 0 | K2: MENU
I3: =IF(D3="PENDIENTE",C3,0) -> 0
I4: =IF(D4="PENDIENTE",C4,0) -> 0
I5: =IF(D5="PENDIENTE",C5,0) -> 0
I6: =IF(D6="PENDIENTE",C6,0) -> 0
I7: =IF(D7="PENDIENTE",C7,0) -> 0
I8: =IF(D8="PENDIENTE",C8,0) -> 0
I9: =IF(D9="PENDIENTE",C9,0) -> 0
I10: =IF(D10="PENDIENTE",C10,0) -> 0
I11: =IF(D11="PENDIENTE",C11,0) -> 0
I12: =IF(D12="PENDIENTE",C12,0) -> 0
I13: =IF(D13="PENDIENTE",C13,0) -> 0
I14: =IF(D14="PENDIENTE",C14,0) -> 0
... I37: =IF(D37="PENDIENTE",C37,0) -> 0

Sheet CESAR CARDENAS
A1: FECHA | B1: REPUESTO | C1: PRECIO | D1: CONDICION | E1: FACTURA | F1: VENDEDOR | H1: FACTURA | I1: DEUDA | J1: TOTAL DEUDA
C2: 0 | H2: =IF(E:E="NO FACTURADO","PENDIENTE","AL DIA") -> AL DIA | I2: =IF(D2="PENDIENTE",C2,0) -> 0 | J2: =SUM(I:I) -> 0 | K2: MENU
I3: =IF(D3="PENDIENTE",C3,0) -> 0
I4: =IF(D4="PENDIENTE",C4,0) -> 0
I5: =IF(D5="PENDIENTE",C5,0) -> 0
I6: =IF(D6="PENDIENTE",C6,0) -> 0
I7: =IF(D7="PENDIENTE",C7,0) -> 0
I8: =IF(D8="PENDIENTE",C8,0) -> 0
I9: =IF(D9="PENDIENTE",C9,0) -> 0
I10: =IF(D10="PENDIENTE",C10,0) -> 0
I11: =IF(D11="PENDIENTE",C11,0) -> 0
I12: =IF(D12="PENDIENTE",C12,0) -> 0
I13: =IF(D13="PENDIENTE",C13,0) -> 0
I14: =IF(D14="PENDIENTE",C14,0) -> 0
... I37: =IF(D37="PENDIENTE",C37,0) -> 0

Sheet VICTOR GUTTIERREZ (TIO PABLO)
A1: FECHA | B1: REPUESTO | C1: PRECIO | D1: CONDICION | E1: FACTURA | F1: VENDEDOR | H1: FACTURA | I1: DEUDA | J1: TOTAL DEUDA
C2: 0 | H2: =IF(E:E="NO FACTURADO","PENDIENTE","AL DIA") -> AL DIA | I2: =IF(D2="PENDIENTE",C2,0) -> 0 | J2: =SUM(I:I) -> 0 | K2: MENU
I3: =IF(D3="PENDIENTE",C3,0) -> 0
I4: =IF(D4="PENDIENTE",C4,0) -> 0
I5: =IF(D5="PENDIENTE",C5,0) -> 0
I6: =IF(D6="PENDIENTE",C6,0) -> 0
I7: =IF(D7="PENDIENTE",C7,0) -> 0
I8: =IF(D8="PENDIENTE",C8,0) -> 0
I9: =IF(D9="PENDIENTE",C9,0) -> 0
I10: =IF(D10="PENDIENTE",C10,0) -> 0
I11: =IF(D11="PENDIENTE",C11,0) -> 0
I12: =IF(D12="PENDIENTE",C12,0) -> 0
I13: =IF(D13="PENDIENTE",C13,0) -> 0
I14: =IF(D14="PENDIENTE",C14,0) -> 0
... I37: =IF(D37="PENDIENTE",C37,0) -> 0

Sheet BORIS MANCILLA (CACHETE)
A1: FECHA | B1: REPUESTO | C1: PRECIO | D1: CONDICION | E1: FACTURA | F1: VENDEDOR | H1: FACTURA | I1: DEUDA | J1: TOTAL DEUDA
C2: 0 | H2: =IF(E:E="NO FACTURADO","PENDIENTE","AL DIA") -> AL DIA | I2: =IF(D2="PENDIENTE",C2,0) -> 0 | J2: =SUM(I:I) -> 0 | K2: MENU
I3: =IF(D3="PENDIENTE",C3,0) -> 0
I4: =IF(D4="PENDIENTE",C4,0) -> 0
I5: =IF(D5="PENDIENTE",C5,0) -> 0
I6: =IF(D6="PENDIENTE",C6,0) -> 0
I7: =IF(D7="PENDIENTE",C7,0) -> 0
I8: =IF(D8="PENDIENTE",C8,0) -> 0
I9: =IF(D9="PENDIENTE",C9,0) -> 0
I10: =IF(D10="PENDIENTE",C10,0) -> 0
I11: =IF(D11="PENDIENTE",C11,0) -> 0
I12: =IF(D12="PENDIENTE",C12,0) -> 0
I13: =IF(D13="PENDIENTE",C13,0) -> 0
I14: =IF(D14="PENDIENTE",C14,0) -> 0
... I37: =IF(D37="PENDIENTE",C37,0) -> 0

Sheet VICTOR MUÑOZ PEREZ (HUEITRA)
A1: FECHA | B1: REPUESTO | C1: PRECIO | D1: CONDICION | E1: FACTURA | F1: VENDEDOR | H1: FACTURA | I1: DEUDA | J1: TOTAL DEUDA
C2: 0 | H2: =IF(E:E="NO FACTURADO","PENDIENTE","AL DIA") -> AL DIA | I2: =IF(D2="PENDIENTE",C2,0) -> 0 | J2: =SUM(I:I) -> 0 | K2: MENU
I3: =IF(D3="PENDIENTE",C3,0) -> 0
I4: =IF(D4="PENDIENTE",C4,0) -> 0
I5: =IF(D5="PENDIENTE",C5,0) -> 0
I6: =IF(D6="PENDIENTE",C6,0) -> 0
I7: =IF(D7="PENDIENTE",C7,0) -> 0
I8: =IF(D8="PENDIENTE",C8,0) -> 0
I9: =IF(D9="PENDIENTE",C9,0) -> 0
I10: =IF(D10="PENDIENTE",C10,0) -> 0
I11: =IF(D11="PENDIENTE",C11,0) -> 0
I12: =IF(D12="PENDIENTE",C12,0) -> 0
I13: =IF(D13="PENDIENTE",C13,0) -> 0
I14: =IF(D14="PENDIENTE",C14,0) -> 0
... I37: =IF(D37="PENDIENTE",C37,0) -> 0

Sheet DON JAIME GALLARDO PUCA
A1: FECHA | B1: REPUESTO | C1: PRECIO | D1: CONDICION | E1: FACTURA | F1: VENDEDOR | H1: FACTURA | I1: DEUDA | J1: TOTAL DEUDA
C2: 0 | H2: =IF(E:E="NO FACTURADO","PENDIENTE","AL DIA") -> AL DIA | I2: =IF(D2="PENDIENTE",C2,0) -> 0 | J2: =SUM(I:I) -> 0 | K2: MENU
I3: =IF(D3="PENDIENTE",C3,0) -> 0
I4: =IF(D4="PENDIENTE",C4,0) -> 0
I5: =IF(D5="PENDIENTE",C5,0) -> 0
I6: =IF(D6="PENDIENTE",C6,0) -> 0
I7: =IF(D7="PENDIENTE",C7,0) -> 0
I8: =IF(D8="PENDIENTE",C8,0) -> 0
I9: =IF(D9="PENDIENTE",C9,0) -> 0
I10: =IF(D10="PENDIENTE",C10,0) -> 0
I11: =IF(D11="PENDIENTE",C11,0) -> 0
I12: =IF(D12="PENDIENTE",C12,0) -> 0
I13: =IF(D13="PENDIENTE",C13,0) -> 0
I14: =IF(D14="PENDIENTE",C14,0) -> 0
... I37: =IF(D37="PENDIENTE",C37,0) -> 0

Sheet ESTEBAN FARSO
A1: FECHA | B1: REPUESTO | C1: PRECIO | D1: CONDICION | E1: FACTURA | F1: VENDEDOR | H1: FACTURA | I1: DEUDA | J1: TOTAL DEUDA
C2: 0 | H2: =IF(E:E="NO FACTURADO","PENDIENTE","AL DIA") -> AL DIA | I2: =IF(D2="PENDIENTE",C2,0) -> 0 | J2: =SUM(I:I) -> 0 | K2: MENU
I3: =IF(D3="PENDIENTE",C3,0) -> 0
I4: =IF(D4="PENDIENTE",C4,0) -> 0
I5: =IF(D5="PENDIENTE",C5,0) -> 0
I6: =IF(D6="PENDIENTE",C6,0) -> 0
I7: =IF(D7="PENDIENTE",C7,0) -> 0
I8: =IF(D8="PENDIENTE",C8,0) -> 0
I9: =IF(D9="PENDIENTE",C9,0) -> 0
I10: =IF(D10="PENDIENTE",C10,0) -> 0
I11: =IF(D11="PENDIENTE",C11,0) -> 0
I12: =IF(D12="PENDIENTE",C12,0) -> 0
I13: =IF(D13="PENDIENTE",C13,0) -> 0
I14: =IF(D14="PENDIENTE",C14,0) -> 0
... I37: =IF(D37="PENDIENTE",C37,0) -> 0

Sheet MANUEL VILLA 
A1: FECHA | B1: REPUESTO | C1: PRECIO | D1: CONDICION | E1: FACTURA | F1: VENDEDOR | H1: FACTURA | I1: DEUDA | J1: TOTAL DEUDA
C2: 0 | H2: =IF(E:E="NO FACTURADO","PENDIENTE","AL DIA") -> AL DIA | I2: =IF(D2="PENDIENTE",C2,0) -> 0 | J2: =SUM(I:I) -> 0 | K2: MENU
I3: =IF(D3="PENDIENTE",C3,0) -> 0
I4: =IF(D4="PENDIENTE",C4,0) -> 0
I5: =IF(D5="PENDIENTE",C5,0) -> 0
I6: =IF(D6="PENDIENTE",C6,0) -> 0
I7: =IF(D7="PENDIENTE",C7,0) -> 0
I8: =IF(D8="PENDIENTE",C8,0) -> 0
I9: =IF(D9="PENDIENTE",C9,0) -> 0
I10: =IF(D10="PENDIENTE",C10,0) -> 0
I11: =IF(D11="PENDIENTE",C11,0) -> 0
I12: =IF(D12="PENDIENTE",C12,0) -> 0
I13: =IF(D13="PENDIENTE",C13,0) -> 0
I14: =IF(D14="PENDIENTE",C14,0) -> 0
... I37: =IF(D37="PENDIENTE",C37,0) -> 0

Sheet VECINO GAS MOLL
A1: FECHA | B1: REPUESTO | C1: PRECIO | D1: CONDICION | E1: FACTURA | F1: VENDEDOR | H1: FACTURA | I1: DEUDA | J1: TOTAL DEUDA
C2: 0 | H2: =IF(E:E="NO FACTURADO","PENDIENTE","AL DIA") -> AL DIA | I2: =IF(D2="PENDIENTE",C2,0) -> 0 | J2: =SUM(I:I) -> 0 | K2: MENU
I3: =IF(D3="PENDIENTE",C3,0) -> 0
I4: =IF(D4="PENDIENTE",C4,0) -> 0
I5: =IF(D5="PENDIENTE",C5,0) -> 0
I6: =IF(D6="PENDIENTE",C6,0) -> 0
I7: =IF(D7="PENDIENTE",C7,0) -> 0
I8: =IF(D8="PENDIENTE",C8,0) -> 0
I9: =IF(D9="PENDIENTE",C9,0) -> 0
I10: =IF(D10="PENDIENTE",C10,0) -> 0
I11: =IF(D11="PENDIENTE",C11,0) -> 0
I12: =IF(D12="PENDIENTE",C12,0) -> 0
I13: =IF(D13="PENDIENTE",C13,0) -> 0
I14: =IF(D14="PENDIENTE",C14,0) -> 0
... I37: =IF(D37="PENDIENTE",C37,0) -> 0

Sheet PAPA DE GUILLE
A1: FECHA | B1: REPUESTO | C1: PRECIO | D1: CONDICION | E1: FACTURA | F1: VENDEDOR | H1: FACTURA | I1: DEUDA | J1: TOTAL DEUDA
H2: =IF(E:E="NO FACTURADO","PENDIENTE","AL DIA") -> AL DIA | I2: =IF(D2="PENDIENTE",C2,0) -> 0 | J2: =SUM(I:I) -> 0 | K2: MENU
I3: =IF(D3="PENDIENTE",C3,0) -> 0
I4: =IF(D4="PENDIENTE",C4,0) -> 0
I5: =IF(D5="PENDIENTE",C5,0) -> 0
I6: =IF(D6="PENDIENTE",C6,0) -> 0
I7: =IF(D7="PENDIENTE",C7,0) -> 0
I8: =IF(D8="PENDIENTE",C8,0) -> 0
I9: =IF(D9="PENDIENTE",C9,0) -> 0
I10: =IF(D10="PENDIENTE",C10,0) -> 0
I11: =IF(D11="PENDIENTE",C11,0) -> 0
I12: =IF(D12="PENDIENTE",C12,0) -> 0
I13: =IF(D13="PENDIENTE",C13,0) -> 0
I14: =IF(D14="PENDIENTE",C14,0) -> 0
... I37: =IF(D37="PENDIENTE",C37,0) -> 0

Sheet SEGOVIA GUILLERMO
A1: FECHA | B1: REPUESTO | C1: PRECIO | D1: CONDICION | E1: FACTURA | F1: VENDEDOR | H1: FACTURA | I1: DEUDA | J1: TOTAL DEUDA
H2: =IF(E:E="NO FACTURADO","PENDIENTE","AL DIA") -> AL DIA | I2: =IF(D2="PENDIENTE",C2,0) -> 0 | J2: =SUM(I:I) -> 0 | K2: MENU
A3: 02/0572023 | B3: SALDO BATERIA S10 | C3: 80000 | D3: PAGADO | F3: DELIS | I3: =IF(D3="PENDIENTE",C3,0) -> 0
I4: =IF(D4="PENDIENTE",C4,0) -> 0
I5: =IF(D5="PENDIENTE",C5,0) -> 0
I6: =IF(D6="PENDIENTE",C6,0) -> 0
I7: =IF(D7="PENDIENTE",C7,0) -> 0
I8: =IF(D8="PENDIENTE",C8,0) -> 0
I9: =IF(D9="PENDIENTE",C9,0) -> 0
I10: =IF(D10="PENDIENTE",C10,0) -> 0
I11: =IF(D11="PENDIENTE",C11,0) -> 0
I12: =IF(D12="PENDIENTE",C12,0) -> 0
I13: =IF(D13="PENDIENTE",C13,0) -> 0
I14: =IF(D14="PENDIENTE",C14,0) -> 0
I15: =IF(D15="PENDIENTE",C15,0) -> 0
... I37: =IF(D37="PENDIENTE",C37,0) -> 0

Sheet FERNANDEZ NICASIO (TIO CABALLO)
A1: FECHA | B1: REPUESTO | C1: PRECIO | D1: CONDICION | E1: FACTURA | F1: VENDEDOR | H1: FACTURA | I1: DEUDA | J1: TOTAL DEUDA
H2: =IF(E:E="NO FACTURADO","PENDIENTE","AL DIA") -> AL DIA | I2: =IF(D2="PENDIENTE",C2,0) -> 0 | J2: =SUM(I:I) -> 0 | K2: MENU
A3: 45044 | B3: CREMALLERA DIRECCION DMAX | C3: 185000 | D3: pagado | I3: =IF(D3="PENDIENTE",C3,0) -> 0
A4: 45044 | B4: ATF | C4: 7500 | D4: pagado | I4: =IF(D4="PENDIENTE",C4,0) -> 0
A5: 45379 | B5: saldo kit embrague | C5: 50000 | D5: pagado | E5: pagado | I5: =IF(E5="PENDIENTE",C5,0) -> 0
A6: 45527 | B6: REPUESTOS LUV 2,2 | C6: 40000 | D6: pagado | E6: abono $50000 25/09 | I6: =IF(D6="PENDIENTE",C6,0) -> 0
A7: 45533 | B7: EJE LEVA BALANCIN | C7: 121000 | D7: pagado | I7: =IF(D7="PENDIENTE",C7,0) -> 0
I8: =IF(D8="PENDIENTE",C8,0) -> 0
I9: =IF(D9="PENDIENTE",C9,0) -> 0
I10: =IF(D10="PENDIENTE",C10,0) -> 0
I11: =IF(D11="PENDIENTE",C11,0) -> 0
I12: =IF(D12="PENDIENTE",C12,0) -> 0
I13: =IF(D13="PENDIENTE",C13,0) -> 0
I14: =IF(D14="PENDIENTE",C14,0) -> 0
I15: =IF(D15="PENDIENTE",C15,0) -> 0
I16: =IF(D16="PENDIENTE",C16,0) -> 0
I17: =IF(D17="PENDIENTE",C17,0) -> 0
I18: =IF(D18="PENDIENTE",C18,0) -> 0
I19: =IF(D19="PENDIENTE",C19,0) -> 0
... I37: =IF(D37="PENDIENTE",C37,0) -> 0

Sheet TIO CABALLO
A1: FECHA | B1: REPUESTO | C1: PRECIO | D1: CONDICION | E1: FACTURA | F1: VENDEDOR | H1: FACTURA | I1: DEUDA | J1: TOTAL DEUDA
A2: 45065 | B2: saldo cremallera | C2: 27000 | D2: pagado | H2: =IF(E:E="NO FACTURADO","PENDIENTE","AL DIA") -> AL DIA | I2: =IF(D2="PENDIENTE",C2,0) -> 0 | J2: =SUM(I:I) -> 112000 | K2: MENU
A3: 45170 | B3: saldo optico | C3: 15000 | D3: pagado | I3: =IF(D3="PENDIENTE",C3,0) -> 0
B4: TAMBOR FRENO PATINES | C4: 95000 | D4: pagado | I4: =IF(D4="PENDIENTE",C4,0) -> 0
A5: 45358 | B5: kit embrague | C5: 85000 | D5: pagado | I5: =IF(D5="PENDIENTE",C5,0) -> 0
A6: 45415 | B6: BATERIA 90AMPERES POSITIVO LH | C6: 110000 | D6: pagado | I6: =IF(D6="PENDIENTE",C6,0) -> 0
A7: 45608 | B7: pistones caliper x2 | C7: 50000 | D7: pagado | I7: =IF(D7="PENDIENTE",C7,0) -> 0
A8: 45609 | B8: jgo rodamiento maza x2 | C8: 90000 | D8: pagado | I8: =IF(D8="PENDIENTE",C8,0) -> 0
A9: 45609 | B9: homocinetica x1 | C9: 20000 | D9: pendiente | E9: abono $160000 | I9: =IF(D9="PENDIENTE",C9,0) -> 20000
A10: 45609 | B10: rotula inferior x2 | C10: 64000 | D10: pendiente | I10: =IF(D10="PENDIENTE",C10,0) -> 64000
A11: 45602 | B11: repuesto | C11: 28000 | D11: pendiente | I11: =IF(D11="PENDIENTE",C11,0) -> 28000
I12: =IF(D12="PENDIENTE",C12,0) -> 0
I13: =IF(D13="PENDIENTE",C13,0) -> 0
I14: =IF(D14="PENDIENTE",C14,0) -> 0
I15: =IF(D15="PENDIENTE",C15,0) -> 0
I16: =IF(D16="PENDIENTE",C16,0) -> 0
I17: =IF(D17="PENDIENTE",C17,0) -> 0
I18: =IF(D18="PENDIENTE",C18,0) -> 0
I19: =IF(D19="PENDIENTE",C19,0) -> 0
I20: =IF(D20="PENDIENTE",C20,0) -> 0
I21: =IF(D21="PENDIENTE",C21,0) -> 0
I22: =IF(D22="PENDIENTE",C22,0) -> 0
I23: =IF(D23="PENDIENTE",C23,0) -> 0
... I37: =IF(D37="PENDIENTE",C37,0) -> 0

Sheet PAREDES JUAN (PERRITO)
A1: FECHA | B1: REPUESTO | C1: PRECIO | D1: CONDICION | E1: FACTURA | F1: VENDEDOR | H1: FACTURA | I1: DEUDA | J1: TOTAL DEUDA
A2: 44753 | B2: cilindro freno y liquido | C2: 30000 | D2: PAGADO | F2: delis | H2: =IF(E:E="NO FACTURADO","PENDIENTE","AL DIA") -> AL DIA | I2: =IF(D2="PENDIENTE",C2,0) -> 0 | J2: =SUM(I:I) -> 0 | K2: MENU
A3: 45112 | B3: ACEITE SHELL X2 CATALITICO | C3: 120000 | D3: PAGADO | F3: CESAR | I3: =IF(D3="PENDIENTE",C3,0) -> 0
I4: =IF(D4="PENDIENTE",C4,0) -> 0
I5: =IF(D5="PENDIENTE",C5,0) -> 0
I6: =IF(D6="PENDIENTE",C6,0) -> 0
I7: =IF(D7="PENDIENTE",C7,0) -> 0
I8: =IF(D8="PENDIENTE",C8,0) -> 0
I9: =IF(D9="PENDIENTE",C9,0) -> 0
I10: =IF(D10="PENDIENTE",C10,0) -> 0
I11: =IF(D11="PENDIENTE",C11,0) -> 0
I12: =IF(D12="PENDIENTE",C12,0) -> 0
I13: =IF(D13="PENDIENTE",C13,0) -> 0
I14: =IF(D14="PENDIENTE",C14,0) -> 0
I15: =IF(D15="PENDIENTE",C15,0) -> 0
... I37: =IF(D37="PENDIENTE",C37,0) -> 0

Sheet PALMA ROSAS JUAN  (VITOY)
A1: FECHA | B1: REPUESTO | C1: PRECIO | D1: CONDICION | E1: FACTURA | F1: VENDEDOR | H1: FACTURA | I1: DEUDA | J1: TOTAL DEUDA
A2: 44852 | B2: BATERIA 55 AMP | C2: 50000 | D2: PAGADO | F2: CESAR | H2: =IF(E:E="NO FACTURADO","PENDIENTE","AL DIA") -> AL DIA | I2: =IF(D2="PENDIENTE",C2,0) -> 0 | J2: =SUM(I:I) -> 0 | K2: MENU
A3: 44902 | B3: OPTICO CORSA LH | C3: 30000 | D3: PAGADO | F3: DELIS | I3: =IF(D3="PENDIENTE",C3,0) -> 0
A4: 45224 | B4: KIT EMBRAGUE | C4: 130000 | D4: PAGADO | F4: DELIS | I4: =IF(D4="PENDIENTE",C4,0) -> 0
A5: 45265 | B5: PATINES Y PASTILLA FRENO | C5: 46000 | D5: PAGADO | I5: =IF(D5="PENDIENTE",C5,0) -> 0
A6: 44937 | B6: bandeja accent 2018 | C6: 52000 | D6: PAGADO | I6: =IF(D6="PENDIENTE",C6,0) -> 0
I7: =IF(D7="PENDIENTE",C7,0) -> 0
I8: =IF(D8="PENDIENTE",C8,0) -> 0
I9: =IF(D9="PENDIENTE",C9,0) -> 0
I10: =IF(D10="PENDIENTE",C10,0) -> 0
I11: =IF(D11="PENDIENTE",C11,0) -> 0
I12: =IF(D12="PENDIENTE",C12,0) -> 0
I13: =IF(D13="PENDIENTE",C13,0) -> 0
I14: =IF(D14="PENDIENTE",C14,0) -> 0
I15: =IF(D15="PENDIENTE",C15,0) -> 0
I16: =IF(D16="PENDIENTE",C16,0) -> 0
I17: =IF(D17="PENDIENTE",C17,0) -> 0
I18: =IF(D18="PENDIENTE",C18,0) -> 0
... I37: =IF(D37="PENDIENTE",C37,0) -> 0

Sheet CORONADO LORENA
A1: FECHA | B1: REPUESTO | C1: PRECIO | D1: CONDICION | E1: FACTURA | F1: VENDEDOR | H1: FACTURA | I1: DEUDA | J1: TOTAL DEUDA
A2: 44894 | B2: saldo repuestos | C2: 100000 | D2: pagado | F2: delis | H2: =IF(E:E="NO FACTURADO","PENDIENTE","AL DIA") -> AL DIA | I2: =IF(D2="PENDIENTE",C2,0) -> 0 | J2: =SUM(I:I) -> 0 | K2: MENU
A3: 44945 | B3: SALDO REPUESTOS BATERIA PASTILLA LIQU FRENO | C3: 59500 | D3: pagado | F3: DELIS | I3: =IF(D3="PENDIENTE",C3,0) -> 0
A4: 44992 | B4: bateria filtro aire foco carro | C4: 65000 | D4: PAGADO | F4: cesar | I4: =IF(D4="PENDIENTE",C4,0) -> 0
A5: 45077 | B5: pastilla d21 + liquido freno senfineco | C5: 21500 | D5: PAGADO | F5: omar | I5: =IF(D5="PENDIENTE",C5,0) -> 0
A6: 45146 | B6: amortiguadores traseros kia | C6: 80000 | D6: PAGADO | F6: cesar | I6: =IF(D6="PENDIENTE",C6,0) -> 0
A7: 45217 | B7: AMORTIGUADORES DELANTEROS BUJES Y PTA | C7: 15000 | D7: PAGADO | F7: DELIS | I7: =IF(D7="PENDIENTE",C7,0) -> 0
A8: 45225 | B8: bomba embrague y liquido freno | C8: 38500 | D8: PAGADO | F8: cesar | I8: =IF(D8="PENDIENTE",C8,0) -> 0
A9: 45331 | B9: pastillas de frenos kia | C9: 20000 | D9: pagado | I9: =IF(D9="PENDIENTE",C9,0) -> 0
A10: 45446 | B10: PRESUPUESTO 6213 | C10: 420000 | D10: pagado | E10: ABONO $150000 | I10: =IF(D10="PENDIENTE",C10,0) -> 0
A11: 45471 | B11: filtro aire y bornes bateria | C11: 16000 | D11: pagado | I11: =IF(D11="PENDIENTE",C11,0) -> 0
I12: =IF(D12="PENDIENTE",C12,0) -> 0
I13: =IF(D13="PENDIENTE",C13,0) -> 0
I14: =IF(D14="PENDIENTE",C14,0) -> 0
I15: =IF(D15="PENDIENTE",C15,0) -> 0
I16: =IF(D16="PENDIENTE",C16,0) -> 0
I17: =IF(D17="PENDIENTE",C17,0) -> 0
I18: =IF(D18="PENDIENTE",C18,0) -> 0
I19: =IF(D19="PENDIENTE",C19,0) -> 0
I20: =IF(D20="PENDIENTE",C20,0) -> 0
I21: =IF(D21="PENDIENTE",C21,0) -> 0
I22: =IF(D22="PENDIENTE",C22,0) -> 0
I23: =IF(D23="PENDIENTE",C23,0) -> 0
... I37: =IF(D37="PENDIENTE",C37,0) -> 0

Sheet MAESTRO GODOY  CACHITO
A1: FECHA | B1: REPUESTO | C1: PRECIO | D1: CONDICION | E1: FACTURA | F1: VENDEDOR | H1: FACTURA | I1: DEUDA | J1: TOTAL DEUDA
C2: 15000 | D2: PENDIENTE | H2: =IF(E:E="NO FACTURADO","PENDIENTE","AL DIA") -> AL DIA | I2: =IF(D2="PENDIENTE",C2,0) -> 15000 | J2: =SUM(I:I) -> 15000 | K2: MENU
I3: =IF(D3="PENDIENTE",C3,0) -> 0
I4: =IF(D4="PENDIENTE",C4,0) -> 0
I5: =IF(D5="PENDIENTE",C5,0) -> 0
I6: =IF(D6="PENDIENTE",C6,0) -> 0
I7: =IF(D7="PENDIENTE",C7,0) -> 0
I8: =IF(D8="PENDIENTE",C8,0) -> 0
I9: =IF(D9="PENDIENTE",C9,0) -> 0
I10: =IF(D10="PENDIENTE",C10,0) -> 0
I11: =IF(D11="PENDIENTE",C11,0) -> 0
I12: =IF(D12="PENDIENTE",C12,0) -> 0
I13: =IF(D13="PENDIENTE",C13,0) -> 0
I14: =IF(D14="PENDIENTE",C14,0) -> 0
... I37: =IF(D37="PENDIENTE",C37,0) -> 0

Sheet NAGIAN BERNARDO 
A1: FECHA | B1: REPUESTO | C1: PRECIO | D1: CONDICION | E1: FACTURA | F1: VENDEDOR | H1: FACTURA | I1: DEUDA | J1: TOTAL DEUDA
H2: =IF(E:E="NO FACTURADO","PENDIENTE","AL DIA") -> AL DIA | I2: =IF(D2="PENDIENTE",C2,0) -> 0 | J2: =SUM(I:I) -> 0 | K2: MENU
I3: =IF(D3="PENDIENTE",C3,0) -> 0
I4: =IF(D4="PENDIENTE",C4,0) -> 0
I5: =IF(D5="PENDIENTE",C5,0) -> 0
I6: =IF(D6="PENDIENTE",C6,0) -> 0
I7: =IF(D7="PENDIENTE",C7,0) -> 0
I8: =IF(D8="PENDIENTE",C8,0) -> 0
I9: =IF(D9="PENDIENTE",C9,0) -> 0
I10: =IF(D10="PENDIENTE",C10,0) -> 0
I11: =IF(D11="PENDIENTE",C11,0) -> 0
I12: =IF(D12="PENDIENTE",C12,0) -> 0
I13: =IF(D13="PENDIENTE",C13,0) -> 0
I14: =IF(D14="PENDIENTE",C14,0) -> 0
... I37: =IF(D37="PENDIENTE",C37,0) -> 0

Sheet TIO OMAR
A1: FECHA | B1: REPUESTO | C1: PRECIO | D1: CONDICION | E1: FACTURA | F1: VENDEDOR | H1: FACTURA | I1: DEUDA | J1: TOTAL DEUDA
D2: pendiente | H2: =IF(E:E="NO FACTURADO","PENDIENTE","AL DIA") -> AL DIA | I2: =IF(D2="PENDIENTE",C2,0) -> 0 | J2: =SUM(I:I) -> 0 | K2: MENU
A3: 45107 | B3: filtro aire y cabina | C3: 10000 | D3: pagado | F3: delis | I3: =IF(D3="PENDIENTE",C3,0) -> 0
A4: 45348 | B4: cazoleta delantera derecha | C4: 18000 | D4: pagado | I4: =IF(D4="PENDIENTE",C4,0) -> 0
A5: 45436 | B5: filtro cabina | C5: 5000 | D5: pagado | I5: =IF(D5="PENDIENTE",C5,0) -> 0
I6: =IF(D6="PENDIENTE",C6,0) -> 0
I7: =IF(D7="PENDIENTE",C7,0) -> 0
I8: =IF(D8="PENDIENTE",C8,0) -> 0
I9: =IF(D9="PENDIENTE",C9,0) -> 0
I10: =IF(D10="PENDIENTE",C10,0) -> 0
I11: =IF(D11="PENDIENTE",C11,0) -> 0
I12: =IF(D12="PENDIENTE",C12,0) -> 0
I13: =IF(D13="PENDIENTE",C13,0) -> 0
I14: =IF(D14="PENDIENTE",C14,0) -> 0
I15: =IF(D15="PENDIENTE",C15,0) -> 0
I16: =IF(D16="PENDIENTE",C16,0) -> 0
I17: =IF(D17="PENDIENTE",C17,0) -> 0
... I37: =IF(D37="PENDIENTE",C37,0) -> 0

Sheet AROS MARCIA
A1: FECHA | B1: REPUESTO | C1: PRECIO | D1: CONDICION | E1: FACTURA | F1: VENDEDOR | H1: FACTURA | I1: DEUDA | J1: TOTAL DEUDA
H2: =IF(E:E="NO FACTURADO","PENDIENTE","AL DIA") -> AL DIA | I2: =IF(D2="PENDIENTE",C2,0) -> 0 | J2: =SUM(I:I) -> 0 | K2: MENU
I3: =IF(D3="PENDIENTE",C3,0) -> 0
I4: =IF(D4="PENDIENTE",C4,0) -> 0
I5: =IF(D5="PENDIENTE",C5,0) -> 0
I6: =IF(D6="PENDIENTE",C6,0) -> 0
I7: =IF(D7="PENDIENTE",C7,0) -> 0
I8: =IF(D8="PENDIENTE",C8,0) -> 0
I9: =IF(D9="PENDIENTE",C9,0) -> 0
I10: =IF(D10="PENDIENTE",C10,0) -> 0
I11: =IF(D11="PENDIENTE",C11,0) -> 0
I12: =IF(D12="PENDIENTE",C12,0) -> 0
I13: =IF(D13="PENDIENTE",C13,0) -> 0
I14: =IF(D14="PENDIENTE",C14,0) -> 0
... I37: =IF(D37="PENDIENTE",C37,0) -> 0

Sheet TOSKA
A1: FECHA | B1: REPUESTO | C1: PRECIO | D1: CONDICION | E1: FACTURA | F1: VENDEDOR | H1: FACTURA | I1: DEUDA | J1: TOTAL DEUDA
H2: =IF(E:E="NO FACTURADO","PENDIENTE","AL DIA") -> AL DIA | I2: =IF(D2="PENDIENTE",C2,0) -> 0 | J2: =SUM(I:I) -> 0 | K2: MENU
A3: 45072 | B3: farol kia | C3: 48000 | D3: PAGADO | F3: cesar | I3: =IF(D3="PENDIENTE",C3,0) -> 0
I4: =IF(D4="PENDIENTE",C4,0) -> 0
I5: =IF(D5="PENDIENTE",C5,0) -> 0
I6: =IF(D6="PENDIENTE",C6,0) -> 0
I7: =IF(D7="PENDIENTE",C7,0) -> 0
I8: =IF(D8="PENDIENTE",C8,0) -> 0
I9: =IF(D9="PENDIENTE",C9,0) -> 0
I10: =IF(D10="PENDIENTE",C10,0) -> 0
I11: =IF(D11="PENDIENTE",C11,0) -> 0
I12: =IF(D12="PENDIENTE",C12,0) -> 0
I13: =IF(D13="PENDIENTE",C13,0) -> 0
I14: =IF(D14="PENDIENTE",C14,0) -> 0
I15: =IF(D15="PENDIENTE",C15,0) -> 0
... I37: =IF(D37="PENDIENTE",C37,0) -> 0

Sheet CLIENTE NUEVO
A1: FECHA | B1: REPUESTO | C1: PRECIO | D1: CONDICION | E1: FACTURA | F1: VENDEDOR | H1: FACTURA | I1: DEUDA | J1: TOTAL DEUDA
H2: =IF(E:E="NO FACTURADO","PENDIENTE","AL DIA") -> AL DIA | I2: =IF(D2="PENDIENTE",C2,0) -> 0 | J2: =SUM(I:I) -> 0 | K2: MENU
I3: =IF(D3="PENDIENTE",C3,0) -> 0
I4: =IF(D4="PENDIENTE",C4,0) -> 0
I5: =IF(D5="PENDIENTE",C5,0) -> 0
I6: =IF(D6="PENDIENTE",C6,0) -> 0
I7: =IF(D7="PENDIENTE",C7,0) -> 0
I8: =IF(D8="PENDIENTE",C8,0) -> 0
I9: =IF(D9="PENDIENTE",C9,0) -> 0
I10: =IF(D10="PENDIENTE",C10,0) -> 0
I11: =IF(D11="PENDIENTE",C11,0) -> 0
I12: =IF(D12="PENDIENTE",C12,0) -> 0
I13: =IF(D13="PENDIENTE",C13,0) -> 0
I14: =IF(D14="PENDIENTE",C14,0) -> 0
... I37: =IF(D37="PENDIENTE",C37,0) -> 0

Sheet CHICO JULIO
A1: FECHA | B1: REPUESTO | C1: PRECIO | D1: CONDICION | E1: FACTURA | F1: VENDEDOR | H1: FACTURA | I1: DEUDA | J1: TOTAL DEUDA
B2: SALDO | C2: 12000 | D2: PENDIENTE | F2: DELIS | H2: =IF(E:E="NO FACTURADO","PENDIENTE","AL DIA") -> AL DIA | I2: =IF(D2="PENDIENTE",C2,0) -> 12000 | J2: =SUM(I:I) -> 12000 | K2: MENU
I3: =IF(D3="PENDIENTE",C3,0) -> 0
I4: =IF(D4="PENDIENTE",C4,0) -> 0
I5: =IF(D5="PENDIENTE",C5,0) -> 0
I6: =IF(D6="PENDIENTE",C6,0) -> 0
I7: =IF(D7="PENDIENTE",C7,0) -> 0
I8: =IF(D8="PENDIENTE",C8,0) -> 0
I9: =IF(D9="PENDIENTE",C9,0) -> 0
I10: =IF(D10="PENDIENTE",C10,0) -> 0
I11: =IF(D11="PENDIENTE",C11,0) -> 0
I12: =IF(D12="PENDIENTE",C12,0) -> 0
I13: =IF(D13="PENDIENTE",C13,0) -> 0
I14: =IF(D14="PENDIENTE",C14,0) -> 0
... I37: =IF(D37="PENDIENTE",C37,0) -> 0

Sheet FELIPE AGUILAR (BULLA) LICAN
A1: FECHA | B1: REPUESTO | C1: PRECIO | D1: CONDICION | E1: FACTURA | F1: VENDEDOR | H1: FACTURA | I1: DEUDA | J1: TOTAL DEUDA
A2: 44638 | B2: AMPOLLETAS | C2: 3000 | D2: PAGADO | E2: no factura | F2: CESAR | H2: =IF(E:E="NO FACTURADO","PENDIENTE","AL DIA") -> AL DIA | I2: =IF(D2="PENDIENTE",C2,0) -> 0 | J2: =SUM(I:I) -> 0 | K2: MENU
A3: 44648 | B3: silicona | C3: 7000 | D3: PAGADO | E3: no factura | F3: CESAR | I3: =IF(D3="PENDIENTE",C3,0) -> 0
A4: 44665 | B4: AMPOLLETAS | C4: 4000 | D4: PAGADO | F4: CESAR | I4: =IF(D4="PENDIENTE",C4,0) -> 0
A5: 44704 | B5: MANTENCIAN KUN | C5: 98000 | D5: PAGADO | I5: =IF(D5="PENDIENTE",C5,0) -> 0
A6: 44711 | B6: amortiguadores trasero kun | C6: 100000 | D6: PAGADO | I6: =IF(D6="PENDIENTE",C6,0) -> 0
A7: 44750 | B7: kit embrague kun santa clara lican | C7: 458000 | D7: PAGADO | F7: CESAR | I7: =IF(D7="PENDIENTE",C7,0) -> 0
A8: 44665 | B8: bilomoide | C8: 4000 | D8: PAGADO | F8: omar | I8: =IF(D8="PENDIENTE",C8,0) -> 0
A9: 44764 | B9: FILTRO COMBUSTIBLE | C9: 10000 | D9: PAGADO | F9: CESAR | I9: =IF(D9="PENDIENTE",C9,0) -> 0
A10: 44767 | B10: aceite 75w90 gl5 3lts | C10: 43500 | D10: PAGADO | F10: CESAR | I10: =IF(D10="PENDIENTE",C10,0) -> 0
A11: 44795 | B11: ROTULA SUPERIOR | C11: 22000 | D11: PAGADO | F11: CESAR | I11: =IF(D11="PENDIENTE",C11,0) -> 0
A12: 44795 | B12: JGO PASTILLA FRENO | C12: 20000 | D12: PAGADO | F12: CESAR | I12: =IF(D12="PENDIENTE",C12,0) -> 0
A13: 44796 | B13: cilindro freno + bliquido freno | C13: 25000 | D13: PAGADO | F13: CESAR | I13: =IF(D13="PENDIENTE",C13,0) -> 0
A14: 44798 | B14: limpiador freno | C14: 12000 | D14: PAGADO | F14: CESAR | I14: =IF(D14="PENDIENTE",C14,0) -> 0
A15: 44809 | B15: silicona y ampolleta | C15: 7000 | D15: PAGADO | F15: CESAR | I15: =IF(D15="PENDIENTE",C15,0) -> 0
A16: 44826 | B16: RADIADOR CALEFA + FUELLE | C16: 72000 | D16: PAGADO | F16: CESAR | I16: =IF(D16="PENDIENTE",C16,0) -> 0
A17: 44854 | B17: cruceta + aceite 75w90 | C17: 53000 | D17: PAGADO | F17: CESAR | I17: =IF(D17="PENDIENTE",C17,0) -> 0
A18: 44874 | B18: cambio aceite 4n15 | C18: 150000 | D18: pAGADO | F18: CESAR | I18: =IF(D18="PENDIENTE",C18,0) -> 0
... A24: 45215 | B24: 75w90 gl5 3lts | C24: 40500 | D24: pAGADO | F24: CESAR | I24: =IF(D24="PENDIENTE",C24,0) -> 0
I25: =IF(D25="PENDIENTE",C25,0) -> 0
I26: =IF(D26="PENDIENTE",C26,0) -> 0
I27: =IF(D27="PENDIENTE",C27,0) -> 0
I28: =IF(D28="PENDIENTE",C28,0) -> 0
I29: =IF(D29="PENDIENTE",C29,0) -> 0
I30: =IF(D30="PENDIENTE",C30,0) -> 0
I31: =IF(D31="PENDIENTE",C31,0) -> 0
I32: =IF(D32="PENDIENTE",C32,0) -> 0
I33: =IF(D33="PENDIENTE",C33,0) -> 0
I34: =IF(D34="PENDIENTE",C34,0) -> 0
I35: =IF(D35="PENDIENTE",C35,0) -> 0
I36: =IF(D36="PENDIENTE",C36,0) -> 0

Sheet FUENTES HECTOR
A1: FECHA | B1: REPUESTO | C1: PRECIO | D1: CONDICION | E1: FACTURA | F1: VENDEDOR | H1: FACTURA | I1: DEUDA | J1: TOTAL DEUDA
H2: =IF(E:E="NO FACTURADO","PENDIENTE","AL DIA") -> AL DIA | I2: =IF(D2="PENDIENTE",C2,0) -> 0 | J2: =SUM(I:I) -> 0 | K2: MENU
A3: 44623 | B3: PRESUPUESTO Nº 4830 SOBRINO | C3: 592000 | D3: pagado | E3: facturado | F3: DELIS | I3: =IF(D3="PENDIENTE",C3,0) -> 0
I4: =IF(D4="PENDIENTE",C4,0) -> 0
I5: =IF(D5="PENDIENTE",C5,0) -> 0
I6: =IF(D6="PENDIENTE",C6,0) -> 0
I7: =IF(D7="PENDIENTE",C7,0) -> 0
I8: =IF(D8="PENDIENTE",C8,0) -> 0
I9: =IF(D9="PENDIENTE",C9,0) -> 0
I10: =IF(D10="PENDIENTE",C10,0) -> 0
I11: =IF(D11="PENDIENTE",C11,0) -> 0
I12: =IF(D12="PENDIENTE",C12,0) -> 0
I13: =IF(D13="PENDIENTE",C13,0) -> 0
I14: =IF(D14="PENDIENTE",C14,0) -> 0
I15: =IF(D15="PENDIENTE",C15,0) -> 0
... I37: =IF(D37="PENDIENTE",C37,0) -> 0

Sheet LOAIZA JOSE(FRANKE)
A1: FECHA | B1: REPUESTO | C1: PRECIO | D1: CONDICION | E1: FACTURA | F1: VENDEDOR | H1: FACTURA | I1: DEUDA | J1: TOTAL DEUDA
H2: =IF(E:E="NO FACTURADO","PENDIENTE","AL DIA") -> AL DIA | I2: =IF(D2="PENDIENTE",C2,0) -> 0 | J2: =SUM(I:I) -> 0 | K2: MENU
I3: =IF(D3="PENDIENTE",C3,0) -> 0
I4: =IF(D4="PENDIENTE",C4,0) -> 0
I5: =IF(D5="PENDIENTE",C5,0) -> 0
I6: =IF(D6="PENDIENTE",C6,0) -> 0
I7: =IF(D7="PENDIENTE",C7,0) -> 0
I8: =IF(D8="PENDIENTE",C8,0) -> 0
I9: =IF(D9="PENDIENTE",C9,0) -> 0
I10: =IF(D10="PENDIENTE",C10,0) -> 0
I11: =IF(D11="PENDIENTE",C11,0) -> 0
I12: =IF(D12="PENDIENTE",C12,0) -> 0
I13: =IF(D13="PENDIENTE",C13,0) -> 0
I14: =IF(D14="PENDIENTE",C14,0) -> 0
... I37: =IF(D37="PENDIENTE",C37,0) -> 0

Sheet LORCA EMERSON
A1: FECHA | B1: REPUESTO | C1: PRECIO | D1: CONDICION | E1: FACTURA | F1: VENDEDOR | H1: FACTURA | I1: DEUDA | J1: TOTAL DEUDA
A2: 44384 | C2: 42000 | D2: PENDIENTE | H2: =IF(E:E="NO FACTURADO","PENDIENTE","AL DIA") -> AL DIA | I2: =IF(D2="PENDIENTE",C2,0) -> 42000 | J2: =SUM(I:I) -> 56000 | K2: MENU
A3: 44545 | B3: mas 14000 del 15/12 | C3: 14000 | D3: PENDIENTE | I3: =IF(D3="PENDIENTE",C3,0) -> 14000
I4: =IF(D4="PENDIENTE",C4,0) -> 0
I5: =IF(D5="PENDIENTE",C5,0) -> 0
I6: =IF(D6="PENDIENTE",C6,0) -> 0
I7: =IF(D7="PENDIENTE",C7,0) -> 0
I8: =IF(D8="PENDIENTE",C8,0) -> 0
I9: =IF(D9="PENDIENTE",C9,0) -> 0
I10: =IF(D10="PENDIENTE",C10,0) -> 0
I11: =IF(D11="PENDIENTE",C11,0) -> 0
I12: =IF(D12="PENDIENTE",C12,0) -> 0
I13: =IF(D13="PENDIENTE",C13,0) -> 0
I14: =IF(D14="PENDIENTE",C14,0) -> 0
I15: =IF(D15="PENDIENTE",C15,0) -> 0
... I37: =IF(D37="PENDIENTE",C37,0) -> 0

Sheet PUSCHEL PABLO
A1: FECHA | B1: REPUESTO | C1: PRECIO | D1: CONDICION | E1: FACTURA | F1: VENDEDOR | H1: FACTURA | I1: DEUDA | J1: TOTAL DEUDA
A2: 44665 | B2: SALDO AJUSTE L200 | C2: 50000 | D2: PAGADO | F2: CESAR | H2: =IF(E:E="NO FACTURADO","PENDIENTE","AL DIA") -> AL DIA | I2: =IF(D2="PENDIENTE",C2,0) -> 0 | J2: =SUM(I:I) -> 0 | K2: MENU
I3: =IF(D3="PENDIENTE",C3,0) -> 0
I4: =IF(D4="PENDIENTE",C4,0) -> 0
I5: =IF(D5="PENDIENTE",C5,0) -> 0
I6: =IF(D6="PENDIENTE",C6,0) -> 0
I7: =IF(D7="PENDIENTE",C7,0) -> 0
I8: =IF(D8="PENDIENTE",C8,0) -> 0
I9: =IF(D9="PENDIENTE",C9,0) -> 0
I10: =IF(D10="PENDIENTE",C10,0) -> 0
I11: =IF(D11="PENDIENTE",C11,0) -> 0
I12: =IF(D12="PENDIENTE",C12,0) -> 0
I13: =IF(D13="PENDIENTE",C13,0) -> 0
I14: =IF(D14="PENDIENTE",C14,0) -> 0
... I37: =IF(D37="PENDIENTE",C37,0) -> 0

Sheet HENRIQUES JORGE (HUEVO)
A1: FECHA | B1: REPUESTO | C1: PRECIO | D1: CONDICION | E1: FACTURA | F1: VENDEDOR | H1: FACTURA | I1: DEUDA | J1: TOTAL DEUDA
A2: 44349 | B2: abono 50000 14/09 abono $10000 14/12/2022 | C2: 10000 | D2: pagado | H2: =IF(E:E="NO FACTURADO","PENDIENTE","AL DIA") -> AL DIA | I2: =IF(D2="PENDIENTE",C2,0) -> 0 | J2: =SUM(I:I) -> 12000 | K2: MENU
A3: 45524 | B3: amortiguador portalon h1 | C3: 13000 | D3: pagado | I3: =IF(D3="PENDIENTE",C3,0) -> 0
A4: 44430 | B4: saldo suspension h1 | C4: 12000 | D4: pendiente | I4: =IF(D4="PENDIENTE",C4,0) -> 12000 | L4: abono huevo 29/08/2024 $8000+8000 03/08
I5: =IF(D5="PENDIENTE",C5,0) -> 0
I6: =IF(D6="PENDIENTE",C6,0) -> 0
I7: =IF(D7="PENDIENTE",C7,0) -> 0
I8: =IF(D8="PENDIENTE",C8,0) -> 0
I9: =IF(D9="PENDIENTE",C9,0) -> 0
I10: =IF(D10="PENDIENTE",C10,0) -> 0
I11: =IF(D11="PENDIENTE",C11,0) -> 0
I12: =IF(D12="PENDIENTE",C12,0) -> 0
I13: =IF(D13="PENDIENTE",C13,0) -> 0
I14: =IF(D14="PENDIENTE",C14,0) -> 0
I15: =IF(D15="PENDIENTE",C15,0) -> 0
I16: =IF(D16="PENDIENTE",C16,0) -> 0
... I37: =IF(D37="PENDIENTE",C37,0) -> 0

Sheet ROA MANUEL
A1: FECHA | B1: REPUESTO | C1: PRECIO | D1: CONDICION | E1: FACTURA | F1: VENDEDOR | H1: FACTURA | I1: DEUDA | J1: TOTAL DEUDA
A2: 44358 | B2: CIL EMBR | C2: 67000 | D2: PENDIENTE | H2: =IF(E:E="NO FACTURADO","PENDIENTE","AL DIA") -> AL DIA | I2: =IF(D2="PENDIENTE",C2,0) -> 67000 | J2: =SUM(I:I) -> 356000 | K2: MENU
A3: 44359 | B3: ACEITE | C3: 24000 | D3: PENDIENTE | I3: =IF(D3="PENDIENTE",C3,0) -> 24000
B4: amortigua. Artiz | C4: 180000 | D4: PENDIENTE | I4: =IF(D4="PENDIENTE",C4,0) -> 180000
A5: 44373 | B5: RODAM | C5: 70000 | D5: PENDIENTE | I5: =IF(D5="PENDIENTE",C5,0) -> 70000
B6: pastillas | C6: 15000 | D6: PENDIENTE | I6: =IF(D6="PENDIENTE",C6,0) -> 15000
I7: =IF(D7="PENDIENTE",C7,0) -> 0
I8: =IF(D8="PENDIENTE",C8,0) -> 0
I9: =IF(D9="PENDIENTE",C9,0) -> 0
I10: =IF(D10="PENDIENTE",C10,0) -> 0
I11: =IF(D11="PENDIENTE",C11,0) -> 0
I12: =IF(D12="PENDIENTE",C12,0) -> 0
I13: =IF(D13="PENDIENTE",C13,0) -> 0
I14: =IF(D14="PENDIENTE",C14,0) -> 0
I15: =IF(D15="PENDIENTE",C15,0) -> 0
I16: =IF(D16="PENDIENTE",C16,0) -> 0
I17: =IF(D17="PENDIENTE",C17,0) -> 0
I18: =IF(D18="PENDIENTE",C18,0) -> 0
... I37: =IF(D37="PENDIENTE",C37,0) -> 0

Sheet BAHAMONDEZ JORGE
A1: FECHA | B1: REPUESTO | C1: PRECIO | D1: CONDICION | E1: FACTURA | F1: VENDEDOR | H1: FACTURA | I1: DEUDA | J1: TOTAL DEUDA
H2: =IF(E:E="NO FACTURADO","PENDIENTE","AL DIA") -> AL DIA | I2: =IF(D2="PENDIENTE",C2,0) -> 0 | J2: =SUM(I:I) -> 0 | K2: MENU
I3: =IF(D3="PENDIENTE",C3,0) -> 0
I4: =IF(D4="PENDIENTE",C4,0) -> 0
I5: =IF(D5="PENDIENTE",C5,0) -> 0
I6: =IF(D6="PENDIENTE",C6,0) -> 0
I7: =IF(D7="PENDIENTE",C7,0) -> 0
I8: =IF(D8="PENDIENTE",C8,0) -> 0
I9: =IF(D9="PENDIENTE",C9,0) -> 0
I10: =IF(D10="PENDIENTE",C10,0) -> 0
I11: =IF(D11="PENDIENTE",C11,0) -> 0
I12: =IF(D12="PENDIENTE",C12,0) -> 0
I13: =IF(D13="PENDIENTE",C13,0) -> 0
I14: =IF(D14="PENDIENTE",C14,0) -> 0
... I37: =IF(D37="PENDIENTE",C37,0) -> 0

Sheet VELASQUEZ MECANICO
A1: FECHA | B1: REPUESTO | C1: PRECIO | D1: CONDICION | E1: FACTURA | F1: VENDEDOR | H1: FACTURA | I1: DEUDA | J1: TOTAL DEUDA
H2: =IF(E:E="NO FACTURADO","PENDIENTE","AL DIA") -> AL DIA | I2: =IF(D2="PENDIENTE",C2,0) -> 0 | J2: =SUM(I:I) -> 0 | K2: MENU
I3: =IF(D3="PENDIENTE",C3,0) -> 0
I4: =IF(D4="PENDIENTE",C4,0) -> 0
I5: =IF(D5="PENDIENTE",C5,0) -> 0
I6: =IF(D6="PENDIENTE",C6,0) -> 0
I7: =IF(D7="PENDIENTE",C7,0) -> 0
I8: =IF(D8="PENDIENTE",C8,0) -> 0
I9: =IF(D9="PENDIENTE",C9,0) -> 0
I10: =IF(D10="PENDIENTE",C10,0) -> 0
I11: =IF(D11="PENDIENTE",C11,0) -> 0
I12: =IF(D12="PENDIENTE",C12,0) -> 0
I13: =IF(D13="PENDIENTE",C13,0) -> 0
I14: =IF(D14="PENDIENTE",C14,0) -> 0
... I37: =IF(D37="PENDIENTE",C37,0) -> 0

Sheet CONTRERAS SEBASTIAN (PAREJAJUST
A1: FECHA | B1: REPUESTO | C1: PRECIO | D1: CONDICION | E1: FACTURA | F1: VENDEDOR | H1: FACTURA | I1: DEUDA | J1: TOTAL DEUDA
A2: 44572 | B2: RODAMIENTO MAZA TERCEL | C2: 14000 | D2: pagado | E2: NO | F2: CESAR | H2: =IF(E:E="NO FACTURADO","PENDIENTE","AL DIA") -> AL DIA | I2: =IF(D2="PENDIENTE",C2,0) -> 0 | J2: =SUM(I:I) -> 38000 | K2: MENU
A3: 44596 | B3: accent 2005 hermana | C3: 14000 | D3: pagado | E3: no | F3: omar | I3: =IF(D3="PENDIENTE",C3,0) -> 0
A4: 44601 | B4: bateria 55 | C4: 40000 | D4: PAGADO | F4: delis | I4: =IF(D4="PENDIENTE",C4,0) -> 0
A5: 44606 | B5: PRESUPUESTO Nº4922 (LUV) | C5: 77500 | D5: pagado | E5: NO | F5: omar | I5: =IF(D5="PENDIENTE",C5,0) -> 0
A6: 44629 | B6: saldo pistola | C6: 40000 | D6: PAGADO | E6: NO | F6: delis | I6: =IF(D6="PENDIENTE",C6,0) -> 0
A7: 44677 | B7: metales towner | C7: 30000 | D7: PAGADO | E7: no | F7: omar | I7: =IF(D7="PENDIENTE",C7,0) -> 0
A8: 44704 | B8: CABLES BUJIAS ACCENT | C8: 15000 | D8: PAGADO | F8: CESAR | I8: =IF(D8="PENDIENTE",C8,0) -> 0
C9: 3000 | D9: PAGADO | I9: =IF(D9="PENDIENTE",C9,0) -> 0
A10: 44756 | B10: filtro aire y bujias baleno | C10: 15000 | D10: PAGADO | F10: omar | I10: =IF(D10="PENDIENTE",C10,0) -> 0
A11: 44776 | B11: Bandeja + rotula tercel 1998 | C11: 39000 | D11: PAGADO | F11: omar | I11: =IF(D11="PENDIENTE",C11,0) -> 0
A12: 44869 | B12: BATERIA 55AMPERES BEST Y CORREA TERCEL | C12: 63000 | D12: PAGADO | F12: omar | I12: =IF(D12="PENDIENTE",C12,0) -> 0
A13: 44875 | B13: poncho valvula baleno (16.000 ABONO 7.000) | C13: 7000 | D13: PAGADO | F13: omar | I13: =IF(D13="PENDIENTE",C13,0) -> 0 | L13: abono $20000 | M13: 45117
A14: 44893 | B14: aceite 10w40 + filtro | C14: 18000 | D14: pagado | F14: omar | I14: =IF(D14="PENDIENTE",C14,0) -> 0
A15: 44932 | B15: CORREA DMAX B39 | C15: 6000 | D15: pagado | F15: CESAR | I15: =IF(D15="PENDIENTE",C15,0) -> 0
A16: 44932 | B16: JUEGO BIELETAS DMAX BHORKE | C16: 30000 | D16: pagado | F16: CESAR | I16: =IF(D16="PENDIENTE",C16,0) -> 0
A17: 44938 | B17: JUEGO AMORTIGUADOR | C17: 38000 | D17: PENDIENTE | F17: CESAR | I17: =IF(D17="PENDIENTE",C17,0) -> 38000
I18: =IF(D18="PENDIENTE",C18,0) -> 0
I19: =IF(D19="PENDIENTE",C19,0) -> 0
I20: =IF(D20="PENDIENTE",C20,0) -> 0
I21: =IF(D21="PENDIENTE",C21,0) -> 0
I22: =IF(D22="PENDIENTE",C22,0) -> 0
I23: =IF(D23="PENDIENTE",C23,0) -> 0
I24: =IF(D24="PENDIENTE",C24,0) -> 0
I25: =IF(D25="PENDIENTE",C25,0) -> 0
I26: =IF(D26="PENDIENTE",C26,0) -> 0
I27: =IF(D27="PENDIENTE",C27,0) -> 0
I28: =IF(D28="PENDIENTE",C28,0) -> 0
I29: =IF(D29="PENDIENTE",C29,0) -> 0
... I37: =IF(D37="PENDIENTE",C37,0) -> 0

Sheet CARRASCO PEDRO (ZORRO)
A1: FECHA | B1: REPUESTO | C1: PRECIO | D1: CONDICION | E1: FACTURA | F1: VENDEDOR | H1: FACTURA | I1: DEUDA | J1: TOTAL DEUDA
A2: 44408 | C2: 14000 | D2: pagado | H2: =IF(E:E="NO FACTURADO","PENDIENTE","AL DIA") -> AL DIA | I2: =IF(D2="PENDIENTE",C2,0) -> 0 | J2: =SUM(I:I) -> 28000 | K2: MENU
A3: 44620 | B3: AROMATIZANTE PASTILLA | C3: 15000 | D3: pagado | I3: =IF(D3="PENDIENTE",C3,0) -> 0
A4: 44830 | B4: shampo con cera | C4: 9000 | D4: pagado | F4: cesar | I4: =IF(D4="PENDIENTE",C4,0) -> 0
A5: 45042 | B5: SALDO 5W/30 | C5: 30000 | D5: pagado | F5: DELIS | I5: =IF(D5="PENDIENTE",C5,0) -> 0
A6: 45086 | B6: disco freno | C6: 40000 | D6: pagado | F6: DELIS | I6: =IF(D6="PENDIENTE",C6,0) -> 0
A7: 45267 | B7: KIT DISTRIBUCION BBA AGUA SALDO | C7: 50000 | D7: pagado | F7: CESAR | I7: =IF(D7="PENDIENTE",C7,0) -> 0
A8: 45526 | B8: SALDO 5W/30 | C8: 28000 | D8: pendiente | F8: cesar | I8: =IF(D8="PENDIENTE",C8,0) -> 28000
I9: =IF(D9="PENDIENTE",C9,0) -> 0
I10: =IF(D10="PENDIENTE",C10,0) -> 0
I11: =IF(D11="PENDIENTE",C11,0) -> 0
I12: =IF(D12="PENDIENTE",C12,0) -> 0
I13: =IF(D13="PENDIENTE",C13,0) -> 0
I14: =IF(D14="PENDIENTE",C14,0) -> 0
I15: =IF(D15="PENDIENTE",C15,0) -> 0
I16: =IF(D16="PENDIENTE",C16,0) -> 0
I17: =IF(D17="PENDIENTE",C17,0) -> 0
I18: =IF(D18="PENDIENTE",C18,0) -> 0
I19: =IF(D19="PENDIENTE",C19,0) -> 0
I20: =IF(D20="PENDIENTE",C20,0) -> 0
... I37: =IF(D37="PENDIENTE",C37,0) -> 0

Sheet TIO CHINO LESPAI
A1: FECHA | B1: REPUESTO | C1: PRECIO | D1: CONDICION | E1: FACTURA | F1: VENDEDOR | H1: FACTURA | I1: DEUDA | J1: TOTAL DEUDA
A2: 44578 | B2: PARACHOQUE DELANTERO LUV | C2: 0 | D2: PENDIENTE | E2: NOP | F2: DELIS | H2: =IF(E:E="NO FACTURADO","PENDIENTE","AL DIA") -> AL DIA | I2: =IF(D2="PENDIENTE",C2,0) -> 0 | J2: 0 | K2: MENU | L2: abono 20000 | M2: 44634
A3: 44657 | B3: BATERIA SALDO | C3: 15000 | D3: pagado | E3: NOP | F3: DELIS | I3: =IF(D3="PENDIENTE",C3,0) -> 0
A4: 45033 | B4: SALDO FOCO | C4: 6000 | D4: pagado | F4: DELIS | I4: =IF(D4="PENDIENTE",C4,0) -> 0
A5: 45090 | B5: BOMBA CEBADORA | C5: 25000 | D5: pagado | I5: =IF(D5="PENDIENTE",C5,0) -> 0
A6: 45090 | B6: JGO BUJIAS | C6: 24000 | D6: pagado | I6: =IF(D6="PENDIENTE",C6,0) -> 0 | L6: ABONO $60000 | M6: 45091
A7: 45090 | B7: CILINDRO FRENO | C7: 25000 | D7: pagado | I7: =IF(D7="PENDIENTE",C7,0) -> 0
A8: 45090 | B8: LIQUIDO FRENO | C8: 4500 | D8: pagado | I8: =IF(D8="PENDIENTE",C8,0) -> 0
A9: 45090 | B9: MANILLA PUERTA RH | C9: 5000 | D9: pagado | I9: =IF(D9="PENDIENTE",C9,0) -> 0
A10: 45252 | B10: RODAMIENTO Y HORQUILLA EMBRAGUE YD25 MACACO | C10: 35000 | D10: pagado | I10: =IF(D10="PENDIENTE",C10,0) -> 0
I11: =IF(D11="PENDIENTE",C11,0) -> 0
I12: =IF(D12="PENDIENTE",C12,0) -> 0
I13: =IF(D13="PENDIENTE",C13,0) -> 0
I14: =IF(D14="PENDIENTE",C14,0) -> 0
I15: =IF(D15="PENDIENTE",C15,0) -> 0
I16: =IF(D16="PENDIENTE",C16,0) -> 0
I17: =IF(D17="PENDIENTE",C17,0) -> 0
I18: =IF(D18="PENDIENTE",C18,0) -> 0
I19: =IF(D19="PENDIENTE",C19,0) -> 0
I20: =IF(D20="PENDIENTE",C20,0) -> 0
I21: =IF(D21="PENDIENTE",C21,0) -> 0
I22: =IF(D22="PENDIENTE",C22,0) -> 0
... I37: =IF(D37="PENDIENTE",C37,0) -> 0

Sheet BAHAMONDEZ MARCO (SUBOFICIAL)
A1: FECHA | B1: REPUESTO | C1: PRECIO | D1: CONDICION | E1: FACTURA | F1: VENDEDOR | H1: FACTURA | I1: DEUDA | J1: TOTAL DEUDA
A2: 44558 | B2: ACEITE BUJIAS EMP. | C2: 43000 | D2: PAGADO | H2: =IF(E:E="NO FACTURADO","PENDIENTE","AL DIA") -> AL DIA | I2: =IF(D2="PENDIENTE",C2,0) -> 0 | J2: =SUM(I:I) -> 201500 | K2: MENU
A3: 44558 | B3: cable bujia roedores sensor T limpiainyectores | C3: 20900 | D3: PAGADO | I3: =IF(D3="PENDIENTE",C3,0) -> 0
A4: 44558 | B4: hijo | C4: 115000 | D4: PAGADO | I4: =IF(D4="PENDIENTE",C4,0) -> 0
A5: 44589 | B5: BATERIA 55 AMP ROCKET | C5: 60000 | D5: PAGADO | E5: NO | F5: OMAR | I5: =IF(D5="PENDIENTE",C5,0) -> 0
A6: 44656 | B6: PRESUPUESTO Nº5104 | C6: 30800 | D6: PAGADO | I6: =IF(D6="PENDIENTE",C6,0) -> 0
A7: 44663 | B7: REPUESTOS SAIL BIELETA CAZOLETA TERMINALES | C7: 7800 | D7: PAGADO | I7: =IF(D7="PENDIENTE",C7,0) -> 0
A8: 44818 | B8: gotita afinamiento luv 2,2 shell | C8: 19000 | D8: PAGADO | F8: delis | I8: =IF(D8="PENDIENTE",C8,0) -> 0 | K8: ABONO $50000 22/02/2023
A9: 44818 | B9: pino aromatico | C9: 1000 | D9: PAGADO | F9: delis | I9: =IF(D9="PENDIENTE",C9,0) -> 0
A10: 44851 | B10: kit embrague sail | C10: 40000 | D10: PAGADO | F10: cesar | I10: =IF(D10="PENDIENTE",C10,0) -> 0 | K10: ABONO $50000 06/06/2023
A11: 44872 | B11: BATERIA CUÑADO | C11: 50000 | D11: pagado | F11: delis | I11: =IF(D11="PENDIENTE",C11,0) -> 0 | K11: abono 50000 22/02/2023
A12: 45096 | B12: BULBO FRENO SAIL | C12: 7500 | D12: pagado | F12: delis | I12: =IF(D12="PENDIENTE",C12,0) -> 0
A13: 45237 | B13: BANDEJA 2RODAMIENTO | C13: 13000 | D13: pagado | F13: delis | I13: =IF(D13="PENDIENTE",C13,0) -> 0 | K13: abono $34000 21/12/2023
A14: 45260 | B14: FLOTADOR LUV | C14: 25000 | D14: PAGADO | F14: delis | I14: =IF(D14="PENDIENTE",C14,0) -> 0
A15: 45261 | B15: BATERIA 90 AMP | C15: 70000 | D15: pendiente | E15: $50.000 | I15: =IF(D15="PENDIENTE",C15,0) -> 70000
A16: 44934 | B16: AMORTIGUADORES QUASQUAI | C16: 50000 | D16: pendiente | E16: $100,000 | I16: =IF(D16="PENDIENTE",C16,0) -> 50000 | K16: ABONO 50000 19/04/2024
A17: 44934 | B17: BIELETA QUASQUAI | C17: 4500 | D17: pendiente | I17: =IF(D17="PENDIENTE",C17,0) -> 4500
A18: 44934 | B18: CAZOLETA QUASQUAI | C18: 6000 | D18: PAGADO | E18: $56,000 | I18: =IF(D18="PENDIENTE",C18,0) -> 0 | K18: abono $50,000 09/04/2024
B19: TERMINAL DIRECCION | C19: 44000 | D19: pendiente | I19: =IF(D19="PENDIENTE",C19,0) -> 44000 | K19: abono $50000 26/06/2024
A20: 45481 | B20: afinamiento sail | C20: 33000 | D20: pendiente | I20: =IF(D20="PENDIENTE",C20,0) -> 33000 | K20: ABONO $50000 2/10/2024
I21: =IF(D21="PENDIENTE",C21,0) -> 0
I22: =IF(D22="PENDIENTE",C22,0) -> 0
I23: =IF(D23="PENDIENTE",C23,0) -> 0
I24: =IF(D24="PENDIENTE",C24,0) -> 0
I25: =IF(D25="PENDIENTE",C25,0) -> 0
I26: =IF(D26="PENDIENTE",C26,0) -> 0
I27: =IF(D27="PENDIENTE",C27,0) -> 0
I28: =IF(D28="PENDIENTE",C28,0) -> 0
I29: =IF(D29="PENDIENTE",C29,0) -> 0
I30: =IF(D30="PENDIENTE",C30,0) -> 0
I31: =IF(D31="PENDIENTE",C31,0) -> 0
I32: =IF(D32="PENDIENTE",C32,0) -> 0
... I36: =IF(D36="PENDIENTE",C36,0) -> 0

Sheet PINUER OMAR
A1: FECHA | B1: REPUESTO | C1: PRECIO | D1: CONDICION | E1: FACTURA | F1: VENDEDOR | H1: FACTURA | I1: DEUDA | J1: TOTAL DEUDA
A2: 44617 | B2: galon aceite 15w40 | C2: 20000 | D2: pendiente | E2: no | F2: omar | H2: =IF(E:E="NO FACTURADO","PENDIENTE","AL DIA") -> AL DIA | I2: =IF(D2="PENDIENTE",C2,0) -> 20000 | J2: =SUM(I:I) -> 126000 | K2: MENU
B3: AFINAMIENTO JGO EMP | C3: 94000 | D3: pendiente | F3: CESAR | I3: =IF(D3="PENDIENTE",C3,0) -> 94000
A4: 44641 | B4: FILTRO AIRE | C4: 12000 | D4: pendiente | F4: CESAR | I4: =IF(D4="PENDIENTE",C4,0) -> 12000
I5: =IF(D5="PENDIENTE",C5,0) -> 0
I6: =IF(D6="PENDIENTE",C6,0) -> 0
I7: =IF(D7="PENDIENTE",C7,0) -> 0
I8: =IF(D8="PENDIENTE",C8,0) -> 0
I9: =IF(D9="PENDIENTE",C9,0) -> 0
I10: =IF(D10="PENDIENTE",C10,0) -> 0
I11: =IF(D11="PENDIENTE",C11,0) -> 0
I12: =IF(D12="PENDIENTE",C12,0) -> 0
I13: =IF(D13="PENDIENTE",C13,0) -> 0
I14: =IF(D14="PENDIENTE",C14,0) -> 0
I15: =IF(D15="PENDIENTE",C15,0) -> 0
I16: =IF(D16="PENDIENTE",C16,0) -> 0
... I37: =IF(D37="PENDIENTE",C37,0) -> 0

Sheet HERNANDEZ HECTOR (FALABELLA)
A1: FECHA | B1: REPUESTO | C1: PRECIO | D1: CONDICION | E1: FACTURA | F1: VENDEDOR | H1: FACTURA | I1: DEUDA | J1: TOTAL DEUDA
H2: =IF(E:E="NO FACTURADO","PENDIENTE","AL DIA") -> AL DIA | I2: =IF(D2="PENDIENTE",C2,0) -> 0 | J2: =SUM(I:I) -> 0 | K2: MENU
I3: =IF(D3="PENDIENTE",C3,0) -> 0
I4: =IF(D4="PENDIENTE",C4,0) -> 0
I5: =IF(D5="PENDIENTE",C5,0) -> 0
I6: =IF(D6="PENDIENTE",C6,0) -> 0
I7: =IF(D7="PENDIENTE",C7,0) -> 0
I8: =IF(D8="PENDIENTE",C8,0) -> 0
I9: =IF(D9="PENDIENTE",C9,0) -> 0
I10: =IF(D10="PENDIENTE",C10,0) -> 0
I11: =IF(D11="PENDIENTE",C11,0) -> 0
I12: =IF(D12="PENDIENTE",C12,0) -> 0
I13: =IF(D13="PENDIENTE",C13,0) -> 0
I14: =IF(D14="PENDIENTE",C14,0) -> 0
... I37: =IF(D37="PENDIENTE",C37,0) -> 0

Sheet BARRIA MIGUEL
A1: FECHA | B1: REPUESTO | C1: PRECIO | D1: CONDICION | E1: FACTURA | F1: VENDEDOR | H1: FACTURA | I1: DEUDA | J1: TOTAL DEUDA
A2: 44575 | B2: BOBINA | C2: 18500 | D2: pagado | F2: DELIS | H2: =IF(E:E="NO FACTURADO","PENDIENTE","AL DIA") -> AL DIA | I2: =IF(D2="PENDIENTE",C2,0) -> 0 | J2: =SUM(I:I) -> 3000 | K2: MENU
A3: 44581 | B3: BOMBA BENCINA CARRY | C3: 18000 | D3: pagado | F3: DELIS | I3: =IF(D3="PENDIENTE",C3,0) -> 0
A4: 44589 | B4: JGO ROTULAS DMAX | C4: 70000 | D4: pagado | F4: CESAR | I4: =IF(D4="PENDIENTE",C4,0) -> 0
A5: 44599 | B5: JGO AMORTIGUADORES DELANTEROS | C5: 40000 | D5: pagado | F5: DELIS | I5: =IF(D5="PENDIENTE",C5,0) -> 0
A6: 11 02 2022 | B6: amortiguadores | C6: 130000 | D6: pagado | F6: delis | I6: =IF(D6="PENDIENTE",C6,0) -> 0
A7: 44861 | B7: saldo disco y pastilla | C7: 3000 | D7: pendiente | F7: DELIS | I7: =IF(D7="PENDIENTE",C7,0) -> 3000
I8: =IF(D8="PENDIENTE",C8,0) -> 0
I9: =IF(D9="PENDIENTE",C9,0) -> 0
I10: =IF(D10="PENDIENTE",C10,0) -> 0
I11: =IF(D11="PENDIENTE",C11,0) -> 0
I12: =IF(D12="PENDIENTE",C12,0) -> 0
I13: =IF(D13="PENDIENTE",C13,0) -> 0
I14: =IF(D14="PENDIENTE",C14,0) -> 0
I15: =IF(D15="PENDIENTE",C15,0) -> 0
I16: =IF(D16="PENDIENTE",C16,0) -> 0
I17: =IF(D17="PENDIENTE",C17,0) -> 0
I18: =IF(D18="PENDIENTE",C18,0) -> 0
I19: =IF(D19="PENDIENTE",C19,0) -> 0
... I37: =IF(D37="PENDIENTE",C37,0) -> 0

Sheet ROBLES LUIS
A1: FECHA | B1: REPUESTO | C1: PRECIO | D1: CONDICION | E1: FACTURA | F1: VENDEDOR | H1: FACTURA | I1: DEUDA | J1: TOTAL DEUDA
A2: 44536 | B2: SALDO BOMBA DIRECCION | C2: 0 | D2: COBRADO | E2: NO | H2: =IF(E:E="NO FACTURADO","PENDIENTE","AL DIA") -> AL DIA | I2: =IF(D2="PENDIENTE",C2,0) -> 0 | J2: =SUM(I:I) -> 0 | K2: MENU
A3: 44676 | B3: A FAVOR | C3: 61000 | I3: =IF(D3="PENDIENTE",C3,0) -> 0
B4: a favor | C4: 41000 | I4: =IF(D4="PENDIENTE",C4,0) -> 0
B5: a favor | C5: 23000 | E5: no | I5: =IF(D5="PENDIENTE",C5,0) -> 0 | K5: 44859
I6: =IF(D6="PENDIENTE",C6,0) -> 0
I7: =IF(D7="PENDIENTE",C7,0) -> 0
I8: =IF(D8="PENDIENTE",C8,0) -> 0
I9: =IF(D9="PENDIENTE",C9,0) -> 0
I10: =IF(D10="PENDIENTE",C10,0) -> 0
I11: =IF(D11="PENDIENTE",C11,0) -> 0
I12: =IF(D12="PENDIENTE",C12,0) -> 0
I13: =IF(D13="PENDIENTE",C13,0) -> 0
I14: =IF(D14="PENDIENTE",C14,0) -> 0
I15: =IF(D15="PENDIENTE",C15,0) -> 0
I16: =IF(D16="PENDIENTE",C16,0) -> 0
I17: =IF(D17="PENDIENTE",C17,0) -> 0
... I37: =IF(D37="PENDIENTE",C37,0) -> 0

Sheet SOBARZO RODOLFO
A1: FECHA | B1: REPUESTO | C1: PRECIO | D1: CONDICION | E1: FACTURA | F1: VENDEDOR | H1: FACTURA | I1: DEUDA | J1: TOTAL DEUDA
A2: 44572 | B2: kit distribucion | C2: 17000 | D2: pagado | H2: =IF(E:E="NO FACTURADO","PENDIENTE","AL DIA") -> AL DIA | I2: =IF(D2="PENDIENTE",C2,0) -> 0 | J2: =SUM(I:I) -> 0 | K2: MENU
A3: 44614 | B3: JGO AXIALES | C3: 32000 | D3: pagado | E3: NO | F3: CESAR | I3: =IF(D3="PENDIENTE",C3,0) -> 0
A4: 44705 | B4: jgo bujia | C4: 20000 | D4: pagado | F4: cesar | I4: =IF(D4="PENDIENTE",C4,0) -> 0
A5: 44734 | B5: bateria 90 amperes | C5: 30000 | D5: pagado | F5: delis | I5: =IF(D5="PENDIENTE",C5,0) -> 0
A6: 44805 | B6: SALDO FOCO TRASERO HILUX | C6: 25000 | D6: pagado | F6: CESAR | I6: =IF(D6="PENDIENTE",C6,0) -> 0
A7: 44900 | B7: bujias incandescente (2) | C7: 14000 | D7: pagado | I7: =IF(D7="PENDIENTE",C7,0) -> 0
A8: 44914 | B8: saldo rotula | C8: 25000 | D8: pagado | F8: delis | I8: =IF(D8="PENDIENTE",C8,0) -> 0
A9: 44914 | B9: jugo patines | C9: 1500 | D9: pagado | I9: =IF(D9="PENDIENTE",C9,0) -> 0
A10: 45048 | B10: JGO BUJIAS | C10: 28000 | D10: pagado | F10: CESAR | I10: =IF(D10="PENDIENTE",C10,0) -> 0
A11: 45168 | B11: saldo kit distribucion | C11: 40000 | D11: pagado | I11: =IF(D11="PENDIENTE",C11,0) -> 0
A12: 45253 | B12: disco freno empaquetadura media | C12: 55000 | D12: pagado | F12: delis | I12: =IF(D12="PENDIENTE",C12,0) -> 0 | L12: abono $30000 01/12/2023 $25000 19/12/2023
A13: 45352 | B13: filtro aire h1 | C13: 10000 | D13: pagado | I13: =IF(D13="PENDIENTE",C13,0) -> 0
I14: =IF(D14="PENDIENTE",C14,0) -> 0
I15: =IF(D15="PENDIENTE",C15,0) -> 0
I16: =IF(D16="PENDIENTE",C16,0) -> 0
I17: =IF(D17="PENDIENTE",C17,0) -> 0
I18: =IF(D18="PENDIENTE",C18,0) -> 0
I19: =IF(D19="PENDIENTE",C19,0) -> 0
I20: =IF(D20="PENDIENTE",C20,0) -> 0
I21: =IF(D21="PENDIENTE",C21,0) -> 0
I22: =IF(D22="PENDIENTE",C22,0) -> 0
I23: =IF(D23="PENDIENTE",C23,0) -> 0
I24: =IF(D24="PENDIENTE",C24,0) -> 0
I25: =IF(D25="PENDIENTE",C25,0) -> 0
... I37: =IF(D37="PENDIENTE",C37,0) -> 0

Sheet AGUILAR HANZ
A1: FECHA | B1: REPUESTO | C1: PRECIO | D1: CONDICION | E1: FACTURA | F1: VENDEDOR | H1: FACTURA | I1: DEUDA | J1: TOTAL DEUDA
A2: 44552 | B2: SALDO V16 | C2: 0 | D2: PENDIENTE | E2: NO | H2: =IF(E:E="NO FACTURADO","PENDIENTE","AL DIA") -> AL DIA | I2: =IF(D2="PENDIENTE",C2,0) -> 0 | J2: =SUM(I:I) -> 189000 | K2: MENU
A3: 44860 | B3: saldo factura nº6898 | C3: 81000 | D3: PAGADO | I3: =IF(D3="PENDIENTE",C3,0) -> 0
A4: 44908 | B4: mazasa traseras | C4: 50000 | D4: PAGADO | F4: cesar | I4: =IF(D4="PENDIENTE",C4,0) -> 0
A5: 45027 | B5: PRESUPUESTO 5708 SALDO ABONO 100000 | C5: 170000 | D5: PENDIENTE | F5: cesar | I5: =IF(D5="PENDIENTE",C5,0) -> 170000 | L5: ABONO $100.000 14/05/2023
A6: 45051 | B6: PRESUPUESTO 5727 | C6: 19000 | D6: PENDIENTE | F6: cesar | I6: =IF(D6="PENDIENTE",C6,0) -> 19000 | L6: abono $30000 | M6: 45202
I7: =IF(D7="PENDIENTE",C7,0) -> 0
I8: =IF(D8="PENDIENTE",C8,0) -> 0
I9: =IF(D9="PENDIENTE",C9,0) -> 0
I10: =IF(D10="PENDIENTE",C10,0) -> 0
I11: =IF(D11="PENDIENTE",C11,0) -> 0
I12: =IF(D12="PENDIENTE",C12,0) -> 0
I13: =IF(D13="PENDIENTE",C13,0) -> 0
I14: =IF(D14="PENDIENTE",C14,0) -> 0
I15: =IF(D15="PENDIENTE",C15,0) -> 0
I16: =IF(D16="PENDIENTE",C16,0) -> 0
I17: =IF(D17="PENDIENTE",C17,0) -> 0
I18: =IF(D18="PENDIENTE",C18,0) -> 0
... I37: =IF(D37="PENDIENTE",C37,0) -> 0

Sheet VENEGAS EFRAIN BERNABE
A1: FECHA | B1: REPUESTO | C1: PRECIO | D1: CONDICION | E1: FACTURA | F1: VENDEDOR | H1: FACTURA | I1: DEUDA | J1: TOTAL DEUDA
B2: SALDO FILTRO MONTERO | C2: 9000 | D2: PAGADO | E2: NO | H2: =IF(E:E="NO FACTURADO","PENDIENTE","AL DIA") -> AL DIA | I2: =IF(D2="PENDIENTE",C2,0) -> 0 | J2: =SUM(I:I) -> 0 | K2: MENU
A3: 45644 | B3: rodamiento sacaperno | C3: 28000 | D3: PAGADO | I3: =IF(D3="PENDIENTE",C3,0) -> 0
I4: =IF(D4="PENDIENTE",C4,0) -> 0
I5: =IF(D5="PENDIENTE",C5,0) -> 0
I6: =IF(D6="PENDIENTE",C6,0) -> 0
I7: =IF(D7="PENDIENTE",C7,0) -> 0
I8: =IF(D8="PENDIENTE",C8,0) -> 0
I9: =IF(D9="PENDIENTE",C9,0) -> 0
I10: =IF(D10="PENDIENTE",C10,0) -> 0
I11: =IF(D11="PENDIENTE",C11,0) -> 0
I12: =IF(D12="PENDIENTE",C12,0) -> 0
I13: =IF(D13="PENDIENTE",C13,0) -> 0
I14: =IF(D14="PENDIENTE",C14,0) -> 0
I15: =IF(D15="PENDIENTE",C15,0) -> 0
... I37: =IF(D37="PENDIENTE",C37,0) -> 0

Sheet MONTES WALTER (LOCO EDY)
A1: FECHA | B1: REPUESTO | C1: PRECIO | D1: CONDICION | E1: FACTURA | F1: VENDEDOR | H1: FACTURA | I1: DEUDA | J1: TOTAL DEUDA
A2: 44558 | B2: AROMATIZANTE CUBREVOLANTE | C2: 10000 | D2: PENDIENTE | E2: NO | H2: =IF(E:E="NO FACTURADO","PENDIENTE","AL DIA") -> AL DIA | I2: =IF(D2="PENDIENTE",C2,0) -> 10000 | J2: =SUM(I:I) -> 159000 | K2: MENU
A3: 44571 | B3: INYECTORES LUV 2,2 | C3: 120000 | D3: PENDIENTE | E3: NO | I3: =IF(D3="PENDIENTE",C3,0) -> 120000
A4: 44776 | B4: INYECTORES LUV 2,2 | C4: 29000 | D4: PENDIENTE | I4: =IF(D4="PENDIENTE",C4,0) -> 29000
B5: ABONO $40.000 | I5: =IF(D5="PENDIENTE",C5,0) -> 0
B6: ABONO $30000 9/12/2023 | I6: =IF(D6="PENDIENTE",C6,0) -> 0
B7: abono $50000 19/04/2024 | I7: =IF(D7="PENDIENTE",C7,0) -> 0
I8: =IF(D8="PENDIENTE",C8,0) -> 0
I9: =IF(D9="PENDIENTE",C9,0) -> 0
I10: =IF(D10="PENDIENTE",C10,0) -> 0
I11: =IF(D11="PENDIENTE",C11,0) -> 0
I12: =IF(D12="PENDIENTE",C12,0) -> 0
I13: =IF(D13="PENDIENTE",C13,0) -> 0
I14: =IF(D14="PENDIENTE",C14,0) -> 0
I15: =IF(D15="PENDIENTE",C15,0) -> 0
I16: =IF(D16="PENDIENTE",C16,0) -> 0
I17: =IF(D17="PENDIENTE",C17,0) -> 0
I18: =IF(D18="PENDIENTE",C18,0) -> 0
I19: =IF(D19="PENDIENTE",C19,0) -> 0
... I37: =IF(D37="PENDIENTE",C37,0) -> 0

Sheet RICARDO 5L
A1: FECHA | B1: REPUESTO | C1: PRECIO | D1: CONDICION | E1: FACTURA | F1: VENDEDOR | H1: FACTURA | I1: DEUDA | J1: TOTAL DEUDA
A2: 44567 | B2: DIFERENCIA DEVOLUCION | C2: 50000 | D2: pagado | E2: SI | H2: =IF(E:E="NO FACTURADO","PENDIENTE","AL DIA") -> AL DIA | I2: =IF(E8="PENDIENTE",C2,0) -> 0 | J2: =SUM(I:I) -> 0 | K2: MENU
A3: 44573 | B3: RODAMIENTO CARDAN | C3: 47000 | D3: pagado | E3: SI | I3: =IF(D3="PENDIENTE",C3,0) -> 0
A4: 44623 | B4: rotula dmax terminal rost off | C4: 85000 | D4: pagado | E4: SI | I4: =IF(D4="PENDIENTE",C4,0) -> 0
I5: =IF(D5="PENDIENTE",C5,0) -> 0
I6: =IF(D6="PENDIENTE",C6,0) -> 0
I7: =IF(D7="PENDIENTE",C7,0) -> 0
I8: =IF(D8="PENDIENTE",C8,0) -> 0
I9: =IF(D9="PENDIENTE",C9,0) -> 0
I10: =IF(D10="PENDIENTE",C10,0) -> 0
I11: =IF(D11="PENDIENTE",C11,0) -> 0
I12: =IF(D12="PENDIENTE",C12,0) -> 0
I13: =IF(D13="PENDIENTE",C13,0) -> 0
I14: =IF(D14="PENDIENTE",C14,0) -> 0
I15: =IF(D15="PENDIENTE",C15,0) -> 0
I16: =IF(D16="PENDIENTE",C16,0) -> 0
... I37: =IF(D37="PENDIENTE",C37,0) -> 0

Sheet BELARMINO MONSALVE
A1: FECHA | B1: REPUESTO | C1: PRECIO | D1: CONDICION | E1: FACTURA | F1: VENDEDOR | H1: FACTURA | I1: DEUDA | J1: TOTAL DEUDA
A2: 44301 | B2: 8 BALANCIN 3 PERNOS REGULADOR BALANCIN | C2: 58000 | D2: pagado | E2: NO | F2: OMAR | H2: =IF(E:E="NO FACTURADO","PENDIENTE","AL DIA") -> AL DIA | I2: =IF(D2="PENDIENTE",C2,0) -> 0 | J2: =SUM(I:I) -> 0 | K2: MENU
A3: 44587 | B3: BOMBA H100 VALVULAS KIA | C3: 170000 | D3: pagado | E3: si | F3: DELIS | I3: =IF(D3="PENDIENTE",C3,0) -> 0
A4: 44592 | B4: metal biela yd25 | C4: 27500 | D4: pagado | E4: si | F4: DELIS | I4: =IF(D4="PENDIENTE",C4,0) -> 0
A5: 44735 | B5: bateria 35amp hijo | C5: 55000 | D5: pagado | F5: DELIS | I5: =IF(D5="PENDIENTE",C5,0) -> 0
I6: =IF(D6="PENDIENTE",C6,0) -> 0
I7: =IF(D7="PENDIENTE",C7,0) -> 0
I8: =IF(D8="PENDIENTE",C8,0) -> 0
I9: =IF(D9="PENDIENTE",C9,0) -> 0
I10: =IF(D10="PENDIENTE",C10,0) -> 0
I11: =IF(D11="PENDIENTE",C11,0) -> 0
I12: =IF(D12="PENDIENTE",C12,0) -> 0
I13: =IF(D13="PENDIENTE",C13,0) -> 0
I14: =IF(D14="PENDIENTE",C14,0) -> 0
I15: =IF(D15="PENDIENTE",C15,0) -> 0
I16: =IF(D16="PENDIENTE",C16,0) -> 0
I17: =IF(D17="PENDIENTE",C17,0) -> 0
... I37: =IF(D37="PENDIENTE",C37,0) -> 0

Sheet FUENTES LUIS
A1: FECHA | B1: REPUESTO | C1: PRECIO | D1: CONDICION | E1: FACTURA | F1: VENDEDOR | H1: FACTURA | I1: DEUDA | J1: TOTAL DEUDA
B2: SALDO | D2: PENDIENTE | E2: NO | F2: OMAR | H2: =IF(E:E="NO FACTURADO","PENDIENTE","AL DIA") -> AL DIA | I2: =IF(D2="PENDIENTE",C2,0) -> 0 | J2: =SUM(I:I) -> 0 | K2: MENU
I3: =IF(D3="PENDIENTE",C3,0) -> 0
A4: 44280 | C4: 55000 | D4: PAGADO | F4: CESAR | I4: =IF(D4="PENDIENTE",C4,0) -> 0
A5: 44305 | B5: SALDO ACEITE HUJO ALBERTO | C5: 8000 | D5: PAGADO | F5: DELIS | I5: =IF(D5="PENDIENTE",C5,0) -> 0
B6: PRESUPUESTO #4340 SALDO | C6: 36000 | D6: PAGADO | F6: CESAR | I6: =IF(D6="PENDIENTE",C6,0) -> 0
B7: SALDO OPTICO 6052 | C7: 5000 | D7: PAGADO | F7: CESAR | I7: =IF(D7="PENDIENTE",C7,0) -> 0
B8: RPTOS CARRY | C8: 100000 | D8: pagado | F8: CESAR | I8: =IF(D8="PENDIENTE",C8,0) -> 0
B9: JGO PICAROES | C9: 16000 | D9: pagado | F9: CESAR | I9: =IF(D9="PENDIENTE",C9,0) -> 0
B10: FAROL PATENTE | C10: 4500 | D10: pagado | F10: CESAR | I10: =IF(D10="PENDIENTE",C10,0) -> 0
B11: CINTA AISLADORA | C11: 2000 | D11: pagado | F11: CESAR | I11: =IF(D11="PENDIENTE",C11,0) -> 0
B12: SALDO SUSPENSION HILUX 2Y | C12: 10000 | D12: pagado | F12: CESAR | I12: =IF(D12="PENDIENTE",C12,0) -> 0
B13: rodamientos masa 2y | C13: 25000 | D13: pagado | F13: DELIS | I13: =IF(D13="PENDIENTE",C13,0) -> 0
A14: 44531 | B14: ACEITE Y FILTRO | C14: 21000 | D14: pagado | E14: NO | F14: CESAR | I14: =IF(D14="PENDIENTE",C14,0) -> 0
A15: 44678 | B15: bujias aceite | C15: 30000 | D15: PAGADO | F15: CESAR | I15: =IF(D15="PENDIENTE",C15,0) -> 0
A16: 45006 | B16: ACEITE Y FILTRO | C16: 30000 | D16: PAGADO | F16: DELIS | I16: =IF(D16="PENDIENTE",C16,0) -> 0
A17: 45147 | B17: SALDO BATERIA Y BUJIAS | C17: 16000 | D17: PAGADO | F17: DELIS | I17: =IF(D17="PENDIENTE",C17,0) -> 0 | L17: ABONO $14000 23/08/2023
B18: ACEITE Y FILTRO | C18: 27000 | D18: PAGADO | F18: DELIS | I18: =IF(D18="PENDIENTE",C18,0) -> 0
A19: 45322 | B19: ACEITE Y FILTRO SUPER | C19: 20000 | D19: PAGADO | I19: =IF(D19="PENDIENTE",C19,0) -> 0
A20: 45611 | B20: FAROL ESQUINA AMPOLLETA | C20: 23000 | D20: PAGADO | I20: =IF(D20="PENDIENTE",C20,0) -> 0
I21: =IF(D21="PENDIENTE",C21,0) -> 0
I22: =IF(D22="PENDIENTE",C22,0) -> 0
I23: =IF(D23="PENDIENTE",C23,0) -> 0
I24: =IF(D24="PENDIENTE",C24,0) -> 0
I25: =IF(D25="PENDIENTE",C25,0) -> 0
I26: =IF(D26="PENDIENTE",C26,0) -> 0
I27: =IF(D27="PENDIENTE",C27,0) -> 0
I28: =IF(D28="PENDIENTE",C28,0) -> 0
I29: =IF(D29="PENDIENTE",C29,0) -> 0
I30: =IF(D30="PENDIENTE",C30,0) -> 0
I31: =IF(D31="PENDIENTE",C31,0) -> 0
I32: =IF(D32="PENDIENTE",C32,0) -> 0
... I37: =IF(D37="PENDIENTE",C37,0) -> 0

Sheet RUIZ MIREYA
A1: FECHA | B1: REPUESTO | C1: PRECIO | D1: CONDICION | E1: FACTURA | F1: VENDEDOR | H1: FACTURA | I1: DEUDA | J1: TOTAL DEUDA
A2: 44286 | B2: SALDO BJAS AXIAL | C2: 39000 | D2: PAGADO | E2: NO | F2: OMAR | H2: =IF(E:E="NO FACTURADO","PENDIENTE","AL DIA") -> AL DIA | I2: =IF(D2="PENDIENTE",C2,0) -> 0 | J2: =SUM(I:I) -> 73000 | K2: MENU
A3: 44326 | B3: PARACHOQUE$35000 Y OPTICO $38000 | C3: 73000 | D3: PENDIENTE | E3: NO | F3: DELIS | I3: =IF(D3="PENDIENTE",C3,0) -> 73000
I4: 0
I5: =IF(D4="PENDIENTE",C4,0) -> 0
I6: =IF(D5="PENDIENTE",C5,0) -> 0
I7: =IF(D6="PENDIENTE",C6,0) -> 0
I8: =IF(D7="PENDIENTE",C7,0) -> 0
I9: =IF(D8="PENDIENTE",C8,0) -> 0
I10: =IF(D9="PENDIENTE",C9,0) -> 0
I11: =IF(D10="PENDIENTE",C10,0) -> 0
I12: =IF(D11="PENDIENTE",C11,0) -> 0
I13: =IF(D12="PENDIENTE",C12,0) -> 0
I14: =IF(D13="PENDIENTE",C13,0) -> 0
I15: =IF(D14="PENDIENTE",C14,0) -> 0
I16: =IF(D15="PENDIENTE",C15,0) -> 0
... I37: =IF(D36="PENDIENTE",C36,0) -> 0

Sheet VIDAL CARLOS (ESTACIONAMIENTO)
A1: FECHA | B1: REPUESTO | C1: PRECIO | D1: CONDICION | E1: FACTURA | F1: VENDEDOR | H1: FACTURA | I1: DEUDA | J1: TOTAL DEUDA
A2: 44295 | B2: BATERIA 90 AMP $108000 ABONO 22000 25/5 | C2: 6000 | D2: PAGADO | E2: NO | F2: OMAR | H2: =IF(E:E="NO FACTURADO","PENDIENTE","AL DIA") -> AL DIA | I2: =IF(D2="PENDIENTE",C2,0) -> 0 | J2: =SUM(I:I) -> 9500 | K2: MENU
B3: 1 L LIQUIDO DE FRENO | C3: 4000 | D3: PAGADO | E3: NO | F3: DELIS | I3: =IF(D3="PENDIENTE",C3,0) -> 0
A4: 44361 | B4: BATERIA 90AMP SALDO | C4: 40000 | D4: PAGADO | E4: NO | F4: DELIS | I4: =IF(D4="PENDIENTE",C4,0) -> 0
A5: 44418 | B5: liquido freno | C5: 3500 | D5: PAGADO | E5: NO | F5: DELIS | I5: =IF(D5="PENDIENTE",C5,0) -> 0
A6: 44467 | B6: LIMPIADOR INTERIORES SONAX | C6: 10000 | D6: PAGADO | E6: NO | F6: DELIS | I6: =IF(D6="PENDIENTE",C6,0) -> 0
A7: 44578 | B7: piso refrigerante | C7: 18000 | D7: PAGADO | E7: no | F7: delis | I7: =IF(D7="PENDIENTE",C7,0) -> 0
A8: 44578 | B8: rost off | C8: 4500 | D8: PAGADO | E8: no | F8: DELIS | I8: =IF(D8="PENDIENTE",C8,0) -> 0
A9: 44636 | B9: ROST OFF SILICONA | C9: 14500 | D9: PAGADO | I9: =IF(D9="PENDIENTE",C9,0) -> 0
A10: 44655 | B10: REFRIGERANTE | C10: 4500 | D10: PAGADO | I10: =IF(D10="PENDIENTE",C10,0) -> 0
A11: 44727 | B11: filtro petroleo | C11: 6500 | D11: PAGADO | I11: =IF(D11="PENDIENTE",C11,0) -> 0
B12: BUJIAS | C12: 32000 | D12: pagado | F12: delis | I12: =IF(D12="PENDIENTE",C12,0) -> 0
A13: 44802 | B13: saldo bateria | C13: 15000 | D13: PAGADO | F13: cesar | I13: =IF(D13="PENDIENTE",C13,0) -> 0
A14: 44838 | B14: SILICONA | C14: 4500 | D14: PAGADO | I14: =IF(D14="PENDIENTE",C14,0) -> 0
A15: 44931 | B15: coolant rojo | C15: 4500 | D15: PAGADO | I15: =IF(D15="PENDIENTE",C15,0) -> 0
A16: 44957 | B16: anticongelante x2 | C16: 9000 | D16: PAGADO | F16: delis | I16: =IF(D16="PENDIENTE",C16,0) -> 0
A17: 45093 | B17: ANTICONGELNTE X2 | C17: 9000 | D17: PAGADO | F17: delis | I17: =IF(D17="PENDIENTE",C17,0) -> 0
B18: SALDO A FAVOR | C18: 58500 | D18: PAGADO | I18: =IF(D18="PENDIENTE",C18,0) -> 0
A19: 45194 | B19: saldo bateria | C19: 16500 | D19: PAGADO | I19: =IF(D19="PENDIENTE",C19,0) -> 0
A20: 45202 | B20: BOMBA BENCINA | C20: 18000 | D20: PAGADO | I20: =IF(D20="PENDIENTE",C20,0) -> 0
A21: 45210 | B21: turbo d4cb | C21: 220000 | D21: pagado | I21: =IF(D21="PENDIENTE",C21,0) -> 0
A22: 45212 | B22: aceite penco 7 LITROS saldo | C22: 35000 | D22: pagado | I22: =IF(D22="PENDIENTE",C22,0) -> 0
A23: 45265 | B23: SILICONA WURT | C23: 6000 | D23: pagado | I23: =IF(D23="PENDIENTE",C23,0) -> 0
B24: ROST OFF | C24: 6000 | D24: pagado | I24: =IF(D24="PENDIENTE",C24,0) -> 0
B25: aceite 10w/30 | C25: 8000 | D25: pagado | I25: =IF(D25="PENDIENTE",C25,0) -> 0
B26: bateria 90 | C26: 50000 | D26: pagado | I26: =IF(D26="PENDIENTE",C26,0) -> 0
B27: limpiacontacto | C27: 5500 | D27: pagado | I27: =IF(D27="PENDIENTE",C27,0) -> 0
A28: 45358 | B28: PEGATANKE | C28: 12000 | D28: pagado | I28: =IF(D28="PENDIENTE",C28,0) -> 0
A29: 45359 | B29: LIQUIDO FRENO | C29: 4500 | D29: pagado | I29: =IF(D29="PENDIENTE",C29,0) -> 0
A30: 45387 | B30: aceite 20w/50 galon | C30: 18000 | D30: pagado | I30: =IF(D30="PENDIENTE",C30,0) -> 0
A31: 45387 | B31: EMPAQUETADURA CULATA Y TAPA VALVULA 1Y | C31: 15000 | D31: pagado | I31: =IF(D31="PENDIENTE",C31,0) -> 0
A32: 45392 | B32: coolan | C32: 8000 | D32: pagado | I32: =IF(D32="PENDIENTE",C32,0) -> 0
A33: 45397 | B33: COOLANT | C33: 4500 | D33: pagado | I33: =IF(D33="PENDIENTE",C33,0) -> 0
A34: 45428 | B34: rost off y 2 ampolleta | C34: 2000 | D34: pagado | I34: =IF(D34="PENDIENTE",C34,0) -> 0
A35: 45439 | B35: LIQUIDO REFRIGERANTE X2 | C35: 9000 | D35: pagado | I35: =IF(D35="PENDIENTE",C35,0) -> 0
A36: 45447 | B36: aceite 15w/40 6lts | C36: 18000 | D36: pagado | E36: abono $30000 | I36: =IF(D36="PENDIENTE",C36,0) -> 0
A37: 45534 | B37: silicona loctite | C37: 1000 | D37: pendiente | I37: =IF(D37="PENDIENTE",C37,0) -> 1000
A38: 45649 | B38: rost off | C38: 5000 | D38: pendiente | I38: =IF(D38="PENDIENTE",C38,0) -> 5000
A39: 45659 | C39: 3500 | D39: pendiente | I39: =IF(D39="PENDIENTE",C39,0) -> 3500
I40: =IF(D40="PENDIENTE",C40,0) -> 0
I41: =IF(D41="PENDIENTE",C41,0) -> 0
I42: =IF(D42="PENDIENTE",C42,0) -> 0
I43: =IF(D43="PENDIENTE",C43,0) -> 0
I44: =IF(D44="PENDIENTE",C44,0) -> 0
I45: =IF(D45="PENDIENTE",C45,0) -> 0
I46: =IF(D46="PENDIENTE",C46,0) -> 0
I47: =IF(D47="PENDIENTE",C47,0) -> 0
I48: =IF(D48="PENDIENTE",C48,0) -> 0
I49: =IF(D49="PENDIENTE",C49,0) -> 0
I50: =IF(D50="PENDIENTE",C50,0) -> 0
I51: =IF(D51="PENDIENTE",C51,0) -> 0
... I56: =IF(D56="PENDIENTE",C56,0) -> 0

Sheet AGUILAR FELIPE (BULLA)
B1: REPUESTO | C1: PRECIO | D1: CONDICION | E1: FACTURA | F1: VENDEDOR | H1: FACTURA | I1: DEUDA | J1: TOTAL DEUDA
A2: 43466 | B2: SALDO | D2: PAGADO | E2: NO | F2: OMAR | H2: =IF(E:E="NO FACTURADO","PENDIENTE","AL DIA") -> AL DIA | I2: =IF(D2="PENDIENTE",C2,0) -> 0 | J2: =SUM(I:I) -> 538000 | K2: MENU
A3: 44237 | B3: FILTRO ACEITE NAVARA | C3: 5000 | D3: PAGADO | E3: NO | F3: CESAR | I3: =IF(D3="PENDIENTE",C3,0) -> 0
A4: 44237 | B4: 2 COOLANT 711 | C4: 8000 | D4: PAGADO | E4: NO | F4: CESAR | I4: =IF(D4="PENDIENTE",C4,0) -> 0
A5: 44239 | B5: 2 COOLANT 711 | C5: 8000 | D5: PAGADO | E5: NO | F5: CESAR | I5: =IF(D5="PENDIENTE",C5,0) -> 0
A6: 44239 | B6: 15W40 L | C6: 5000 | D6: PAGADO | E6: NO | F6: CESAR | I6: =IF(D6="PENDIENTE",C6,0) -> 0
A7: 44250 | B7: KIT DISTRIBUCION MITSUBISHI | C7: 163000 | D7: PAGADO | E7: NO | F7: CESAR | I7: =IF(D7="PENDIENTE",C7,0) -> 0
A8: 44287 | B8: EMP. MOTOR,METAL BILEA,EMP.CULATA K74 | C8: 66000 | D8: PAGADO | E8: NO | F8: CESAR | I8: =IF(D8="PENDIENTE",C8,0) -> 0
A9: 44302 | B9: EMP. MOTOR + CULATA METALICA | C9: 83000 | D9: PAGADO | E9: NO | F9: CESAR | I9: =IF(D9="PENDIENTE",C9,0) -> 0
A10: 44312 | B10: filtro aceite sorento | C10: 22000 | D10: PAGADO | E10: NO | F10: CESAR | I10: =IF(D10="PENDIENTE",C10,0) -> 0
A11: 44334 | B11: rodamiento rda platina | C11: 14000 | D11: PAGADO | E11: no | F11: CESAR | I11: =IF(D11="PENDIENTE",C11,0) -> 0
A12: 44335 | B12: mantencion rio 5 negro caja 6ta full | C12: 53000 | D12: PAGADO | E12: NO | F12: CESAR | I12: =IF(D12="PENDIENTE",C12,0) -> 0
A13: 44336 | B13: PASTILLA FRENO I10 | C13: 15000 | D13: PAGADO | E13: NO | F13: CESAR | I13: =IF(D13="PENDIENTE",C13,0) -> 0
A14: 44341 | B14: jgo emp.+silicona+kit distribucion+ 4 guia escape | C14: 121000 | D14: PAGADO | E14: NO | F14: CESAR | I14: =IF(D14="PENDIENTE",C14,0) -> 0
... A24: 44399 | B24: terminal kun (2) 18000 | C24: 36000 | D24: PAGADO | E24: no | F24: CESAR | I24: =IF(D24="PENDIENTE",C24,0) -> 0
A25: 44411 | B25: JGO RETENES LANCER | C25: 15000 | D25: DEVUELTOS | I25: =IF(D25="PENDIENTE",C25,0) -> 0
A26: 44411 | B26: JGO BIELETAS KIA RIO | C26: 30000 | D26: PAGADO | F26: CESAR | I26: =IF(D26="PENDIENTE",C26,0) -> 0
A27: 44441 | B27: valvula ignis | C27: 90000 | D27: PAGADO | E27: no | F27: CESAR | I27: =IF(D27="PENDIENTE",C27,0) -> 0
A28: 44442 | B28: L200 2005 | C28: 28000 | D28: PAGADO | E28: no | F28: CESAR | I28: =IF(D28="PENDIENTE",C28,0) -> 0
A29: 44445 | B29: aceite para la cascara | C29: 29000 | D29: PAGADO | E29: no | F29: CESAR | I29: =IF(D29="PENDIENTE",C29,0) -> 0
A30: 44446 | B30: aceite filtro termosttao l200 | C30: 59000 | D30: PAGADO | F30: delis | I30: =IF(D30="PENDIENTE",C30,0) -> 0
A31: 44463 | B31: homocinetica mazda 3 | C31: 75000 | D31: DEVUELTOS | E31: no | F31: CESAR | I31: =IF(D31="PENDIENTE",C31,0) -> 0
A32: 44488 | B32: SOPORTE MOTOR L200 | C32: 20000 | D32: PAGADO | E32: NO | F32: CESAR | I32: =IF(D32="PENDIENTE",C32,0) -> 0
A33: 44511 | B33: jgo pastilla freno | C33: 24000 | D33: PAGADO | F33: CESAR | I33: =IF(D33="PENDIENTE",C33,0) -> 0
A34: 44523 | B34: cambio aceite nomade | C34: 40000 | D34: PAGADO | E34: no | F34: CESAR | I34: =IF(D34="PENDIENTE",C34,0) -> 0
A35: 44525 | B35: ACEITE 5W/30 | C35: 60000 | D35: PAGADO | F35: CESAR | I35: =IF(D35="PENDIENTE",C35,0) -> 0
A36: 44532 | B36: maza accent 1997 jgo | C36: 60000 | D36: PAGADO | E36: NO | F36: CESAR | I36: =IF(D36="PENDIENTE",C36,0) -> 0
A37: 44532 | B37: CAMBIO ACEITE MAGNATEC | C37: 33000 | D37: PAGADO | E37: NO | F37: CESAR | I37: =IF(D37="PENDIENTE",C37,0) -> 0
A38: 44546 | B38: soporte cardan d21 | C38: 22000 | D38: PAGADO | E38: no | F38: cesar | I38: =IF(D38="PENDIENTE",C38,0) -> 0
A39: 44546 | B39: anillos motor | C39: 33000 | D39: pendiente | E39: no | F39: CESAR | I39: =IF(D39="PENDIENTE",C39,0) -> 33000
A40: 44546 | B40: aceite y filtro | C40: 22000 | D40: PAGADO | E40: no | F40: CESAR | I40: =IF(D40="PENDIENTE",C40,0) -> 0
A41: 44546 | B41: emp. tapa valvula y camisa bujia | C41: 23000 | D41: PAGADO | E41: no | F41: CESAR | I41: =IF(D41="PENDIENTE",C41,0) -> 0
A42: 44550 | B42: jgo optico | C42: 100000 | D42: PAGADO | E42: no | F42: CESAR | I42: =IF(D42="PENDIENTE",C42,0) -> 0
A43: 44550 | B43: rotor | C43: 3000 | D43: PAGADO | E43: no | F43: CESAR | I43: =IF(D43="PENDIENTE",C43,0) -> 0
A44: 44559 | B44: cambio de aceite abispa | C44: 38000 | D44: pendiente | E44: no | F44: CESAR | I44: =IF(D44="PENDIENTE",C44,0) -> 38000
A45: 44575 | B45: cremallera direccion accent | C45: 40000 | D45: PAGADO | E45: no | F45: CESAR | I45: =IF(D45="PENDIENTE",C45,0) -> 0
A46: 44578 | B46: correa distribucion kb4 | C46: 25000 | D46: PAGADO | E46: no | F46: CESAR | I46: =IF(D46="PENDIENTE",C46,0) -> 0
A47: 44581 | B47: repuestos 3y | C47: 64000 | D47: PAGADO | E47: NO | F47: CESAR | I47: =IF(D47="PENDIENTE",C47,0) -> 0
... A54: 44631 | B54: repuesto elantra 1,6 | C54: 49000 | D54: PAGADO | E54: no | F54: OMAR | I54: =IF(D54="PENDIENTE",C54,0) -> 0
A55: 44634 | B55: tensor sail narco | C55: 30000 | D55: PAGADO | F55: cesar | I55: =IF(D55="PENDIENTE",C55,0) -> 0
A56: 44634 | B56: bobina + bujias | C56: 55000 | D56: PAGADO | F56: CESAR | I56: =IF(D56="PENDIENTE",C56,0) -> 0
A57: 44648 | B57: bujias + termostato (casi suegra) | C57: 60000 | D57: PAGADO | E57: NO | F57: CESAR | I57: =IF(D57="PENDIENTE",C57,0) -> 0
A58: 44648 | B58: 75W90 | C58: 38000 | D58: PAGADO | E58: no | F58: CESAR | I58: =IF(D58="PENDIENTE",C58,0) -> 0
A59: 44655 | B59: JGO CABLES BUJIAS ACCENT | C59: 12000 | D59: PAGADO | E59: NO | F59: CESAR | I59: =IF(D59="PENDIENTE",C59,0) -> 0
A60: 44656 | B60: castrol gran nomade v6 | C60: 33000 | D60: PAGADO | F60: CESAR | I60: =IF(D60="PENDIENTE",C60,0) -> 0
A61: 44700 | B61: castrol 80/90ls *3 + limpador radiador | C61: 50000 | D61: PAGADO | F61: CESAR | I61: =IF(D61="PENDIENTE",C61,0) -> 0
A62: 44701 | B62: tapa rad+sellos agua limpiaradiador | C62: 20000 | D62: PAGADO | F62: CESAR | I62: =IF(D62="PENDIENTE",C62,0) -> 0
A63: 44719 | B63: ACEITE MOTOR BALENO | C63: 58000 | D63: PAGADO | F63: CESAR | I63: =IF(D63="PENDIENTE",C63,0) -> 0
A64: 44726 | B64: SERVICIO ACCENT RB | C64: 98000 | D64: pagado | F64: CESAR | I64: =IF(D64="PENDIENTE",C64,0) -> 0
A65: 44726 | B65: K74 MITSUBISHI | C65: 5000 | D65: PAGADO | F65: CESAR | I65: =IF(D65="PENDIENTE",C65,0) -> 0
A66: 44735 | B66: elantra hermanita | C66: 90000 | D66: PAGADO | F66: CESAR | I66: =IF(D66="PENDIENTE",C66,0) -> 0
A67: 44749 | B67: coolant colorado | C67: 12000 | D67: PAGADO | F67: CESAR | I67: =IF(D67="PENDIENTE",C67,0) -> 0
A68: 44756 | B68: repuestos tucson | C68: 170000 | D68: PAGADO | F68: omar | I68: =IF(D68="PENDIENTE",C68,0) -> 0
A69: 44761 | B69: PRESUPUESTO Nº5227 | C69: 443000 | D69: PAGADO | F69: CESAR | I69: =IF(D69="PENDIENTE",C69,0) -> 0
A70: 44777 | B70: REPUESTO CORSA APARECIO | C70: 59000 | D70: PAGADO | F70: CESAR | I70: =IF(D70="PENDIENTE",C70,0) -> 0
A71: 44798 | B71: espejo nissan | C71: 10000 | D71: PAGADO | F71: cesar | I71: =IF(D71="PENDIENTE",C71,0) -> 0
... A100: 44974 | B100: 2 juegos amarra metalica | C100: 6000 | D100: PAGADO | F100: OMAR | I100: =IF(D100="PENDIENTE",C100,0) -> 0
A101: 44978 | B101: ACEITE Y FILTRO | C101: 28000 | D101: PAGADO | E101: NO | F101: CESAR | I101: =IF(D101="PENDIENTE",C101,0) -> 0
A102: 45020 | B102: CAMBIO ACEITE BETO | C102: 58000 | D102: PAGADO | F102: CESAR | I102: =IF(D102="PENDIENTE",C102,0) -> 0 | K102: ABONO $20000 16/06/2023
A103: 45020 | B103: BUJIAS SANTA FE | C103: 35000 | D103: pagado | F103: CESAR | I103: =IF(D103="PENDIENTE",C103,0) -> 0
A104: 45029 | B104: repuestos apache | C104: 130500 | D104: PAGADO | F104: CESAR | I104: =IF(D104="PENDIENTE",C104,0) -> 0
A105: 45040 | B105: limpiador cuerpo aceleracion | C105: 10000 | D105: pagado | F105: CESAR | I105: =IF(D105="PENDIENTE",C105,0) -> 0
A106: 45042 | B106: SILICONA LOCTITE | C106: 7500 | D106: pagado | F106: CESAR | I106: =IF(D106="PENDIENTE",C106,0) -> 0
A107: 45049 | B107: luz freno carroceria | C107: 5000 | D107: PAGADO | F107: CESAR | I107: =IF(D107="PENDIENTE",C107,0) -> 0
A108: 45049 | B108: repuesto sail americo | C108: 78000 | D108: PAGADO | F108: CESAR | I108: =IF(D108="PENDIENTE",C108,0) -> 0
A109: 45061 | B109: mantencion kun lucho | C109: 85000 | D109: PAGADO | F109: CESAR | I109: =IF(D109="PENDIENTE",C109,0) -> 0
A110: 45061 | B110: presupuesto 5664 + liquido refrigerante+ACEITE | C110: 312000 | D110: PAGADO | F110: CESAR | I110: =IF(D110="PENDIENTE",C110,0) -> 0
A111: 45061 | B111: aceite y filtro + 2coolant +silicona wurth sail 1,4 | C111: 9000 | D111: PAGADO | F111: CESAR | I111: =IF(D111="PENDIENTE",C111,0) -> 0
A112: 45061 | B112: termostato filltro bencina PROTON | C112: 25000 | D112: PAGADO | F112: CESAR | I112: =IF(D112="PENDIENTE",C112,0) -> 0
A113: 45063 | B113: kit embrague alto | C113: 105000 | D113: PAGADO | F113: CESAR | I113: =IF(D113="PENDIENTE",C113,0) -> 0
A114: 45063 | B114: aceite filtro sonic | C114: 55000 | D114: PAGADO | E114: 45071 | F114: CESAR | I114: =IF(D114="PENDIENTE",C114,0) -> 0
A115: 45064 | B115: agregar a repuestos toyota | C115: 108000 | D115: PAGADO | F115: CESAR | I115: =IF(D115="PENDIENTE",C115,0) -> 0
A116: 45071 | B116: REPUSETOS ELANTRA | C116: 18000 | D116: PAGADO | F116: CESAR | I116: =IF(D116="PENDIENTE",C116,0) -> 0
A117: 45077 | B117: repuestos porter | C117: 39000 | D117: PAGADO | F117: CESAR | I117: =IF(D117="PENDIENTE",C117,0) -> 0
A118: 45078 | B118: PRESTONE | C118: 12000 | D118: PAGADO | F118: CESAR | I118: =IF(D118="PENDIENTE",C118,0) -> 0
A119: 45083 | B119: MAZA YARIS | C119: 50000 | D119: PAGADO | F119: CESAR | I119: =IF(D119="PENDIENTE",C119,0) -> 0
A120: 45085 | B120: aceite 75w/90 gl5 ALTO | C120: 27000 | D120: PAGADO | F120: CESAR | I120: =IF(D120="PENDIENTE",C120,0) -> 0
A121: 45086 | B121: aceite 75w/90 gl5 ALTO | C121: 13500 | D121: PAGADO | F121: CESAR | I121: =IF(D121="PENDIENTE",C121,0) -> 0
A122: 45105 | B122: liquido refrigerante x5 | C122: 11700 | D122: PAGADO | F122: CESAR | I122: =IF(D122="PENDIENTE",C122,0) -> 0
A123: 45112 | B123: SALDO DISTRIBUCION PEUGEOT | C123: 77000 | D123: PAGADO | F123: CESAR | I123: =IF(D123="PENDIENTE",C123,0) -> 0
A124: 45118 | B124: FILTRO FRONTIER | C124: 15000 | D124: PAGADO | F124: CESAR | I124: =IF(D124="PENDIENTE",C124,0) -> 0
A125: 45118 | B125: PRESTONE | C125: 27000 | D125: PAGADO | F125: cesar | I125: =IF(D125="PENDIENTE",C125,0) -> 0
A126: 45121 | B126: aceite y filtro ronald | C126: 40000 | D126: PAGADO | F126: cesar | I126: =IF(D126="PENDIENTE",C126,0) -> 0
A127: 45127 | B127: pastillas freno kun | C127: 24000 | D127: PAGADO | F127: CESAR | I127: =IF(D127="PENDIENTE",C127,0) -> 0
B128: KIT EMBRAGUE CORSA | C128: 78000 | D128: PAGADO | F128: CESAR | I128: =IF(D128="PENDIENTE",C128,0) -> 0
B129: rodamiento cardan | C129: 23000 | D129: PAGADO | F129: CESAR | I129: =IF(D129="PENDIENTE",C129,0) -> 0
B130: limpieza inyectores | C130: 35000 | D130: PAGADO | F130: CESAR | I130: =IF(D130="PENDIENTE",C130,0) -> 0
B131: 75w/90 litro | C131: 7000 | D131: PAGADO | F131: CESAR | I131: =IF(D131="PENDIENTE",C131,0) -> 0
A132: 45161 | B132: ACEITE + FILTROS ELANTRA + CORREA | C132: 63500 | D132: PAGADO | F132: CESAR | I132: =IF(D132="PENDIENTE",C132,0) -> 0
A133: 45166 | B133: TERMINALES | C133: 16000 | D133: PAGADO | F133: CESAR | I133: =IF(D133="PENDIENTE",C133,0) -> 0
A134: 45175 | B134: PRESTONE 2 CHERY + RETEN | C134: 30500 | D134: PAGADO | F134: CESAR | I134: =IF(D134="PENDIENTE",C134,0) -> 0
A135: 45175 | B135: CORREA ARTIZ | C135: 6000 | D135: PAGADO | F135: CESAR | I135: =IF(D135="PENDIENTE",C135,0) -> 0
A136: 45175 | B136: ACEITE 80W/90 HILUX | C136: 10000 | D136: PAGADO | F136: CESAR | I136: =IF(D136="PENDIENTE",C136,0) -> 0
B137: sensor oxigeno | C137: 30000 | D137: PAGADO | F137: CESAR | I137: =IF(D137="PENDIENTE",C137,0) -> 0
A138: 45182 | B138: filtro aire tapa radiador | C138: 15000 | D138: PAGADO | F138: CESAR | I138: =IF(D138="PENDIENTE",C138,0) -> 0
A139: 45191 | B139: prestone | C139: 13000 | D139: PAGADO | F139: CESAR | I139: =IF(D139="PENDIENTE",C139,0) -> 0
A140: 45191 | B140: liquido rojo x2 | C140: 10000 | D140: PAGADO | F140: CESAR | I140: =IF(D140="PENDIENTE",C140,0) -> 0
A141: 45198 | B141: mantencion baleno | C141: 78000 | D141: PAGADO | F141: CESAR | I141: =IF(D141="PENDIENTE",C141,0) -> 0
B142: PONCHO | C142: 10000 | D142: PAGADO | F142: CESAR | I142: =IF(D142="PENDIENTE",C142,0) -> 0
B143: SELLADOR RADIADOR | C143: 10000 | D143: PAGADO | F143: CESAR | I143: =IF(D143="PENDIENTE",C143,0) -> 0
...

Sheet CANALES JOSE LUIS
A1: FECHA | B1: REPUESTO | C1: PRECIO | D1: CONDICION | E1: FACTURA | F1: VENDEDOR | H1: FACTURA | I1: DEUDA | J1: TOTAL DEUDA
A2: 44181 | B2: SELLO DE VALVULA D22 | C2: 14000 | D2: PAGADO | E2: FACTURADO | F2: OMAR | H2: =IF(E:E="NO FACTURADO","PENDIENTE","AL DIA") -> AL DIA | I2: =IF(D2="PENDIENTE",C2,0) -> 0 | J2: 0 | K2: MENU
A3: 44181 | B3: SILICONA LOCTITE | C3: 5000 | D3: PAGADO | E3: FACTURADO | F3: DELIS | H3: =IF(E:E="NO FACTURADO","PENDIENTE","AL DIA") -> AL DIA | I3: =IF(D3="PENDIENTE",C3,0) -> 0
A4: 44194 | B4: JUEGO EMPAQUETADURA+EMPAQUETADURA | C4: 100000 | D4: PAGADO | E4: FACTURADO | F4: DELIS | H4: =IF(E:E="NO FACTURADO","PENDIENTE","AL DIA") -> AL DIA | I4: =IF(D4="PENDIENTE",C4,0) -> 0
A5: 44194 | B5: SALDO CULATA | C5: 110000 | D5: PAGADO | E5: FACTURADO | F5: CESAR | H5: =IF(E:E="NO FACTURADO","PENDIENTE","AL DIA") -> AL DIA | I5: =IF(D5="PENDIENTE",C5,0) -> 0
A6: 44194 | B6: PRESUPUESTO 4215 | C6: 8500 | D6: PAGADO | E6: NO FACTURADO | F6: DELIS | H6: AL DIA | I6: =IF(D6="PENDIENTE",C6,0) -> 0
A7: 44195 | B7: PRESUPUESTO 4217 | C7: 18500 | D7: PAGADO | E7: NO FACTURADO | F7: DELIS | H7: AL DIA | I7: =IF(D7="PENDIENTE",C7,0) -> 0
A8: 44230 | B8: 6L 5W20 | C8: 10000 | D8: PAGADO | E8: NO FACTURADO | F8: CESAR | H8: AL DIA | I8: =IF(D8="PENDIENTE",C8,0) -> 0
A9: 44239 | B9: 2L 80W90 | C9: 13000 | D9: PAGADO | E9: NO FACTURADO | F9: CESAR | H9: AL DIA | I9: =IF(D9="PENDIENTE",C9,0) -> 0
A10: 44240 | B10: 2 COOLANT | C10: 5600 | D10: PAGADO | E10: NO FACTURADO | F10: CESAR | H10: AL DIA | I10: =IF(D10="PENDIENTE",C10,0) -> 0
A11: 44240 | B11: SILICONA LOCTITE | C11: 5000 | D11: PAGADO | E11: NO FACTURADO | F11: CESAR | H11: AL DIA | I11: =IF(D11="PENDIENTE",C11,0) -> 0
A12: 44509 | B12: saldo pendiente toyota 4y | C12: 90000 | D12: PAGADO | E12: NO FACTURADO | F12: CESAR | H12: AL DIA | I12: =IF(D12="PENDIENTE",C12,0) -> 0
A13: 44705 | B13: bomba freno v16 liquido freno | C13: 50000 | D13: PAGADO | F13: delis | H13: =IF(E:E="NO FACTURADO","PENDIENTE","AL DIA") -> AL DIA | I13: =IF(D13="PENDIENTE",C13,0) -> 0
A14: 44726 | B14: BATERIA 90AMP + 2ANTICOMGELANTE | C14: 129000 | D14: pagado | F14: DELIS | H14: =IF(E:E="NO FACTURADO","PENDIENTE","AL DIA") -> AL DIA | I14: =IF(D14="PENDIENTE",C14,0) -> 0
A15: 44852 | B15: PASTILLA FRENO | C15: 15000 | D15: PAGADO | F15: CESAR | H15: =IF(E:E="NO FACTURADO","PENDIENTE","AL DIA") -> AL DIA | I15: =IF(D15="PENDIENTE",C15,0) -> 0
A16: 44869 | B16: JGO RODAMIENTO | C16: 50000 | D16: PAGADO | F16: CESAR | H16: =IF(E:E="NO FACTURADO","PENDIENTE","AL DIA") -> AL DIA | I16: =IF(D16="PENDIENTE",C16,0) -> 0
A17: 44901 | B17: bateria 55 amperes saldo | C17: 15000 | D17: PAGADO | F17: DELIS | H17: =IF(E:E="NO FACTURADO","PENDIENTE","AL DIA") -> AL DIA | I17: =IF(D17="PENDIENTE",C17,0) -> 0
A18: 45022 | B18: correa distribucion corolla | C18: 24000 | D18: PAGADO | F18: omar | H18: =IF(E:E="NO FACTURADO","PENDIENTE","AL DIA") -> AL DIA | I18: =IF(D18="PENDIENTE",C18,0) -> 0
A19: 45043 | B19: PRESUPUESTO 5724 | C19: 188000 | D19: PAGADO | F19: CESAR | H19: =IF(E:E="NO FACTURADO","PENDIENTE","AL DIA") -> AL DIA | I19: =IF(D19="PENDIENTE",C19,0) -> 0
A20: 45054 | B20: presupuesto 5670 | C20: 92000 | D20: PAGADO | F20: CESAR | H20: =IF(E:E="NO FACTURADO","PENDIENTE","AL DIA") -> AL DIA | I20: =IF(D20="PENDIENTE",C20,0) -> 0
A21: 45057 | B21: PRESUPUESTO 5673 | C21: 85000 | D21: PAGADO | F21: DELIS | H21: =IF(E:E="NO FACTURADO","PENDIENTE","AL DIA") -> AL DIA | I21: =IF(D21="PENDIENTE",C21,0) -> 0
A22: 45075 | B22: presupuesto 5741 | C22: 105000 | D22: PAGADO | F22: DELIS | H22: =IF(E:E="NO FACTURADO","PENDIENTE","AL DIA") -> AL DIA | I22: =IF(D22="PENDIENTE",C22,0) -> 0
A23: 45093 | B23: PRESUPUESTO 5791 | C23: 65000 | D23: PAGADO | F23: DELIS | H23: =IF(E:E="NO FACTURADO","PENDIENTE","AL DIA") -> AL DIA | I23: =IF(D23="PENDIENTE",C23,0) -> 0
A24: 45135 | B24: PRESUPUESTO 5854 | C24: 45000 | D24: PAGADO | F24: DELIS | H24: =IF(E:E="NO FACTURADO","PENDIENTE","AL DIA") -> AL DIA | I24: =IF(D24="PENDIENTE",C24,0) -> 0
A25: 45138 | B25: filtro agua | C25: 17000 | D25: PAGADO | F25: CESAR | H25: =IF(E:E="NO FACTURADO","PENDIENTE","AL DIA") -> AL DIA | I25: =IF(D25="PENDIENTE",C25,0) -> 0
A26: 45139 | B26: RETEN | C26: 10000 | D26: PAGADO | H26: =IF(E:E="NO FACTURADO","PENDIENTE","AL DIA") -> AL DIA | I26: =IF(D26="PENDIENTE",C26,0) -> 0
A27: 45142 | B27: pastilla y tps | C27: 20000 | D27: PAGADO | H27: =IF(E:E="NO FACTURADO","PENDIENTE","AL DIA") -> AL DIA | I27: =IF(D27="PENDIENTE",C27,0) -> 0
A28: 45181 | B28: aceite filtro peugeot; filtro aceite toyota | C28: 38000 | D28: PAGADO | H28: =IF(E:E="NO FACTURADO","PENDIENTE","AL DIA") -> AL DIA | I28: =IF(D28="PENDIENTE",C28,0) -> 0
B29: saldo daewo | C29: 18500 | D29: PAGADO | I29: =IF(D29="PENDIENTE",C29,0) -> 0
A30: 45306 | B30: BUJIAS CABLE FILTRO DAEWO | C30: 28500 | D30: PAGADO | I30: =IF(D31="PENDIENTE",C30,0) -> 0
B31: FLEXIBLE DEPRESOR | C31: 6000 | D31: PAGADO | I31: 6000
B32: JABON | C32: 11000 | D32: PAGADO | I32: =IF(D32="PENDIENTE",C32,0) -> 0
B33: saldo bateria amigo | C33: 45000 | D33: PAGADO | I33: =IF(D33="PENDIENTE",C33,0) -> 0
A34: 45440 | B34: abrillantador foco | C34: 20000 | D34: PAGADO | I34: =IF(D34="PENDIENTE",C34,0) -> 0
A35: 45457 | B35: aceite y filtro refrigerante | C35: 17000 | D35: PAGADO | E35: abono 40000 | I35: =IF(D35="PENDIENTE",C35,0) -> 0
I36: =IF(D36="PENDIENTE",C36,0) -> 0
I37: =IF(D37="PENDIENTE",C37,0) -> 0
I38: =IF(D38="PENDIENTE",C38,0) -> 0
I39: =IF(D39="PENDIENTE",C39,0) -> 0
I40: =IF(D40="PENDIENTE",C40,0) -> 0
I41: =IF(D41="PENDIENTE",C41,0) -> 0
I42: =IF(D42="PENDIENTE",C42,0) -> 0
I43: =IF(D43="PENDIENTE",C43,0) -> 0
I44: =IF(D44="PENDIENTE",C44,0) -> 0
I45: =IF(D45="PENDIENTE",C45,0) -> 0
I46: =IF(D46="PENDIENTE",C46,0) -> 0
I47: =IF(D47="PENDIENTE",C47,0) -> 0
... I89: =IF(D89="PENDIENTE",C89,0) -> 0

Sheet CARDENAS GABRIEL
A1: FECHA | B1: REPUESTO | C1: PRECIO | D1: CONDICION | E1: FACTURA | F1: VENDEDOR | H1: FACTURA | I1: DEUDA | J1: TOTAL DEUDA
A2: 44130 | B2: SALDO | C2: 15000 | D2: pagado | E2: NO | F2: OMAR | H2: =IF(E:E="NO FACTURADO","PENDIENTE","AL DIA") -> AL DIA | I2: =IF(D2="PENDIENTE",C2,0) -> 0 | J2: =SUM(I:I) -> 58000 | K2: MENU
A3: 44273 | B3: CORREA | C3: 3500 | D3: pagado | E3: NO | F3: CESAR | I3: =IF(D3="PENDIENTE",C3,0) -> 0
A4: 44302 | B4: RADIADOR AERIO (MAKINON) | C4: 20000 | D4: pagado | E4: NO | F4: CESAR | I4: =IF(D4="PENDIENTE",C4,0) -> 0
A5: 44310 | B5: 2 cooreas h100 + correa b39 | C5: 13500 | D5: pagado | E5: NO | F5: CESAR | I5: =IF(D5="PENDIENTE",C5,0) -> 0
A6: 44336 | B6: termostato aerio | C6: 14500 | D6: pagado | E6: NO | F6: CESAR | I6: =IF(D6="PENDIENTE",C6,0) -> 0
A7: 44362 | B7: JGO CORREAS D21 | C7: 18000 | D7: pagado | E7: NO | F7: DELIS | I7: =IF(D7="PENDIENTE",C7,0) -> 0
A8: 44383 | B8: CAMBIO ACEITE 10W40 ABONO 20 | C8: 5000 | D8: pagado | E8: NO | F8: CESAR | I8: =IF(D8="PENDIENTE",C8,0) -> 0
A9: 44406 | B9: jgo neblinero makinon | C9: 36000 | D9: pagado | E9: NO | F9: CESAR | I9: =IF(D9="PENDIENTE",C9,0) -> 0
A10: 44448 | B10: saldo optico vivant | C10: 21000 | D10: pagado | E10: no | F10: CESAR | I10: =IF(D10="PENDIENTE",C10,0) -> 0
A11: 44467 | B11: jgo valvula empaquetadura | C11: 28000 | D11: PAGADO | E11: no | F11: CESAR | I11: =IF(D11="PENDIENTE",C11,0) -> 0
A12: 44483 | B12: JURGO ROULA 4ZD1 | C12: 29000 | D12: pagado | E12: NO | F12: CESAR | I12: =IF(D12="PENDIENTE",C12,0) -> 0
A13: 44550 | B13: radiador condensador vivant saldo | C13: 30000 | D13: pagado | E13: si | F13: CESAR | I13: =IF(D13="PENDIENTE",C13,0) -> 0
A14: 44560 | B14: radiador l200 | C14: 130000 | D14: PAGADO | E14: si | F14: CESAR | I14: =IF(D14="PENDIENTE",C14,0) -> 0
... A16: 44608 | B16: empaquetadura baleno | C16: 10000 | D16: Pagado | E16: no | F16: CESAR | I16: =IF(D16="PENDIENTE",C16,0) -> 0
A17: 44663 | B17: presupuesto 5011 | C17: 10000 | D17: pagado | F17: DELIS | I17: =IF(D17="PENDIENTE",C17,0) -> 0
A18: 44742 | B18: anillos y metal biela e13 | C18: 40000 | D18: pagado | F18: cesar | I18: =IF(D18="PENDIENTE",C18,0) -> 0
A19: 44802 | B19: farol trasero yaris | C19: 50000 | D19: pagado | F19: CESAR | I19: =IF(D19="PENDIENTE",C19,0) -> 0
A20: 44812 | B20: espejo yaris | C20: 50000 | D20: pagado | F20: CESAR | I20: =IF(D20="PENDIENTE",C20,0) -> 0
A21: 44846 | B21: SALDO PRESUPUESTO 5358 | C21: 8000 | D21: pagado | F21: CESAR | I21: =IF(D21="PENDIENTE",C21,0) -> 0
A22: 44843 | B22: rotula inferior 4zd1 | C22: 15000 | D22: pagado | F22: OMAR | I22: =IF(D22="PENDIENTE",C22,0) -> 0
A23: 44910 | B23: homocinetica lado caja | C23: 30000 | D23: pagado | F23: cesar | I23: =IF(D23="PENDIENTE",C23,0) -> 0
A24: 44917 | B24: repuestos nissan barra rotula | C24: 25000 | D24: pagado | F24: cesar | I24: =IF(D24="PENDIENTE",C24,0) -> 0
A25: 45037 | B25: saldo hijo yaris regalon | C25: 18000 | D25: pagado | F25: delis | I25: =IF(D25="PENDIENTE",C25,0) -> 0
A26: 45048 | B26: saldo juego empaquetadura aereo | C26: 18000 | D26: pagado | I26: =IF(D26="PENDIENTE",C26,0) -> 0
A27: 45051 | B27: ANILLOS AEREO | C27: 25000 | D27: pagado | I27: =IF(D27="PENDIENTE",C27,0) -> 0
A28: 45154 | B28: juego luces h4 osram | C28: 22000 | D28: pagado | I28: =IF(D28="PENDIENTE",C28,0) -> 0
A29: 45174 | B29: CEBADORA KOREANA | C29: 15000 | D29: pagado | I29: =IF(D29="PENDIENTE",C29,0) -> 0
A30: 45215 | B30: ACEITE + FILTRO | C30: 42000 | D30: pagado | F30: CESAR | I30: =IF(D30="PENDIENTE",C30,0) -> 0
A31: 45232 | B31: PERNO PUNTA BARRA TORSION | C31: 14000 | D31: pagado | F31: CESAR | I31: =IF(D31="PENDIENTE",C31,0) -> 0
A32: 45237 | B32: ACEITE FILTROS YARIS HIJO | C32: 19500 | D32: pagado | F32: CESAR | I32: =IF(D32="PENDIENTE",C32,0) -> 0
A33: 45254 | B33: SALDO ESPEJO | C33: 26000 | D33: pagado | F33: CESAR | I33: =IF(D33="PENDIENTE",C33,0) -> 0
A34: 45265 | B34: CABLES BUJIAS MORNING | C34: 13000 | D34: pagado | I34: =IF(D34="PENDIENTE",C34,0) -> 0
A35: 45341 | B35: presupuesto 6103 | C35: 51000 | D35: pagado | I35: =IF(D35="PENDIENTE",C35,0) -> 0
A36: 45443 | B36: ACEITE + FILTRO (hijo) | C36: 30000 | D36: pagado | F36: cesar | I36: =IF(D36="PENDIENTE",C36,0) -> 0
A37: 45517 | B37: JGO RODAMIENTO | C37: 42000 | D37: pagado | I37: =IF(D37="PENDIENTE",C37,0) -> 0
A38: 45520 | B38: BOMBA Y PATINES FRENO +LIQUIDO FRENO | C38: 52500 | D38: pagado | I38: =IF(D38="PENDIENTE",C38,0) -> 0
A39: 45540 | B39: sensor t termostato accent | C39: 20000 | D39: pagado | I39: =IF(D39="PENDIENTE",C39,0) -> 0
A40: 45569 | B40: saldo bateria hijo | C40: 35000 | D40: Pagado | I40: =IF(D40="PENDIENTE",C40,0) -> 0
A41: 45609 | B41: amortiguadores traseros vivant | C41: 40000 | D41: PENDIENTE | I41: =IF(D41="PENDIENTE",C41,0) -> 40000
A42: 45639 | B42: aceite + filtro | C42: 18000 | D42: pendiente | I42: =IF(D42="PENDIENTE",C42,0) -> 18000
A43: 45639 | B43: saldo compra tarjeta | C43: 15000 | D43: pendiente

Sheet CASTRO ALEX
A1: FECHA | B1: REPUESTO | C1: PRECIO | D1: CONDICION | E1: FACTURA | F1: VENDEDOR | H1: FACTURA | I1: DEUDA | J1: TOTAL DEUDA
B2: SALDO | C2: 466000 | D2: PENDIENTE | E2: NO | F2: OMAR | H2: =IF(E:E="NO FACTURADO","PENDIENTE","AL DIA") -> AL DIA | I2: =IF(D2="PENDIENTE",C2,0) -> 466000 | J2: =SUM(I:I) -> 466000 | K2: MENU
I3: =IF(D3="PENDIENTE",C3,0) -> 0
I4: =IF(D4="PENDIENTE",C4,0) -> 0
I5: =IF(D5="PENDIENTE",C5,0) -> 0
I6: =IF(D6="PENDIENTE",C6,0) -> 0
I7: =IF(D7="PENDIENTE",C7,0) -> 0
I8: =IF(D8="PENDIENTE",C8,0) -> 0
I9: =IF(D9="PENDIENTE",C9,0) -> 0
I10: =IF(D10="PENDIENTE",C10,0) -> 0
I11: =IF(D11="PENDIENTE",C11,0) -> 0
I12: =IF(D12="PENDIENTE",C12,0) -> 0
I13: =IF(D13="PENDIENTE",C13,0) -> 0
I14: =IF(D14="PENDIENTE",C14,0) -> 0
... I40: =IF(D40="PENDIENTE",C40,0) -> 0

Sheet CASTRO NOLBERTO
A1: FECHA | B1: REPUESTO | C1: PRECIO | D1: CONDICION | E1: FACTURA | F1: VENDEDOR | H1: FACTURA | I1: DEUDA | J1: TOTAL DEUDA
B2: SALDO | D2: PENDIENTE | E2: NO | F2: OMAR | H2: =IF(E:E="NO FACTURADO","PENDIENTE","AL DIA") -> AL DIA | I2: =IF(D2="PENDIENTE",C2,0) -> 0 | J2: =SUM(I:I) -> 95000 | K2: MENU
A3: 44266 | B3: PRESUPUESTO 4431 FRONTIER | C3: 806300 | D3: PAGADO | E3: NO | I3: =IF(D3="PENDIENTE",C3,0) -> 0
A4: 43927 | B4: PRESUPUESTO 4446 L300 $588400 SALDO | C4: 88400 | D4: PAGADO | E4: NO | I4: =IF(D4="PENDIENTE",C4,0) -> 0
A5: 44302 | B5: REPUESTOS L200 BERTIN | C5: 90000 | D5: PAGADO | E5: NO | I5: =IF(D5="PENDIENTE",C5,0) -> 0
A6: 44483 | B6: RAPUESTOS BALENO | C6: 87000 | D6: PAGADO | I6: =IF(D6="PENDIENTE",C6,0) -> 0
A7: 44615 | B7: anticongelante filtro aire | C7: 23500 | D7: pagado | F7: omar | I7: =IF(D7="PENDIENTE",C7,0) -> 0
A8: 44671 | B8: BATERIA 90AMP | C8: 108000 | D8: PAGADO | E8: por facturar abono 100.000 | F8: DELIS | I8: =IF(D8="PENDIENTE",C8,0) -> 0
A9: 44678 | B9: KIT EMBRAGUE CRUCETA LIQUIDO | C9: 149500 | D9: PAGADO | E9: por factura | F9: CESAR | I9: =IF(D9="PENDIENTE",C9,0) -> 0
A10: 44775 | B10: aceite 15w40 cambio extendido | C10: 35000 | D10: PAGADO | F10: OMAR | I10: =IF(D10="PENDIENTE",C10,0) -> 0
A11: 44916 | B11: 2- atf | C11: 10000 | D11: PAGADO | F11: DELIS | I11: =IF(D11="PENDIENTE",C11,0) -> 0
A12: 44918 | B12: saldo luv 2,2 | C12: 70000 | D12: PENDIENTE | F12: DELIS | I12: =IF(D12="PENDIENTE",C12,0) -> 70000
A13: 45029 | B13: aceite 5w30 pemco | C13: 60000 | D13: PAGADO | F13: OMAR | I13: =IF(D13="PENDIENTE",C13,0) -> 0
A14: 45064 | B14: saldo luv 2,2 | C14: 150000 | D14: PAGADO | E14: facturado | F14: DELIS | I14: =IF(D14="PENDIENTE",C14,0) -> 0
A15: 45125 | B15: 2aceite 15w/40 2pote grasa tractor (Bertin) | C15: 53000 | D15: PAGADO | F15: delis | I15: =IF(D15="PENDIENTE",C15,0) -> 0
A16: 45154 | B16: aceite 5w/30 7litros 2 preston | C16: 93000 | D16: PAGADO | F16: delis | I16: =IF(D16="PENDIENTE",C16,0) -> 0
A17: 45194 | B17: bateria 90amp rocket alcalde | C17: 90000 | D17: PAGADO | I17: =IF(D17="PENDIENTE",C17,0) -> 0
A18: 45201 | B18: cilindro freno suzuki 2 | D18: PENDIENTE | I18: =IF(D18="PENDIENTE",C18,0) -> 0
A19: 45204 | B19: jgo valvulas 323 liquido freno | D19: PENDIENTE | I19: =IF(D19="PENDIENTE",C19,0) -> 0
A20: 45210 | B20: jgo empaquetadura 323 | C20: 25000 | D20: PENDIENTE | I20: =IF(D20="PENDIENTE",C20,0) -> 25000
A21: 45210 | B21: filtro aceite y correa sportage | C21: 55000 | D21: PAGADO | I21: =IF(D21="PENDIENTE",C21,0) -> 0
A22: 45224 | B22: kit embrague reten trasero | C22: 280000 | D22: PAGADO | F22: delis | I22: =IF(D22="PENDIENTE",C22,0) -> 0
A23: 45235 | B23: rotula superior inferior pastilla limpiacontacto | C23: 85000 | D23: PAGADO | I23: =IF(D23="PENDIENTE",C23,0) -> 0
A24: 45274 | B24: ALTERNADOR Y EMPAQUETADURA TAPA | C24: 164500 | D24: pagado | I24: =IF(D24="PENDIENTE",C24,0) -> 0
A25: 45583 | B25: cruceta$20 filtro$10 correa$225 navara | C25: 48000 | D25: pagado | I25: =IF(D25="PENDIENTE",C25,0) -> 0
B26: rotula terminal | C26: 48000 | D26: pagado | I26: =IF(F28="PENDIENTE",C26,0) -> 0
A27: 45328 | B27: sensor temp | C27: 10000 | D27: pagado | I27: =IF(D27="PENDIENTE",C27,0) -> 0
B28: 4 sellos de 35 | C28: 12000 | D28: pagado | I28: =IF(D28="PENDIENTE",C28,0) -> 0
B29: 2 sellos de 40 | C29: 6000 | D29: pagado | I29: =IF(D29="PENDIENTE",C29,0) -> 0
A30: 45338 | B30: presupuesto galloper 6077 | C30: 79000 | D30: pagado | I30: =IF(D30="PENDIENTE",C30,0) -> 0
A31: 45343 | B31: rost of | C31: 6000 | D31: PAGADO | I31: =IF(D31="PENDIENTE",C31,0) -> 0
A32: 45345 | B32: filtro aire b2500 | C32: 10000 | D32: PAGADO | I32: =IF(D32="PENDIENTE",C32,0) -> 0
B33: suzuki gran nomade | C33: 100000 | D33: PAGADO | I33: =IF(D33="PENDIENTE",C33,0) -> 0
B34: EMPAQUETADURA CULATA | C34: 60000 | D34: PAGADO | I34: =IF(D34="PENDIENTE",C34,0) -> 0
A35: 45414 | B35: COOPER | C35: 22500 | D35: PAGADO | I35: =IF(D35="PENDIENTE",C35,0) -> 0
A36: 45421 | B36: presupuesto 6214 | C36: 72000 | D36: PAGADO | I36: =IF(D36="PENDIENTE",C36,0) -> 0
A37: 45464 | B37: terminal y filtro petroleo porter | C37: 17500 | D37: PAGADO | I37: =IF(D37="PENDIENTE",C37,0) -> 0
A38: 45468 | B38: radiador spark | C38: 45000 | D38: PAGADO | I38: =IF(D38="PENDIENTE",C38,0) -> 0
A39: 45477 | B39: correa ventilador 6pk1513 | C39: 20000 | D39: PAGADO | I39: =IF(D39="PENDIENTE",C39,0) -> 0
B40: sello dea gaua rost of silicona | C40: 18500 | D40: PAGADO | I40: =IF(D40="PENDIENTE",C40,0) -> 0
A41: 45540 | B41: kit distribucion rost off aceite 20w/50 | C41: 170000 | D41: PAGADO | I41: =IF(D41="PENDIENTE",C41,0) -> 0
A42: 45587 | B42: aceite y filtro mazda | C42: 30000 | D42: PAGADO | I42: =IF(D42="PENDIENTE",C42,0) -> 0
B43: litro aceite | C43: 6000 | D43: PAGADO
B44: 2 ampolleta | C44: 6000 | D44: PAGADO
B45: silicona loctitex2 | C45: 14000 | D45: PAGADO
B46: bujes biela | C46: 10000 | D46: PAGADO
B47: guias valvula nkr | C47: 20000 | D47: PAGADO
B48: aflojatodo | C48: 5000 | D48: PAGADO
B49: huincha aisladora | C49: 2500 | D49: PAGADO
B50: liquimoly | C50: 13500 | D50: PAGADO
B51: rostoff | C51: 5000 | D51: PAGADO
A52: 45621 | B52: EMPAQUETADURA CULATA ORIGINAL | C52: 149000
B53: RETEN TRASERO | C53: 14000
B54: RETEN DELANTERO | C54: 7900
B55: ACEITE 5W/30 7litros | C55: 65000
B56: FILTRO ACEITE | C56: 10000
B57: CORREA 7PK1020 | C57: 15000
B58: 4 RETEN INYECTORES | C58: 30000
A59: 45299 | B59: SALDO LOCTITE Y ACEITE | C59: 10000 | D59: PENDIENTE
B60: repuestos mitsubishi | C60: 160000 | D60: PENDIENTE
B61: repuestos navara | C61: 172000 | D61: PENDIENTE

Sheet CEA RAUL
A1: FECHA | B1: REPUESTO | C1: PRECIO | D1: CONDICION | E1: FACTURA | F1: VENDEDOR | H1: FACTURA | I1: DEUDA | J1: TOTAL DEUDA | L1: abono | M1: fecha abono
B2: SALDO | C2: 88500 | D2: PAGADO | E2: NO | F2: OMAR | H2: =IF(E:E="NO FACTURADO","PENDIENTE","AL DIA") -> AL DIA | I2: =IF(D2="PENDIENTE",C2,0) -> 0 | J2: =SUM(I:I) -> 164000 | K2: MENU
A3: 44265 | B3: JUEGO BANDEJA 64000 abono 40000 25-7-2021 | C3: 24000 | D3: pagado | F3: DELIS | I3: =IF(D3="PENDIENTE",C3,0) -> 0
A4: 44355 | B4: JUEGO BUJIAS | C4: 0 | D4: pagado | E4: NO | F4: DELIS | I4: =IF(D4="PENDIENTE",C4,0) -> 0
A5: 44364 | B5: ABRAZADERA METALICA | C5: 0 | D5: pagado | E5: NO | F5: DELIS | I5: =IF(D5="PENDIENTE",C5,0) -> 0
A6: 44371 | B6: ACEITE Y FILTRO CASTROL 27000 ABONO 18000 | C6: 9000 | D6: PAGADO | E6: NO | F6: DELIS | I6: =IF(D6="PENDIENTE",C6,0) -> 0
A7: 44376 | B7: SALDO BATERIA SOBRINO JIMMY | C7: 30000 | D7: pagado | F7: DELIS | I7: =IF(D7="PENDIENTE",C7,0) -> 0
A8: 44435 | B8: AMPOLLETA H4 | C8: 4500 | D8: PAGADO | E8: NO | F8: DELIS | I8: =IF(D8="PENDIENTE",C8,0) -> 0
A9: 44462 | B9: JGO PASTILLAS RB | C9: 25000 | D9: pagado | E9: NO | F9: DELIS | I9: =IF(D9="PENDIENTE",C9,0) -> 0
A10: 44444 | B10: RADIADOR | C10: 5000 | D10: PAGADO | E10: NO | F10: DELIS | I10: =IF(D10="PENDIENTE",C10,0) -> 0 | L10: 30000 | M10: 44504
A11: 44475 | B11: HOMOCINETICA | C11: 35000 | D11: PAGADO | F11: DELIS | I11: =IF(D11="PENDIENTE",C11,0) -> 0
A12: 44502 | B12: BUJIAS | C12: 20000 | D12: PAGADO | F12: DELIS | I12: =IF(D12="PENDIENTE",C12,0) -> 0
A13: 44511 | B13: silicon + filtro | C13: 10000 | D13: PAGADO | F13: cesar | I13: =IF(D13="PENDIENTE",C13,0) -> 0
A14: 44512 | B14: acite 10w/40 con filtro hermano | C14: 7500 | D14: PAGADO | F14: delis | I14: =IF(D14="PENDIENTE",C14,0) -> 0
A15: 44547 | B15: JGO PASTILLAS RB | C15: 8500 | D15: PAGADO | F15: delis | I15: =IF(D15="PENDIENTE",C15,0) -> 0
A16: 44574 | B16: LIQUIDO REFRIGERANTE | C16: 4000 | D16: PAGADO | F16: delis | I16: =IF(D16="PENDIENTE",C16,0) -> 0
A17: 44594 | B17: pastilla freno | C17: 17500 | D17: PAGADO | F17: delis | I17: =IF(D17="PENDIENTE",C17,0) -> 0
A18: 44677 | B18: jgo bujias | C18: 20000 | D18: PAGADO | F18: cesar | I18: =IF(D18="PENDIENTE",C18,0) -> 0 | L18: 30000 | M18: 44720
A19: 44726 | B19: jgo pastilla freno | C19: 18000 | D19: PAGADO | F19: cesar | I19: =IF(D19="PENDIENTE",C19,0) -> 0
A20: 44768 | B20: cilindro freno y liquido | C20: 6500 | D20: PAGADO | F20: delis | I20: =IF(D20="PENDIENTE",C20,0) -> 0 | L20: 30000 | M20: 44789
A21: 44839 | B21: pastilla freno accent rb | C21: 18000 | D21: PAGADO | F21: OMAR | I21: =IF(D21="PENDIENTE",C21,0) -> 0 | L21: 56500
A22: 44935 | B22: anticongelante y pino no fumar | C22: 6000 | D22: PAGADO | F22: cesar | I22: =IF(D22="PENDIENTE",C22,0) -> 0
A23: 44952 | B23: SALDO SWIFT AXIAL HERMANO | C23: 40000 | D23: PAGADO | F23: DELIS | I23: =IF(D23="PENDIENTE",C23,0) -> 0 | L23: pagado 6/03/2023
A24: 45020 | B24: jg. Pastilla freno | C24: 15000 | D24: PAGADO | F24: DELIS | I24: =IF(D24="PENDIENTE",C24,0) -> 0
A25: 45034 | B25: amortiguador trasero rb | C25: 15500 | D25: PAGADO | F25: delis | I25: =IF(D25="PENDIENTE",C25,0) -> 0
A26: 45063 | B26: AMPOLLETA H4 | C26: 4500 | D26: PAGADO | F26: OMAR | I26: =IF(D26="PENDIENTE",C26,0) -> 0
B27: PASTILLA FRENO | C27: 18000 | D27: PAGADO | I27: =IF(D27="PENDIENTE",C27,0) -> 0
A28: 45097 | B28: TERMOSTATO | C28: 8000 | D28: PENDIENTE | I28: =IF(D28="PENDIENTE",C28,0) -> 8000 | L28: abono 40000 | M28: 45110
A29: 45159 | B29: RODAMIENTO MAZA DEL | C29: 21000 | D29: PENDIENTE | I29: =IF(D29="PENDIENTE",C29,0) -> 21000
A30: 45180 | B30: AXIAL DIRECCION X2 | C30: 35000 | D30: PENDIENTE | I30: =IF(D30="PENDIENTE",C30,0) -> 35000
A31: 45181 | B31: presupuesto 5911 | C31: 65500 | D31: PENDIENTE | I31: =IF(D31="PENDIENTE",C31,0) -> 65500
A32: 45182 | B32: tapa radiador | C32: 7500 | D32: PENDIENTE | I32: =IF(D32="PENDIENTE",C32,0) -> 7500
A33: 45196 | B33: jgo pastilla freno | C33: 27000 | D33: PENDIENTE | I33: =IF(D33="PENDIENTE",C33,0) -> 27000
I34: =IF(D34="PENDIENTE",C34,0) -> 0
I35: =IF(D35="PENDIENTE",C35,0) -> 0
I36: =IF(D36="PENDIENTE",C36,0) -> 0
I37: =IF(D37="PENDIENTE",C37,0) -> 0
I38: =IF(D38="PENDIENTE",C38,0) -> 0
I39: =IF(D39="PENDIENTE",C39,0) -> 0
I40: =IF(D40="PENDIENTE",C40,0) -> 0

Sheet COMIGUAL HUGO
A1: FECHA | B1: REPUESTO | C1: PRECIO | D1: CONDICION | E1: FACTURA | F1: VENDEDOR | H1: FACTURA | I1: DEUDA | J1: TOTAL DEUDA | L1: ABONO | M1: FECHA AB.
A2: 43466 | B2: LIBRO | F2: OMAR | H2: =IF(E:E="NO FACTURADO","PENDIENTE","AL DIA") -> AL DIA | I2: =IF(D2="PENDIENTE",C2,0) -> 0 | J2: =SUM(I:I) -> 87500 | K2: MENU
A3: 44206 | B3: CORREA DISTRIBUCION 3L | C3: 31500 | D3: PAGADO | E3: NO | F3: DELIS | H3: AL DIA | I3: 0
A4: 44206 | B4: limpia carburador | C4: 3000 | D4: PAGADO | E4: NO | F4: OMAR | H4: =IF(E:E="NO FACTURADO","PENDIENTE","AL DIA") -> AL DIA | I4: =IF(D4="PENDIENTE",C4,0) -> 0
A5: 44206 | B5: presupuesto Nº 4799 | C5: 35000 | D5: PAGADO | F5: omar | H5: =IF(E:E="NO FACTURADO","PENDIENTE","AL DIA") -> AL DIA | I5: =IF(D5="PENDIENTE",C5,0) -> 0
A6: 44206 | B6: presupuesto 5276 | C6: 50000 | D6: PAGADO | F6: cesar | H6: =IF(E:E="NO FACTURADO","PENDIENTE","AL DIA") -> AL DIA | I6: =IF(D6="PENDIENTE",C6,0) -> 0
A7: 44206 | B7: aceite y filtro luv | C7: 20000 | D7: PAGADO | F7: cesar | H7: =IF(E:E="NO FACTURADO","PENDIENTE","AL DIA") -> AL DIA | I7: =IF(D7="PENDIENTE",C7,0) -> 0
A8: 44206 | B8: 2 anticongelante | C8: 9000 | D8: PAGADO | F8: omar | H8: =IF(E:E="NO FACTURADO","PENDIENTE","AL DIA") -> AL DIA | I8: =IF(D8="PENDIENTE",C8,0) -> 0
A9: 44206 | B9: limpia sistema admision | C9: 12000 | D9: PAGADO | F9: omar | H9: =IF(E:E="NO FACTURADO","PENDIENTE","AL DIA") -> AL DIA | I9: =IF(D9="PENDIENTE",C9,0) -> 0
A10: 44207 | B10: PLUMILLAS | C10: 14000 | D10: PAGADO | E10: NO | F10: CESAR | H10: =IF(E:E="NO FACTURADO","PENDIENTE","AL DIA") -> AL DIA | I10: =IF(D10="PENDIENTE",C10,0) -> 0 | L10: 100000 | M10: 44980
A11: 44208 | B11: 2 SELLO AGUA | C11: 1500 | D11: PAGADO | E11: NO | F11: DELIS | H11: =IF(E:E="NO FACTURADO","PENDIENTE","AL DIA") -> AL DIA | I11: =IF(D11="PENDIENTE",C11,0) -> 0
A12: 44214 | B12: PISTOLA DE IMPACTO | C12: 135000 | D12: PAGADO | E12: NO | F12: DELIS | H12: =IF(E:E="NO FACTURADO","PENDIENTE","AL DIA") -> AL DIA | I12: =IF(D12="PENDIENTE",C12,0) -> 0
A13: 44215 | B13: 2 BUJES | C13: 6000 | D13: PAGADO | E13: NO | F13: CESAR | H13: =IF(E:E="NO FACTURADO","PENDIENTE","AL DIA") -> AL DIA | I13: =IF(D13="PENDIENTE",C13,0) -> 0
A14: 44215 | B14: JUEGO EMPAQUETADURA MOTOR | C14: 38000 | D14: PAGADO | E14: NO | F14: CESAR | H14: =IF(E:E="NO FACTURADO","PENDIENTE","AL DIA") -> AL DIA | I14: =IF(D14="PENDIENTE",C14,0) -> 0
A15: 44216 | B15: PRESUPUESTO 4194 | C15: 39000 | D15: PAGADO | E15: NO | F15: DELIS | H15: =IF(E:E="NO FACTURADO","PENDIENTE","AL DIA") -> AL DIA | I15: =IF(D15="PENDIENTE",C15,0) -> 0
A16: 44228 | B16: FILTRO ACEITE | C16: 3000 | D16: PAGADO | E16: NO | F16: OMAR | H16: =IF(E:E="NO FACTURADO","PENDIENTE","AL DIA") -> AL DIA | I16: =IF(D16="PENDIENTE",C16,0) -> 0
A17: 44242 | B17: BOMBA CEBADORA | C17: 18500 | D17: PAGADO | E17: NO | F17: CESAR | H17: =IF(E:E="NO FACTURADO","PENDIENTE","AL DIA") -> AL DIA | I17: =IF(D17="PENDIENTE",C17,0) -> 0
A18: 44243 | B18: 5 SELLO AGUA 40 MM | C18: 12000 | D18: PAGADO | E18: NO | F18: CESAR | H18: =IF(E:E="NO FACTURADO","PENDIENTE","AL DIA") -> AL DIA | I18: =IF(D18="PENDIENTE",C18,0) -> 0
A19: 44244 | B19: PRESUPUESTO 4412 LANOS | C19: 40000 | D19: PAGADO | E19: NO | F19: CESAR | H19: =IF(E:E="NO FACTURADO","PENDIENTE","AL DIA") -> AL DIA | I19: =IF(D19="PENDIENTE",C19,0) -> 0
A20: 44256 | B20: ACEITE 10W40 C/ DPF | C20: 40000 | D20: PAGADO | E20: NO | F20: DELIS | H20: =IF(E:E="NO FACTURADO","PENDIENTE","AL DIA") -> AL DIA | I20: =IF(D20="PENDIENTE",C20,0) -> 0
A21: 44256 | B21: FILTRO ACEITE | C21: 8000 | D21: PAGADO | E21: NO | F21: DELIS | H21: =IF(E:E="NO FACTURADO","PENDIENTE","AL DIA") -> AL DIA | I21: =IF(D21="PENDIENTE",C21,0) -> 0
A22: 44256 | B22: 3 L 80W90 | C22: 14000 | D22: PAGADO | E22: NO | F22: OMAR | H22: =IF(E:E="NO FACTURADO","PENDIENTE","AL DIA") -> AL DIA | I22: =IF(D22="PENDIENTE",C22,0) -> 0 | L22: 100000 | M22: 44287
A23: 44256 | B23: LIQUIDO DE FRENO | C23: 3500 | D23: PAGADO | E23: NO | F23: OMAR | H23: =IF(E:E="NO FACTURADO","PENDIENTE","AL DIA") -> AL DIA | I23: =IF(D23="PENDIENTE",C23,0) -> 0
A24: 44259 | B24: 2 COOLANT (PRESUPUESTO 4427) | C24: 7000 | D24: PAGADO | E24: NO | F24: OMAR | H24: =IF(E:E="NO FACTURADO","PENDIENTE","AL DIA") -> AL DIA | I24: =IF(D24="PENDIENTE",C24,0) -> 0
A25: 44279 | B25: PRESUPUESTO N 4461 | C25: 12000 | D25: PAGADO | E25: NO | F25: OMAR | H25: =IF(E:E="NO FACTURADO","PENDIENTE","AL DIA") -> AL DIA | I25: =IF(D25="PENDIENTE",C25,0) -> 0
A26: 44279 | B26: PRESUPUESTO N 4463 | C26: 45000 | D26: PAGADO | E26: NO | F26: OMAR | H26: =IF(E:E="NO FACTURADO","PENDIENTE","AL DIA") -> AL DIA | I26: =IF(D26="PENDIENTE",C26,0) -> 0
A27: 44287 | B27: PRESUPUESTO Nº4369 | C27: 50000 | D27: PAGADO | E27: NO | F27: OMAR | H27: =IF(E:E="NO FACTURADO","PENDIENTE","AL DIA") -> AL DIA | I27: =IF(D27="PENDIENTE",C27,0) -> 0
A28: 44295 | B28: PEGAMENTO LOCTITE VIDRIO | C28: 5500 | D28: PAGADO | E28: NO | F28: CESAR | H28: =IF(E:E="NO FACTURADO","PENDIENTE","AL DIA") -> AL DIA | I28: =IF(D28="PENDIENTE",C28,0) -> 0
A29: 44306 | B29: LIQUIDO DE FRENO | C29: 4000 | D29: PAGADO | E29: no | F29: OMAR | H29: =IF(E:E="NO FACTURADO","PENDIENTE","AL DIA") -> AL DIA | I29: =IF(D29="PENDIENTE",C29,0) -> 0
A30: 44315 | B30: fusible y abrazadera | C30: 1500 | D30: PAGADO | E30: no | H30: =IF(E:E="NO FACTURADO","PENDIENTE","AL DIA") -> AL DIA | I30: =IF(D30="PENDIENTE",C30,0) -> 0
A31: 44320 | B31: PRESUPUESTO 4398 | C31: 45000 | D31: PAGADO | E31: NO | F31: OMAR | H31: =IF(E:E="NO FACTURADO","PENDIENTE","AL DIA") -> AL DIA | I31: =IF(D31="PENDIENTE",C31,0) -> 0
A32: 44322 | B32: BUJIAS SD23 PN123 | C32: 30000 | D32: PAGADO | E32: NO | F32: CESAR | H32: =IF(E:E="NO FACTURADO","PENDIENTE","AL DIA") -> AL DIA | I32: =IF(D32="PENDIENTE",C32,0) -> 0
A33: 44327 | B33: PRESUPUESTO 4955 | C33: 35000 | D33: PAGADO | E33: NO | F33: DELIS | H33: =IF(E:E="NO FACTURADO","PENDIENTE","AL DIA") -> AL DIA | I33: =IF(D33="PENDIENTE",C33,0) -> 0
A34: 44327 | B34: AFLOJATODO | C34: 2500 | D34: PAGADO | E34: NO | F34: DELIS | H34: =IF(E:E="NO FACTURADO","PENDIENTE","AL DIA") -> AL DIA | I34: =IF(D34="PENDIENTE",C34,0) -> 0
A35: 44347 | B35: PRESUPUESTO# 4964 | C35: 30500 | D35: PAGADO | E35: NO | F35: CESAR | H35: =IF(E:E="NO FACTURADO","PENDIENTE","AL DIA") -> AL DIA | I35: =IF(D35="PENDIENTE",C35,0) -> 0
A36: 44348 | B36: PRESUPUESTO Nº4517 | C36: 71900 | D36: PAGADO | E36: NO | F36: OMAR | H36: =IF(E:E="NO FACTURADO","PENDIENTE","AL DIA") -> AL DIA | I36: =IF(D36="PENDIENTE",C36,0) -> 0
A37: 44348 | B37: PRESUPUESTONº4518 | C37: 7000 | D37: PAGADO | E37: NO | F37: OMAR | H37: =IF(E:E="NO FACTURADO","PENDIENTE","AL DIA") -> AL DIA | I37: =IF(D37="PENDIENTE",C37,0) -> 0
A38: 44348 | B38: PRESUPUESTO Nº4520 | C38: 22000 | D38: PAGADO | E38: NO | F38: OMAR | H38: =IF(E:E="NO FACTURADO","PENDIENTE","AL DIA") -> AL DIA | I38: =IF(D38="PENDIENTE",C38,0) -> 0
A39: 44349 | B39: espejos yarislh/rh | C39: 60000 | D39: PAGADO | E39: NO | F39: DELIS | H39: =IF(E:E="NO FACTURADO","PENDIENTE","AL DIA") -> AL DIA | I39: =IF(D39="PENDIENTE",C39,0) -> 0
A40: 44349 | B40: GOTITA | C40: 2500 | D40: PAGADO | E40: NO | F40: DELIS | H40: =IF(E:E="NO FACTURADO","PENDIENTE","AL DIA") -> AL DIA | I40: =IF(D40="PENDIENTE",C40,0) -> 0
A41: 44355 | B41: PRESUPUESTO 4492 | C41: 11000 | D41: PAGADO | E41: NO | F41: CESAR | H41: =IF(E:E="NO FACTURADO","PENDIENTE","AL DIA") -> AL DIA | I41: =IF(D41="PENDIENTE",C41,0) -> 0
A42: 44355 | B42: PRESUPUESTO 4493 | C42: 6000 | D42: PAGADO | E42: NO | F42: CESAR | H42: =IF(E:E="NO FACTURADO","PENDIENTE","AL DIA") -> AL DIA | I42: =IF(D42="PENDIENTE",C42,0) -> 0
... A56: 44405 | B56: presupuesto 4662 | C56: 25000 | D56: PAGADO | E56: no | F56: CESAR | H56: =IF(E:E="NO FACTURADO","PENDIENTE","AL DIA") -> AL DIA | I56: =IF(D56="PENDIENTE",C56,0) -> 0
A57: 44405 | B57: anillos d21 | C57: 28000 | D57: PAGADO | E57: no | F57: cesar | I57: =IF(D57="PENDIENTE",C57,0) -> 0
A58: 44410 | B58: PRESUPUESTO 4671 | C58: 15000 | D58: PAGADO | F58: cesar | I58: =IF(D58="PENDIENTE",C58,0) -> 0
A59: 44411 | B59: PIÑON CIGÜEÑAL CORSA | C59: 14000 | D59: PAGADO | E59: NO | F59: CESAR | I59: =IF(D59="PENDIENTE",C59,0) -> 0
A60: 44418 | B60: PRESUPUESTO 4679 | C60: 35000 | D60: PAGADO | E60: NO | F60: DELIS | I60: =IF(D60="PENDIENTE",C60,0) -> 0
A61: 44418 | B61: PRESUPUESTO 4680 | C61: 3500 | D61: PAGADO | F61: DELIS | I61: =IF(D61="PENDIENTE",C61,0) -> 0
A62: 44420 | B62: PRESUPUESTO 4583 | C62: 8000 | D62: PAGADO | E62: NO | F62: OMAR | I62: =IF(D62="PENDIENTE",C62,0) -> 0 | J62: abono | K62: 200000 | L62: 44454
A63: 44446 | B63: presupuesto 4701 saldo presupuesto | C63: 8500 | D63: PAGADO | F63: OMAR | I63: =IF(D63="PENDIENTE",C63,0) -> 0
A64: 44446 | B64: filtro polen i30 | C64: 10000 | D64: PAGADO | F64: OMAR | I64: =IF(D64="PENDIENTE",C64,0) -> 0
A65: 44448 | B65: presupuesto nº 4607 | C65: 41500 | D65: PAGADO | E65: no | F65: OMAR | I65: =IF(D65="PENDIENTE",C65,0) -> 0
A66: 44469 | B66: FILTRO AIRE + LIMPIA CARBURADOR GYLLY | C66: 10000 | D66: PAGADO | F66: CESAR | I66: =IF(D66="PENDIENTE",C66,0) -> 0
A67: 44473 | B67: PASTILLA FRENO PORTER | C67: 14500 | D67: PAGADO | F67: CESAR | I67: =IF(D67="PENDIENTE",C67,0) -> 0
A68: 44482 | B68: rodamiento maza | C68: 19500 | D68: PAGADO | F68: DELIS | I68: =IF(D68="PENDIENTE",C68,0) -> 0
A69: 44483 | B69: PRESUPUESTO 4765 | C69: 25000 | D69: PAGADO | E69: NO | F69: OMAR | I69: =IF(D69="PENDIENTE",C69,0) -> 0
A70: 44484 | B70: LIMPIA CARBURADOR | C70: 4500 | D70: PAGADO | E70: NO | F70: CESAR | I70: =IF(D70="PENDIENTE",C70,0) -> 0
A71: 44484 | B71: presupuesto 4767 | C71: 41000 | D71: PAGADO | E71: no | F71: OMAR | I71: =IF(D71="PENDIENTE",C71,0) -> 0
A72: 44488 | B72: presupuesto 4769 | C72: 21000 | D72: PAGADO | E72: no | F72: OMAR | I72: =IF(D72="PENDIENTE",C72,0) -> 0
A73: 44490 | B73: PRESUPUESTO 4632 | C73: 60000 | D73: PAGADO | F73: OMAR | I73: =IF(D73="PENDIENTE",C73,0) -> 0
A74: 44495 | B74: PRESUPUESTO ROTULA H1 | C74: 10000 | D74: PAGADO | F74: CESAR | I74: 0
A75: 44503 | B75: bandejas + gomas tensoras ignis | C75: 35000 | D75: PAGADO | F75: CESAR | I75: =IF(D75="PENDIENTE",C75,0) -> 0
A76: 44509 | B76: presupuesto 4646 | C76: 72000 | D76: PAGADO | F76: CESAR | I76: =IF(D76="PENDIENTE",C76,0) -> 0
A77: 44524 | B77: EMPA MULTIPLE + LLAVE CORONA | C77: 6000 | D77: PAGADO | E77: NO | F77: CESAR | I77: =IF(D77="PENDIENTE",C77,0) -> 0
A78: 44525 | B78: mantencion navara san juan | C78: 60000 | D78: PAGADO | E78: no | F78: CESAR | I78: =IF(D78="PENDIENTE",C78,0) -> 0
A79: 44525 | B79: distribucion h100 | C79: 40000 | D79: PAGADO | E79: no | F79: CESAR | I79: =IF(D79="PENDIENTE",C79,0) -> 0
A80: 44529 | B80: ACEITE 80/90 | C80: 15000 | D80: PAGADO | E80: NO | F80: CESAR | I80: =IF(D80="PENDIENTE",C80,0) -> 0
A81: 44530 | B81: presupuesto nº4776 | C81: 30000 | D81: PAGADO | E81: no | F81: omar | I81: =IF(D81="PENDIENTE",C81,0) -> 0
A82: 44567 | B82: presupuesto 5435 | C82: 75000 | D82: PAGADO | F82: CESAR | I82: =IF(D82="PENDIENTE",C82,0) -> 0
A83: 44578 | B83: presupuesto nº4901 | C83: 15000 | D83: PAGADO | E83: no | F83: OMAR | I83: =IF(D83="PENDIENTE",C83,0) -> 0
A84: 44582 | B84: LIQUIDO DE FRENO | C84: 4000 | D84: PAGADO | E84: NO | F84: CESAR | I84: =IF(D84="PENDIENTE",C84,0) -> 0
A85: 44585 | B85: presupuesto 4821 | C85: 65000 | D85: PAGADO | E85: no | F85: CESAR | I85: =IF(D85="PENDIENTE",C85,0) -> 0
A86: 44599 | B86: presupuesto 4872 | C86: 25000 | D86: PAGADO | F86: CESAR | I86: =IF(D86="PENDIENTE",C86,0) -> 0
A87: 44599 | B87: gasket | C87: 3500 | D87: PAGADO | F87: CESAR | I87: =IF(D87="PENDIENTE",C87,0) -> 0
A88: 44600 | B88: PRESUPUESTONº4911 | C88: 6000 | D88: PAGADO | E88: NO | F88: OMAR | I88: =IF(D88="PENDIENTE",C88,0) -> 0
A89: 44603 | B89: PRESUPUESTO Nº4915 | C89: 19000 | D89: PAGADO | F89: OMAR | I89: =IF(D89="PENDIENTE",C89,0) -> 0
A90: 44609 | B90: PRESUPUESTO 4833 | C90: 11000 | D90: PAGADO | F90: CESAR | I90: =IF(D90="PENDIENTE",C90,0) -> 0
A91: 44614 | B91: presupuesto 4831 | C91: 5000 | D91: PAGADO | F91: CESAR | I91: =IF(D91="PENDIENTE",C91,0) -> 0
A92: 44636 | B92: aceite 75w90 | C92: 20000 | D92: PAGADO | F92: cesar | I92: =IF(D92="PENDIENTE",C92,0) -> 0
A93: 44638 | B93: aditivo caja | C93: 20000 | D93: PAGADO | F93: CESAR | I93: =IF(D93="PENDIENTE",C93,0) -> 0
A94: 44641 | B94: PRESUPUESTO VG33 N4841 | C94: 56000 | D94: PAGADO | F94: CESAR | I94: =IF(D94="PENDIENTE",C94,0) -> 0 | J94: abono | K94: 100000 | L94: 44672
A95: 44641 | B95: PRESUPUESTO 4849 | C95: 35000 | D95: PAGADO | F95: CESAR | I95: =IF(D95="PENDIENTE",C95,0) -> 0
A96: 44659 | B96: PRESUPUESTO 5063 | C96: 18500 | D96: PAGADO | F96: CESAR | I96: =IF(D96="PENDIENTE",C96,0) -> 0
A97: 44664 | B97: COOLANT | C97: 9000 | D97: pagado | E97: NO | F97: CESAR | I97: =IF(D97="PENDIENTE",C97,0) -> 0
A98: 44672 | B98: empa. Motor d21 toto | C98: 28000 | D98: PAGADO | E98: no | F98: omar | I98: =IF(D98="PENDIENTE",C98,0) -> 0
A99: 44697 | B99: empa. Motor d21 toto | C99: 45000 | D99: PAGADO | F99: delis | I99: =IF(D99="PENDIENTE",C99,0) -> 0
A100: 44701 | B100: radiador galloper + tapa | C100: 51500 | D100: PAGADO | F100: DELIS | I100: =IF(D100="PENDIENTE",C100,0) -> 0
A101: 44704 | B101: CORREA A-46 | C101: 6000 | D101: PAGADO | F101: DELIS | I101: =IF(D101="PENDIENTE",C101,0) -> 0
A102: 44712 | B102: liquido refrigerante+ROS OFF | C102: 9000 | D102: PAGADO | F102: delis | I102: =IF(D102="PENDIENTE",C102,0) -> 0
A103: 44721 | B103: liquido refrigerante x 2 | C103: 9000 | D103: PAGADO | F103: DELIS | I103: =IF(D103="PENDIENTE",C103,0) -> 0
A104: 44727 | B104: axiales 2 ampolleta | C104: 35500 | D104: PAGADO | F104: OMAR | I104: =IF(D104="PENDIENTE",C104,0) -> 0
A105: 44734 | B105: presupuesto 10546 | C105: 100000 | D105: PAGADO | F105: cesar | I105: =IF(D105="PENDIENTE",C105,0) -> 0
A106: 44746 | B106: liquido refrigerante | C106: 13500 | D106: PAGADO | F106: DELIS | I106: =IF(D106="PENDIENTE",C106,0) -> 0
A107: 44763 | B107: presupuesto 5235 | C107: 39500 | D107: PAGADO | F107: CESAR | I107: =IF(D107="PENDIENTE",C107,0) -> 0
A108: 44769 | B108: presupuesto 5240 | C108: 13000 | D108: PAGADO | F108: CESAR | I108: =IF(D108="PENDIENTE",C108,0) -> 0
A109: 44769 | B109: presupuesto 5241 | C109: 25000 | D109: PAGADO | F109: CESAR | I109: =IF(D109="PENDIENTE",C109,0) -> 0
A110: 44775 | B110: presupuesto 5175 | C110: 12000 | D110: PAGADO | F110: omar | I110: =IF(D110="PENDIENTE",C110,0) -> 0
... A140: 44951 | B140: PREUSPUESTO 5605 | C140: 25000 | D140: PAGADO | F140: OMAR | I140: =IF(D140="PENDIENTE",C140,0) -> 0
A141: 44967 | B141: PRESUPUESTO 5591 | C141: 10000 | D141: PAGADO | F141: CESAR | I141: =IF(D141="PENDIENTE",C141,0) -> 0 | K141: abono $100000 | L141: 44984
A142: 44967 | B142: PRESUPUESTO 5590 ABONO 14/02 100.000 MONTO ORIGINAL: 130000 | C142: 30000 | D142: PAGADO | F142: CESAR | I142: =IF(D142="PENDIENTE",C142,0) -> 0
...

Sheet DEL RIO LORCA EMERSON
A1: FECHA | B1: REPUESTO | C1: PRECIO | D1: CONDICION | E1: FACTURA | F1: VENDEDOR | H1: FACTURA | I1: DEUDA | J1: TOTAL DEUDA
B2: SALDO | D2: PENDIENTE | E2: NO | F2: OMAR | H2: =IF(E:E="NO FACTURADO","PENDIENTE","AL DIA") -> AL DIA | I2: =IF(D2="PENDIENTE",C2,0) -> 0 | J2: =SUM(I:I) -> 130000 | K2: MENU
A3: 44247 | B3: BATERIA 90 AMP | C3: 110000 | E3: NO | I3: =IF(D3="PENDIENTE",C3,0) -> 0
B4: AMPOLLETA | C4: 5000 | E4: NO | I4: =IF(D4="PENDIENTE",C4,0) -> 0
B5: 4 BUJIA INCANDESCENTE | C5: 40000 | E5: NO | I5: =IF(D5="PENDIENTE",C5,0) -> 0
A6: 44250 | B6: 2 HOMOCINETICA LADO CAJA | C6: 90000 | D6: PENDIENTE | E6: NO | F6: DELIS | I6: =IF(D6="PENDIENTE",C6,0) -> 90000 | K6: abono 50000 | L6: 45070
A7: 45070 | B7: SALDO BATERIA ACCENT SAMUEL ALVAREZ | C7: 40000 | D7: PENDIENTE | I7: =IF(D7="PENDIENTE",C7,0) -> 40000
I8: =IF(D8="PENDIENTE",C8,0) -> 0
I9: =IF(D9="PENDIENTE",C9,0) -> 0
I10: =IF(D10="PENDIENTE",C10,0) -> 0
I11: =IF(D11="PENDIENTE",C11,0) -> 0
I12: =IF(D12="PENDIENTE",C12,0) -> 0
I13: =IF(D13="PENDIENTE",C13,0) -> 0
I14: =IF(D14="PENDIENTE",C14,0) -> 0
I15: =IF(D15="PENDIENTE",C15,0) -> 0
I16: =IF(D16="PENDIENTE",C16,0) -> 0
I17: =IF(D17="PENDIENTE",C17,0) -> 0
I18: =IF(D18="PENDIENTE",C18,0) -> 0
I19: =IF(D19="PENDIENTE",C19,0) -> 0
... I45: =IF(D45="PENDIENTE",C45,0) -> 0

Sheet DELGADO PATRICIO (RAPIDO Y FUR)
A1: FECHA | B1: REPUESTO | C1: PRECIO | D1: CONDICION | E1: FACTURA | F1: VENDEDOR | H1: FACTURA | I1: DEUDA | J1: TOTAL DEUDA
A2: 44130 | B2: SALDO | D2: PENDIENTE | E2: NO | F2: OMAR | H2: =IF(E:E="NO FACTURADO","PENDIENTE","AL DIA") -> AL DIA | I2: =IF(D2="PENDIENTE",C2,0) -> 0 | J2: =SUM(I:I) -> 0 | K2: MENU
A3: 44210 | B3: 2 HOMOCINETICA saldo | C3: 6000 | D3: pagado | E3: NO | F3: CESAR | I3: =IF(D3="PENDIENTE",C3,0) -> 0
A4: 44293 | B4: HOMOCINETICA LADO CAJA V16 | C4: 20000 | D4: pagado | E4: NO | F4: CESAR | I4: =IF(D4="PENDIENTE",C4,0) -> 0
A5: 44320 | B5: HOMOCINETICA V16 | C5: 20000 | D5: pagado | E5: NO | F5: CESAR | I5: =IF(D5="PENDIENTE",C5,0) -> 0
A6: 44421 | B6: JGO DISCOS+PASTILLAS | C6: 37000 | D6: pagado | E6: NO | F6: CESAR | I6: =IF(D6="PENDIENTE",C6,0) -> 0
I7: =IF(D7="PENDIENTE",C7,0) -> 0
I8: =IF(D8="PENDIENTE",C8,0) -> 0
I9: =IF(D9="PENDIENTE",C9,0) -> 0
I10: =IF(D10="PENDIENTE",C10,0) -> 0
I11: =IF(D11="PENDIENTE",C11,0) -> 0
I12: =IF(D12="PENDIENTE",C12,0) -> 0
I13: =IF(D13="PENDIENTE",C13,0) -> 0
I14: =IF(D14="PENDIENTE",C14,0) -> 0
I15: =IF(D15="PENDIENTE",C15,0) -> 0
I16: =IF(D16="PENDIENTE",C16,0) -> 0
I17: =IF(D17="PENDIENTE",C17,0) -> 0
I18: =IF(D18="PENDIENTE",C18,0) -> 0
... I40: =IF(D40="PENDIENTE",C40,0) -> 0

Sheet FOLLERT CARDENAS JOSE
A1: FECHA | B1: REPUESTO | C1: PRECIO | D1: CONDICION | E1: FACTURA | F1: VENDEDOR | H1: FACTURA | I1: DEUDA | J1: TOTAL DEUDA
B2: SALDO | D2: PENDIENTE | E2: NO | F2: OMAR | H2: =IF(E:E="NO FACTURADO","PENDIENTE","AL DIA") -> AL DIA | I2: =IF(D2="PENDIENTE",C2,0) -> 0 | J2: =SUM(I:I) -> 0 | K2: MENU
A3: 44225 | B3: BATERIA 90 AMP | C3: 120000 | D3: PAGADO | E3: NO FACTURADO | F3: DELIS | H3: =IF(E:E="NO FACTURADO","PENDIENTE","AL DIA") -> PENDIENTE | I3: =IF(D3="PENDIENTE",C3,0) -> 0
A4: 44225 | B4: LIMPIEZA INYECTORES | C4: 20000 | D4: PAGADO | E4: NO FACTURADO | F4: DELIS | H4: =IF(E:E="NO FACTURADO","PENDIENTE","AL DIA") -> PENDIENTE | I4: =IF(D4="PENDIENTE",C4,0) -> 0
H5: =IF(E:E="NO FACTURADO","PENDIENTE","AL DIA") -> AL DIA | I5: =IF(D5="PENDIENTE",C5,0) -> 0
H6: =IF(E:E="NO FACTURADO","PENDIENTE","AL DIA") -> AL DIA | I6: =IF(D6="PENDIENTE",C6,0) -> 0
H7: =IF(E:E="NO FACTURADO","PENDIENTE","AL DIA") -> AL DIA | I7: =IF(D7="PENDIENTE",C7,0) -> 0
H8: =IF(E:E="NO FACTURADO","PENDIENTE","AL DIA") -> AL DIA | I8: =IF(D8="PENDIENTE",C8,0) -> 0
I9: =IF(D9="PENDIENTE",C9,0) -> 0
I10: =IF(D10="PENDIENTE",C10,0) -> 0
I11: =IF(D11="PENDIENTE",C11,0) -> 0
I12: =IF(D12="PENDIENTE",C12,0) -> 0
I13: =IF(D13="PENDIENTE",C13,0) -> 0
I14: =IF(D14="PENDIENTE",C14,0) -> 0
I15: =IF(D15="PENDIENTE",C15,0) -> 0
I16: =IF(D16="PENDIENTE",C16,0) -> 0
I17: =IF(D17="PENDIENTE",C17,0) -> 0
I18: =IF(D18="PENDIENTE",C18,0) -> 0
I19: =IF(D19="PENDIENTE",C19,0) -> 0
I20: =IF(D20="PENDIENTE",C20,0) -> 0
... I40: =IF(D40="PENDIENTE",C40,0) -> 0

Sheet GALLARDO ARMANDO
A1: FECHA | B1: REPUESTO | C1: PRECIO | D1: CONDICION | E1: FACTURA | F1: VENDEDOR | H1: FACTURA | I1: DEUDA | J1: TOTAL DEUDA
B2: SALDO | D2: PENDIENTE | E2: NO | F2: OMAR | H2: =IF(E:E="NO FACTURADO","PENDIENTE","AL DIA") -> AL DIA | I2: =IF(D2="PENDIENTE",C2,0) -> 0 | J2: =SUM(I:I) -> 0 | K2: MENU
A3: 44236 | B3: ANILLO STD CORSA | C3: 30000 | D3: duda | E3: NO | F3: DELIS | I3: =IF(D3="PENDIENTE",C3,0) -> 0
A4: 44362 | B4: JG. EMPA MOTOR | C4: 30000 | D4: duda | E4: NO | I4: =IF(D4="PENDIENTE",C4,0) -> 0
A5: 44810 | B5: jgo valvula santamo | C5: 70000 | D5: pagado | F5: delis | I5: =IF(D5="PENDIENTE",C5,0) -> 0
I6: =IF(D6="PENDIENTE",C6,0) -> 0
I7: =IF(D7="PENDIENTE",C7,0) -> 0
I8: =IF(D8="PENDIENTE",C8,0) -> 0
I9: =IF(D9="PENDIENTE",C9,0) -> 0
I10: =IF(D10="PENDIENTE",C10,0) -> 0
I11: =IF(D11="PENDIENTE",C11,0) -> 0
I12: =IF(D12="PENDIENTE",C12,0) -> 0
I13: =IF(D13="PENDIENTE",C13,0) -> 0
I14: =IF(D14="PENDIENTE",C14,0) -> 0
I15: =IF(D15="PENDIENTE",C15,0) -> 0
I16: =IF(D16="PENDIENTE",C16,0) -> 0
I17: =IF(D17="PENDIENTE",C17,0) -> 0
... I40: =IF(D40="PENDIENTE",C40,0) -> 0

Sheet GONZALEZ NELSON
A1: P | B1: REPUESTO | C1: PRECIO | D1: CONDICION | E1: FACTURA | F1: VENDEDOR | H1: FACTURA | I1: DEUDA | J1: TOTAL DEUDA
A2: 44004 | B2: SALDO JUEGO PASTILLA HONDA (TOTAL 40.000) | C2: 3500 | D2: PAGADO | E2: BOLETA | F2: OMAR | H2: =IF(E:E="NO FACTURADO","PENDIENTE","AL DIA") -> AL DIA | I2: =IF(D2="PENDIENTE",C2,0) -> 0 | J2: =SUM(I:I) -> 25000 | K2: MENU
A3: 44257 | B3: PRESUPUESTO N 4423 | C3: 3500 | D3: PAGADO | E3: NO | F3: OMAR | I3: =IF(D3="PENDIENTE",C3,0) -> 0
A4: 44258 | B4: PRESUPUESTO N 4451 | C4: 17000 | D4: PAGADO | E4: NO | F4: OMAR | I4: =IF(D4="PENDIENTE",C4,0) -> 0
A5: 44354 | B5: CRUCETA | C5: 11000 | D5: PAGADO | F5: DELIS | I5: =IF(D5="PENDIENTE",C5,0) -> 0
A6: 44354 | B6: BOMBA DE BENCINA | C6: 21000 | D6: PAGADO | E6: NO | F6: CESAR | I6: =IF(D6="PENDIENTE",C6,0) -> 0
A7: 44431 | B7: PRESUPUESTO Nº 4693 | C7: 163500 | D7: PAGADO | E7: NO | F7: CESAR | I7: =IF(D7="PENDIENTE",C7,0) -> 0
A8: 44539 | B8: presupuesto nº 4779 | C8: 146000 | D8: PAGADO | F8: cesar | I8: =IF(D8="PENDIENTE",C8,0) -> 0
A9: 44581 | B9: saldo limpiador mariposa | C9: 4000 | D9: PAGADO | E9: no | F9: OMAR | I9: =IF(D9="PENDIENTE",C9,0) -> 0
A10: 44582 | B10: PRESUPUESTO Nº 4905 | C10: 8000 | D10: PAGADO | E10: no | F10: OMAR | I10: =IF(D10="PENDIENTE",C10,0) -> 0
A11: 44638 | B11: aceite sail hija | C11: 20000 | D11: PAGADO | F11: CESAR | I11: =IF(D11="PENDIENTE",C11,0) -> 0
A12: 44706 | B12: saldo bateria | C12: 10000 | D12: PAGADO | F12: CESAR | I12: =IF(D12="PENDIENTE",C12,0) -> 0
A13: 44683 | B13: bujias 2 juegos | C13: 20000 | D13: PAGADO | F13: CESAR | I13: =IF(D13="PENDIENTE",C13,0) -> 0
A14: 44701 | B14: platino + condensador | C14: 9000 | D14: PAGADO | F14: CESAR | I14: =IF(D14="PENDIENTE",C14,0) -> 0
A15: 44753 | B15: presupuesto nº5224 | C15: 88000 | D15: PAGADO | F15: DELIS | I15: =IF(D15="PENDIENTE",C15,0) -> 0
A16: 44757 | B16: filtro petroleo l200 2.5 2009 | C16: 5000 | D16: PAGADO | F16: OMAR | I16: =IF(D16="PENDIENTE",C16,0) -> 0
A17: 44775 | B17: presupuesto 5251 + filtro aire | C17: 21000 | D17: PAGADO | F17: DELIS | I17: =IF(D17="PENDIENTE",C17,0) -> 0
A18: 44796 | B18: PRESUPUESTO 5189 | C18: 76000 | D18: PAGADO | F18: OMAR | I18: =IF(D18="PENDIENTE",C18,0) -> 0
A19: 44809 | B19: presupuesto nº5199 | C19: 72000 | D19: PAGADO | F19: OMAR | I19: =IF(D19="PENDIENTE",C19,0) -> 0
A20: 44816 | B20: RETEN SUZUKI AXIAL HYUNDAI | C20: 18000 | D20: PAGADO | F20: DELIS | I20: =IF(D20="PENDIENTE",C20,0) -> 0
A21: 44817 | B21: AMORTIGUADOR ACCENT (30.000 orig, dcto 15 por rod) | C21: 5000 | D21: PAGADO | F21: CESAR | I21: =IF(D21="PENDIENTE",C21,0) -> 0 | K21: abono venta bandeja $6000 ABONO$ BOMBA IGNIS
A22: 44832 | B22: presupuesto 5308 | C22: 20000 | D22: PAGADO | F22: OMAR | I22: =IF(D22="PENDIENTE",C22,0) -> 0
A23: 44981 | B23: juego bujias rc21 | C23: 14000 | D23: PAGADO | F23: NATALIA | I23: =IF(D23="PENDIENTE",C23,0) -> 0
A24: 44984 | B24: BANDEJA APV | C24: 26000 | D24: PAGADO | F24: CESAR | I24: =IF(D24="PENDIENTE",C24,0) -> 0 | K24: ABONO $30000 06/09/2023
A25: 45000 | B25: SELLA RADIADOR | C25: 8000 | D25: PAGADO | F25: DELIS | I25: =IF(D25="PENDIENTE",C25,0) -> 0
A26: 45000 | B26: saldo valvula petroleo | C26: 15000 | D26: PENDIENTE | F26: DELIS | I26: =IF(D26="PENDIENTE",C26,0) -> 15000
A27: 45051 | B27: BUJIAS S10 CONDICIONAL | C27: 22000 | D27: DEVOLUCION | F27: CESAR | I27: =IF(D27="PENDIENTE",C27,0) -> 0
A28: 45229 | B28: bujias | C28: 10000 | D28: PAGADO | I28: =IF(D28="PENDIENTE",C28,0) -> 0
A29: 45234 | B29: bobina | C29: 30000 | D29: PAGADO | I29: =IF(D29="PENDIENTE",C29,0) -> 0
A30: 45310 | B30: presupuesto 6042 | C30: 50000 | D30: PAGADO | I30: =IF(D30="PENDIENTE",C30,0) -> 0
A31: 45348 | B31: presupuesto 6108 | C31: 64000 | D31: PAGADO | I31: =IF(D31="PENDIENTE",C31,0) -> 0
A32: 45440 | B32: jgo bujias rc21 | C32: 12000 | D32: PAGADO | I32: =IF(D32="PENDIENTE",C32,0) -> 0
A33: 45567 | B33: INYECTORES LUV 2,2 | C33: 60000 | D33: DEVOLUCION | I33: =IF(D33="PENDIENTE",C33,0) -> 0
A34: 45618 | B34: RETEN SUZUKI | C34: 6500 | D34: DEVOLUCION | I34: =IF(D34="PENDIENTE",C34,0) -> 0
A35: 45646 | B35: DISCO FRENO Y PASTILLA | C35: 35000 | D35: PAGADO | I35: =IF(D35="PENDIENTE",C35,0) -> 0
A36: 45663 | B36: jgo bujias fr7dcx | C36: 10000 | D36: PENDIENTE | I36: =IF(D36="PENDIENTE",C36,0) -> 10000
I37: =IF(D37="PENDIENTE",C37,0) -> 0
I38: =IF(D38="PENDIENTE",C38,0) -> 0
I39: =IF(D39="PENDIENTE",C39,0) -> 0
I40: =IF(D40="PENDIENTE",C40,0) -> 0

Sheet GUERRERO RODRIGO
A1: FECHA | B1: REPUESTO | C1: PRECIO | D1: CONDICION | E1: FACTURA | F1: VENDEDOR | H1: FACTURA | I1: DEUDA | J1: TOTAL DEUDA
B2: SALDO | D2: PENDIENTE | E2: NO | F2: OMAR | H2: =IF(E:E="NO FACTURADO","PENDIENTE","AL DIA") -> AL DIA | I2: =IF(D2="PENDIENTE",C2,0) -> 0 | J2: =SUM(I:I) -> 0 | K2: MENU
A3: 44239 | B3: JUEGO DISCOS FRENO | C3: 50000 | D3: ABONO | E3: NO | I3: =((IF(D3="PENDIENTE",C3,0))*OR(IF(D3="ABONO",-C3,0))) -> 0
A4: 44239 | B4: ACEITE, LIQUIDO DE FRENO Y ROST-OFF | C4: 41500 | D4: PAGADO | E4: NO | I4: =IF(D4="PENDIENTE",C4,0) -> 0
B5: FILTRO ACEITE | C5: 4000 | D5: PAGADO | E5: NO | F5: CESAR | I5: =IF(D5="PENDIENTE",C5,0) -> 0
I6: =IF(D6="PENDIENTE",C6,0) -> 0
I7: =IF(D7="PENDIENTE",C7,0) -> 0
I8: =IF(D8="PENDIENTE",C8,0) -> 0
I9: =IF(D9="PENDIENTE",C9,0) -> 0
I10: =IF(D10="PENDIENTE",C10,0) -> 0
I11: =IF(D11="PENDIENTE",C11,0) -> 0
I12: =IF(D12="PENDIENTE",C12,0) -> 0
I13: =IF(D13="PENDIENTE",C13,0) -> 0
I14: =IF(D14="PENDIENTE",C14,0) -> 0
I15: =IF(D15="PENDIENTE",C15,0) -> 0
I16: =IF(D16="PENDIENTE",C16,0) -> 0
I17: =IF(D17="PENDIENTE",C17,0) -> 0
... I40: =IF(D40="PENDIENTE",C40,0) -> 0

Sheet HINOSTROZA MOISES (LA CUMBRE)
A1: FECHA | B1: REPUESTO | C1: PRECIO | D1: CONDICION | E1: FACTURA | F1: VENDEDOR | H1: FACTURA | I1: DEUDA | J1: TOTAL DEUDA
A2: 44284 | B2: SALDO BATERIA | C2: 20000 | D2: pagado | E2: NO | F2: OMAR | H2: =IF(E:E="NO FACTURADO","PENDIENTE","AL DIA") -> AL DIA | I2: =IF(D2="PENDIENTE",C2,0) -> 0 | J2: =SUM(I:I) -> 0 | K2: MENU
I3: 0
I4: =IF(D3="PENDIENTE",C3,0) -> 0
I5: =IF(D4="PENDIENTE",C4,0) -> 0
I6: =IF(D5="PENDIENTE",C5,0) -> 0
I7: =IF(D6="PENDIENTE",C6,0) -> 0
I8: =IF(D7="PENDIENTE",C7,0) -> 0
I9: =IF(D8="PENDIENTE",C8,0) -> 0
I10: =IF(D9="PENDIENTE",C9,0) -> 0
I11: =IF(D10="PENDIENTE",C10,0) -> 0
I12: =IF(D11="PENDIENTE",C11,0) -> 0
I13: =IF(D12="PENDIENTE",C12,0) -> 0
I14: =IF(D13="PENDIENTE",C13,0) -> 0
I15: =IF(D14="PENDIENTE",C14,0) -> 0
... I37: =IF(D36="PENDIENTE",C36,0) -> 0

Sheet HUALA CARLOS
A1: FECHA | B1: REPUESTO | C1: PRECIO | D1: CONDICION | E1: FACTURA | F1: VENDEDOR | H1: FACTURA | I1: DEUDA | J1: TOTAL DEUDA
B2: SALDO | D2: PENDIENTE | E2: NO | F2: OMAR | H2: =IF(E:E="NO FACTURADO","PENDIENTE","AL DIA") -> AL DIA | I2: =IF(D2="PENDIENTE",C2,0) -> 0 | J2: =SUM(I:I) -> 0 | K2: MENU
A3: 44277 | B3: JUEGO PASTILLA | C3: 12000 | D3: pagado | F3: OMAR | I3: =IF(D3="PENDIENTE",C3,0) -> 0
A4: 44743 | B4: piola freno MANO 2Y | C4: 50000 | D4: pagado | E4: NO | F4: DELIS | I4: =IF(D4="PENDIENTE",C4,0) -> 0
A5: 44840 | B5: BORNE BATERIA | C5: 3900 | D5: pagado | F5: CESAR | I5: =IF(D5="PENDIENTE",C5,0) -> 0
A6: 44872 | B6: presupiesto 5397 | C6: 51900 | D6: pagado | F6: delis | I6: =IF(D6="PENDIENTE",C6,0) -> 0
A7: 44880 | B7: REPUESTOS TOYOTA | C7: 52000 | D7: pagado | F7: CESAR | I7: =IF(D7="PENDIENTE",C7,0) -> 0
A8: 44913 | B8: empaquetadura culata corsa | C8: 10000 | D8: pagado | F8: CESAR | I8: =IF(D8="PENDIENTE",C8,0) -> 0
A9: 44971 | B9: cruceta | C9: 10000 | D9: pagado | F9: CESAR | I9: =IF(D9="PENDIENTE",C9,0) -> 0
A10: 44988 | B10: jgo bujias platino condensador | C10: 19000 | D10: pagado | F10: CESAR | I10: =IF(D10="PENDIENTE",C10,0) -> 0
A11: 45030 | B11: CONDENSADOR Y PLATINO | C11: 10000 | D11: pagado | F11: CESAR | I11: =IF(D11="PENDIENTE",C11,0) -> 0
A12: 45055 | B12: EMPAQUETADURA TAPA VALVULA | C12: 7000 | D12: pagado | F12: CESAR | I12: =IF(D12="PENDIENTE",C12,0) -> 0
A13: 45090 | B13: ACEITE BUJIAS | C13: 42000 | D13: pagado | F13: CESAR | I13: =IF(D13="PENDIENTE",C13,0) -> 0
A14: 45286 | B14: ceramol | C14: 10000 | D14: pagado | F14: DELIS | I14: =IF(D14="PENDIENTE",C14,0) -> 0
A15: 45289 | B15: platino y condensador | C15: 9000 | D15: pagado | I15: =IF(D15="PENDIENTE",C15,0) -> 0
A16: 45373 | B16: aceite 20w50 | C16: 18000 | D16: pagado | F16: cesar | I16: =IF(D16="PENDIENTE",C16,0) -> 0
A17: 45457 | B17: bateria 55 amp | C17: 50000 | D17: pagado | I17: =IF(D17="PENDIENTE",C17,0) -> 0
A18: 45495 | B18: PRESUPUESTO 6311 | C18: 45000 | D18: pagado | I18: =IF(D18="PENDIENTE",C18,0) -> 0
A19: 45623 | B19: TERMOSTATO | C19: 15000 | D19: pagado | I19: =IF(D19="PENDIENTE",C19,0) -> 0
A20: 45652 | B20: cuerpo mariposa optra | C20: 90000 | D20: pagado | I20: =IF(D20="PENDIENTE",C20,0) -> 0
A21: 45660 | B21: jgo patines sail | C21: 28000 | D21: pagado | I21: =IF(D21="PENDIENTE",C21,0) -> 0
A22: 45663 | B22: rodamiento del sail | C22: 10000 | D22: pagado | I22: =IF(D22="PENDIENTE",C22,0) -> 0
I23: =IF(D23="PENDIENTE",C23,0) -> 0
I24: =IF(D24="PENDIENTE",C24,0) -> 0
I25: =IF(D25="PENDIENTE",C25,0) -> 0
I26: =IF(D26="PENDIENTE",C26,0) -> 0
I27: =IF(D27="PENDIENTE",C27,0) -> 0
I28: =IF(D28="PENDIENTE",C28,0) -> 0
I29: =IF(D29="PENDIENTE",C29,0) -> 0
I30: =IF(D30="PENDIENTE",C30,0) -> 0
I31: =IF(D31="PENDIENTE",C31,0) -> 0
I32: =IF(D32="PENDIENTE",C32,0) -> 0
I33: =IF(D33="PENDIENTE",C33,0) -> 0
I34: =IF(D34="PENDIENTE",C34,0) -> 0
... I37: =IF(D37="PENDIENTE",C37,0) -> 0

Sheet MALDONADO MOISES
A1: FECHA | B1: REPUESTO | C1: PRECIO | D1: CONDICION | E1: ABONO | F1: FACTURA | G1: VENDEDOR | I1: FACTURA | J1: DEUDA
A2: 44265 | B2: PRESUPUESTO 4324 | C2: 84000 | D2: PAGADO | F2: FACTURADO | G2: OMAR | I2: =IF(F:F="NO FACTURADO","PENDIENTE","AL DIA") -> AL DIA | J2: =IF(D2="PENDIENTE",C2,0) -> 0 | L2: MENU
A3: 44265 | B3: PRESUPUESTO 4325 | C3: 106000 | D3: PAGADO | F3: FACTURADO | G3: CESAR | I3: =IF(F:F="NO FACTURADO","PENDIENTE","AL DIA") -> AL DIA | J3: =IF(D3="PENDIENTE",C3,0) -> 0
A4: 44265 | B4: PRESUPUESTO 4326 | C4: 67000 | D4: PAGADO | F4: FACTURADO | G4: CESAR | I4: =IF(F:F="NO FACTURADO","PENDIENTE","AL DIA") -> AL DIA | J4: =IF(D4="PENDIENTE",C4,0) -> 0
A5: 44265 | B5: PRESUPUESTO 4327 | C5: 134000 | D5: PAGADO | F5: FACTURADO | G5: CESAR | I5: =IF(F:F="NO FACTURADO","PENDIENTE","AL DIA") -> AL DIA | J5: =IF(D5="PENDIENTE",C5,0) -> 0
A6: 44265 | B6: PRESUPUESTO 4328 | C6: 36000 | D6: PAGADO | F6: FACTURADO | G6: CESAR | I6: =IF(F:F="NO FACTURADO","PENDIENTE","AL DIA") -> AL DIA | J6: =IF(D6="PENDIENTE",C6,0) -> 0 | K6: TOTAL DEUDA
A7: 44265 | C7: 133000 | D7: PAGADO | F7: FACTURADO | G7: CESAR | I7: =IF(F:F="NO FACTURADO","PENDIENTE","AL DIA") -> AL DIA | J7: =IF(D7="PENDIENTE",C7,0) -> 0 | K7: =SUM(J:J) -> 0
A8: 44268 | B8: JUEGO DE METALES | C8: 48000 | D8: PAGADO | F8: FACTURADO | G8: CESAR | I8: =IF(F:F="NO FACTURADO","PENDIENTE","AL DIA") -> AL DIA | J8: =IF(D8="PENDIENTE",C8,0) -> 0
A9: 44269 | B9: PRESUPUESTO Nº 4378 | C9: 348000 | D9: PAGADO | F9: NO FACTURADO | G9: CESAR | I9: =IF(F:F="NO FACTURADO","PENDIENTE","AL DIA") -> PENDIENTE | J9: =IF(D9="PENDIENTE",C9,0) -> 0
A10: 44308 | B10: JGO PISTON STD TOYOTA 2T (95.000) | C10: 50000 | D10: PAGADO | F10: NO FACTURADO | G10: CESAR | I10: =IF(F:F="NO FACTURADO","PENDIENTE","AL DIA") -> PENDIENTE | J10: =IF(D10="PENDIENTE",C10,0) -> 0
J11: =IF(D11="PENDIENTE",C11,0) -> 0
J12: =IF(D12="PENDIENTE",C12,0) -> 0
J13: =IF(D13="PENDIENTE",C13,0) -> 0
J14: =IF(D14="PENDIENTE",C14,0) -> 0
J15: =IF(D15="PENDIENTE",C15,0) -> 0
J16: =IF(D16="PENDIENTE",C16,0) -> 0
J17: =IF(D17="PENDIENTE",C17,0) -> 0
J18: =IF(D18="PENDIENTE",C18,0) -> 0
J19: =IF(D19="PENDIENTE",C19,0) -> 0
J20: =IF(D20="PENDIENTE",C20,0) -> 0
J21: =IF(D21="PENDIENTE",C21,0) -> 0
J22: =IF(D22="PENDIENTE",C22,0) -> 0
... J40: =IF(D40="PENDIENTE",C40,0) -> 0

Sheet MARTINEZ EDUARDO (FUSCHLOCHER)
A1: FECHA | B1: REPUESTO | C1: PRECIO | D1: CONDICION | E1: FACTURA | F1: VENDEDOR | H1: FACTURA | I1: DEUDA | J1: TOTAL DEUDA
F2: OMAR | I2: =IF(D2="PENDIENTE",C2,0) -> 0 | J2: =SUM(I:I) -> 0 | K2: MENU
I3: =IF(D3="PENDIENTE",C3,0) -> 0
I4: =IF(D4="PENDIENTE",C4,0) -> 0
I5: =IF(D5="PENDIENTE",C5,0) -> 0
I6: =IF(D6="PENDIENTE",C6,0) -> 0
I7: =IF(D7="PENDIENTE",C7,0) -> 0
I8: =IF(D8="PENDIENTE",C8,0) -> 0
I9: =IF(D9="PENDIENTE",C9,0) -> 0
I10: =IF(D10="PENDIENTE",C10,0) -> 0
I11: =IF(D11="PENDIENTE",C11,0) -> 0
I12: =IF(D12="PENDIENTE",C12,0) -> 0
I13: =IF(D13="PENDIENTE",C13,0) -> 0
I14: =IF(D14="PENDIENTE",C14,0) -> 0
... I40: =IF(D40="PENDIENTE",C40,0) -> 0

Sheet MENARES MAIKOL (GRUA)
A1: FECHA | B1: REPUESTO | C1: PRECIO | D1: CONDICION | E1: FACTURA | F1: VENDEDOR | H1: FACTURA | I1: DEUDA | J1: TOTAL DEUDA | L1: abono
B2: SALDO | D2: PENDIENTE | E2: NO | F2: OMAR | H2: =IF(E:E="NO FACTURADO","PENDIENTE","AL DIA") -> AL DIA | I2: =IF(D2="PENDIENTE",C2,0) -> 0 | J2: =SUM(I:I) -> 110000
A3: 44224 | B3: BATERIA 90 AMP | C3: 10000 | D3: PAGADO | E3: NO FACTURADO | F3: DELIS | H3: =IF(E:E="NO FACTURADO","PENDIENTE","AL DIA") -> PENDIENTE | I3: =IF(D3="PENDIENTE",C3,0) -> 0 | K3: MENU
A4: 44239 | B4: KIT EMBRAGUE | C4: 170000 | D4: PAGADO | E4: NO FACTURADO | F4: DELIS | H4: =IF(E:E="NO FACTURADO","PENDIENTE","AL DIA") -> PENDIENTE | I4: =IF(D4="PENDIENTE",C4,0) -> 0
A5: 44239 | B5: ACEITE 5W30 | C5: 56000 | D5: PAGADO | E5: NO FACTURADO | F5: CESAR | H5: =IF(E:E="NO FACTURADO","PENDIENTE","AL DIA") -> PENDIENTE | I5: =IF(D5="PENDIENTE",C5,0) -> 0
A6: 44261 | B6: SALDO CORREA DIST. Y ACEITE | C6: 12000 | D6: PAGADO | E6: NO FACTURADO | F6: CESAR | H6: =IF(E:E="NO FACTURADO","PENDIENTE","AL DIA") -> PENDIENTE | I6: =IF(D6="PENDIENTE",C6,0) -> 0
A7: 44290 | B7: SALDO RADIADOR FRONTIER | C7: 10000 | D7: PAGADO | E7: NO FACTURADO | F7: CESAR | H7: =IF(E:E="NO FACTURADO","PENDIENTE","AL DIA") -> PENDIENTE | I7: =IF(D7="PENDIENTE",C7,0) -> 0
A8: 44333 | B8: SALDO CRUCETA CARDAN KIA (CHUNCHITO) | C8: 10000 | D8: PAGADO | E8: NO FACTURADO | F8: CESAR | H8: =IF(E:E="NO FACTURADO","PENDIENTE","AL DIA") -> PENDIENTE | I8: =IF(D8="PENDIENTE",C8,0) -> 0
A9: 44357 | B9: SALDO BATERIA | C9: 45000 | D9: PAGADO | E9: NO FACTURADO | F9: DELIS | H9: =IF(E:E="NO FACTURADO","PENDIENTE","AL DIA") -> PENDIENTE | I9: =IF(D9="PENDIENTE",C9,0) -> 0
A10: 44408 | B10: SALDO CARROCERIA FRONTIER | C10: 80000 | D10: PAGADO | E10: NO FACTURADO | F10: CESAR | H10: =IF(E:E="NO FACTURADO","PENDIENTE","AL DIA") -> PENDIENTE | I10: =IF(D10="PENDIENTE",C10,0) -> 0
A11: 44483 | B11: BATERIA 100 AMP saldo 2 abonos | C11: 30000 | D11: PENDIENTE | F11: CESAR | I11: =IF(D11="PENDIENTE",C11,0) -> 30000 | L11: $50000 01/04 + 50000 04/05
A12: 44896 | B12: optico yaris | C12: 80000 | D12: PENDIENTE | F12: cesar | I12: =IF(D12="PENDIENTE",C12,0) -> 80000
I13: =IF(D13="PENDIENTE",C13,0) -> 0
I14: =IF(D14="PENDIENTE",C14,0) -> 0
I15: =IF(D15="PENDIENTE",C15,0) -> 0
I16: =IF(D16="PENDIENTE",C16,0) -> 0
I17: =IF(D17="PENDIENTE",C17,0) -> 0
I18: =IF(D18="PENDIENTE",C18,0) -> 0
I19: =IF(D19="PENDIENTE",C19,0) -> 0
I20: =IF(D20="PENDIENTE",C20,0) -> 0
I21: =IF(D21="PENDIENTE",C21,0) -> 0
I22: =IF(D22="PENDIENTE",C22,0) -> 0
I23: =IF(D23="PENDIENTE",C23,0) -> 0
I24: =IF(D24="PENDIENTE",C24,0) -> 0
... I40: =IF(D40="PENDIENTE",C40,0) -> 0

Sheet MORALES JORGE
A1: FECHA | B1: REPUESTO | C1: PRECIO | D1: CONDICION | E1: FACTURA | F1: VENDEDOR | H1: FACTURA | I1: DEUDA | J1: TOTAL DEUDA
B2: SALDO | D2: PENDIENTE | E2: NO | F2: OMAR | H2: =IF(E:E="NO FACTURADO","PENDIENTE","AL DIA") -> AL DIA | I2: =IF(D2="PENDIENTE",C2,0) -> 0 | J2: =SUM(I:I) -> 18500 | K2: MENU
A3: 44260 | B3: TERMOSTATO | C3: 14500 | D3: PENDIENTE | F3: CESAR | I3: =IF(D3="PENDIENTE",C3,0) -> 14500
A4: 44260 | B4: BALANCIN | C4: 4000 | D4: PENDIENTE | F4: CESAR | I4: =IF(D4="PENDIENTE",C4,0) -> 4000
I5: =IF(D5="PENDIENTE",C5,0) -> 0
I6: =IF(D6="PENDIENTE",C6,0) -> 0
I7: =IF(D7="PENDIENTE",C7,0) -> 0
I8: =IF(D8="PENDIENTE",C8,0) -> 0
I9: =IF(D9="PENDIENTE",C9,0) -> 0
I10: =IF(D10="PENDIENTE",C10,0) -> 0
I11: =IF(D11="PENDIENTE",C11,0) -> 0
I12: =IF(D12="PENDIENTE",C12,0) -> 0
I13: =IF(D13="PENDIENTE",C13,0) -> 0
I14: =IF(D14="PENDIENTE",C14,0) -> 0
I15: =IF(D15="PENDIENTE",C15,0) -> 0
I16: =IF(D16="PENDIENTE",C16,0) -> 0
... I40: =IF(D40="PENDIENTE",C40,0) -> 0

Sheet MOTOR EXPRESS
A1: FECHA | B1: REPUESTO | C1: PRECIO | D1: CONDICION | E1: FACTURA | F1: VENDEDOR | H1: FACTURA | I1: DEUDA | J1: TOTAL DEUDA
A2: ------ | B2: LIBRO | C2: 93000 | D2: PAGADO | E2: FACTURADO | F2: OMAR | H2: =IF(E:E="NO FACTURADO","PENDIENTE","AL DIA") -> AL DIA | I2: =IF(D2="PENDIENTE",C2,0) -> 0 | J2: =SUM(I:I) -> 898400 | K2: MENU
A3: 44207 | B3: CILINDRO EMBRAGUE | C3: 16000 | D3: PAGADO | E3: FACTURADO | F3: CESAR | H3: =IF(E:E="NO FACTURADO","PENDIENTE","AL DIA") -> AL DIA | I3: =IF(D3="PENDIENTE",C3,0) -> 0
A4: 44208 | B4: SENSOR CIGÜEÑAL TERRANO | C4: 20000 | D4: PAGADO | E4: FACTURADO | F4: CESAR | H4: =IF(E:E="NO FACTURADO","PENDIENTE","AL DIA") -> AL DIA | I4: =IF(D4="PENDIENTE",C4,0) -> 0
A5: 44208 | B5: FILTRO Y ACEITE | C5: 21000 | D5: PAGADO | E5: FACTURADO | F5: CESAR | H5: =IF(E:E="NO FACTURADO","PENDIENTE","AL DIA") -> AL DIA | I5: =IF(D5="PENDIENTE",C5,0) -> 0
A6: 44208 | B6: CORREA | C6: 6000 | D6: PAGADO | E6: FACTURADO | F6: CESAR | H6: =IF(E:E="NO FACTURADO","PENDIENTE","AL DIA") -> AL DIA | I6: =IF(D6="PENDIENTE",C6,0) -> 0
A7: 44209 | B7: PASTILLA FRENO D22 | C7: 20000 | D7: PAGADO | E7: BOLETA | F7: OMAR | H7: =IF(E:E="NO FACTURADO","PENDIENTE","AL DIA") -> AL DIA | I7: =IF(D7="PENDIENTE",C7,0) -> 0
A8: 44214 | B8: ACEITE 10W40 ECO | C8: 17000 | D8: PAGADO | E8: FACTURADO | F8: CESAR | H8: =IF(E:E="NO FACTURADO","PENDIENTE","AL DIA") -> AL DIA | I8: =IF(D8="PENDIENTE",C8,0) -> 0
A9: 44214 | B9: JUEGO BUJIA ECO | C9: 12000 | D9: PAGADO | E9: FACTURADO | F9: CESAR | H9: =IF(E:E="NO FACTURADO","PENDIENTE","AL DIA") -> AL DIA | I9: =IF(D9="PENDIENTE",C9,0) -> 0
A10: 44215 | B10: CORREA ACCESORIO ECO | C10: 3000 | D10: PAGADO | E10: FACTURADO | F10: CESAR | H10: =IF(E:E="NO FACTURADO","PENDIENTE","AL DIA") -> AL DIA | I10: =IF(D10="PENDIENTE",C10,0) -> 0
A11: 44215 | B11: FILTRO AIRE ECO | C11: 5000 | D11: PAGADO | E11: FACTURADO | F11: CESAR | H11: =IF(E:E="NO FACTURADO","PENDIENTE","AL DIA") -> AL DIA | I11: =IF(D11="PENDIENTE",C11,0) -> 0
A12: 44215 | B12: BOMBA ACEITE LUV | C12: 40000 | D12: PAGADO | E12: FACTURADO | F12: CESAR | H12: =IF(E:E="NO FACTURADO","PENDIENTE","AL DIA") -> AL DIA | I12: =IF(D12="PENDIENTE",C12,0) -> 0
A13: 44218 | B13: PRESUPUESTO N 4247 | C13: 92500 | D13: PAGADO | E13: FACTURADO | F13: DELIS | H13: =IF(E:E="NO FACTURADO","PENDIENTE","AL DIA") -> AL DIA | I13: =IF(D13="PENDIENTE",C13,0) -> 0
B14: BOMBA BENCINA | C14: 30000 | D14: PAGADO | E14: FACTURADO | F14: DELIS | H14: =IF(E:E="NO FACTURADO","PENDIENTE","AL DIA") -> AL DIA | I14: =IF(D14="PENDIENTE",C14,0) -> 0
A15: 44231 | B15: FAROL CORSA | C15: 18500 | D15: PAGADO | E15: FACTURADO | F15: CESAR | H15: =IF(E:E="NO FACTURADO","PENDIENTE","AL DIA") -> AL DIA | I15: =IF(D15="PENDIENTE",C15,0) -> 0
A16: 44236 | B16: BOMDA AGUA AVELLA | C16: 25000 | D16: PAGADO | E16: FACTURADO | F16: CESAR | H16: =IF(E:E="NO FACTURADO","PENDIENTE","AL DIA") -> AL DIA | I16: =IF(D16="PENDIENTE",C16,0) -> 0
A17: 44236 | B17: ABONO PRESUPUESTO ATOZ | C17: 300000 | D17: PAGADO | E17: FACTURADO | F17: NATALIA | H17: =IF(E:E="NO FACTURADO","PENDIENTE","AL DIA") -> AL DIA | I17: =IF(D17="PENDIENTE",C17,0) -> 0
A18: 44257 | B18: BULBO ACEITE CORSA * | C18: 7500 | D18: PAGADO | E18: FACTURADO | F18: CESAR | H18: =IF(E:E="NO FACTURADO","PENDIENTE","AL DIA") -> AL DIA | I18: =IF(D18="PENDIENTE",C18,0) -> 0
A19: 44285 | B19: JGO BANDEJA | C19: 65000 | D19: PAGADO | E19: FACTURADO | F19: OMAR | H19: =IF(E:E="NO FACTURADO","PENDIENTE","AL DIA") -> AL DIA | I19: =IF(D19="PENDIENTE",C19,0) -> 0
A20: 44285 | B20: JGO TERMINAL | C20: 31000 | D20: PAGADO | E20: FACTURADO | F20: OMAR | H20: =IF(E:E="NO FACTURADO","PENDIENTE","AL DIA") -> AL DIA | I20: =IF(D20="PENDIENTE",C20,0) -> 0
A21: 44285 | B21: JGO AXIAL | C21: 32000 | D21: PAGADO | E21: FACTURADO | F21: OMAR | H21: =IF(E:E="NO FACTURADO","PENDIENTE","AL DIA") -> AL DIA | I21: =IF(D21="PENDIENTE",C21,0) -> 0
A22: 44285 | B22: SILICONA WURTH | C22: 5500 | D22: PAGADO | E22: FACTURADO | F22: OMAR | H22: =IF(E:E="NO FACTURADO","PENDIENTE","AL DIA") -> AL DIA | I22: =IF(D22="PENDIENTE",C22,0) -> 0
A23: 44307 | B23: empaquetadura 8taquet luv 2,2 | C23: 86000 | D23: PAGADO | E23: FACTURADO | F23: cesar | H23: =IF(E:E="NO FACTURADO","PENDIENTE","AL DIA") -> AL DIA | I23: =IF(D23="PENDIENTE",C23,0) -> 0
A24: 44308 | B24: shell 10w40 h7 | C24: 25000 | D24: PAGADO | E24: FACTURADO | F24: CESAR | H24: =IF(E:E="NO FACTURADO","PENDIENTE","AL DIA") -> AL DIA | I24: =IF(D24="PENDIENTE",C24,0) -> 0
A25: 44295 | B25: CHEVROLET SAIL | C25: 20000 | D25: PAGADO | E25: NO FACTURADO | F25: CESAR | H25: =IF(E:E="NO FACTURADO","PENDIENTE","AL DIA") -> PENDIENTE | I25: =IF(D25="PENDIENTE",C25,0) -> 0
A26: 44369 | B26: CHEVROLET SONIC | C26: 57900 | D26: PAGADO | E26: NO FACTURADO | F26: CESAR | H26: =IF(E:E="NO FACTURADO","PENDIENTE","AL DIA") -> PENDIENTE | I26: =IF(D26="PENDIENTE",C26,0) -> 0
A27: 15/07/202 | B27: ACEITE Y FILTRO | C27: 22000 | D27: PAGADO | E27: FACTURADO | F27: CESAR | H27: =IF(E:E="NO FACTURADO","PENDIENTE","AL DIA") -> AL DIA | I27: =IF(D27="PENDIENTE",C27,0) -> 0
A28: 44399 | B28: (3)REFRIGERANTE | C28: 13500 | D28: PAGADO | E28: FACTURADO | F28: CESAR | H28: PENDIENTE | I28: =IF(D28="PENDIENTE",C28,0) -> 0
A29: 44407 | B29: REFRIGERANTE TERRACAN | C29: 20000 | D29: PAGADO | E29: FACTURADO | F29: CESAR | I29: =IF(D29="PENDIENTE",C29,0) -> 0
A30: 44473 | B30: HOMOCINETICA MARUTI | C30: 30000 | D30: PAGADO | E30: NO FACTURADO | F30: CESAR | I30: =IF(D30="PENDIENTE",C30,0) -> 0
A31: 44531 | B31: SENSOR VELOCIDAD RB | C31: 20000 | D31: PAGADO | E31: NO FACTURADO | F31: CESAR | I31: =IF(D31="PENDIENTE",C31,0) -> 0
A32: 44550 | B32: jgo bandeja y terminal accent rb | C32: 103900 | D32: PENDIENTE | E32: NO FACTURADO | F32: CESAR | I32: =IF(D32="PENDIENTE",C32,0) -> 103900
A33: 44551 | B33: cambio aceite rb | C33: 60000 | D33: PENDIENTE | E33: NO FACTURADO | F33: CESAR | I33: =IF(D33="PENDIENTE",C33,0) -> 60000
A34: 45146 | B34: bomba y tapa | C34: 52000 | D34: PAGADO | F34: CESAR | I34: =IF(D34="PENDIENTE",C34,0) -> 0
A35: 45176 | B35: ACEITE | C35: 30000 | D35: PAGADO | F35: CESAR | I35: =IF(D35="PENDIENTE",C35,0) -> 0
A36: 45210 | B36: inzumo taller cambio de aceite ram | C36: 104000 | D36: PENDIENTE | F36: CESAR | I36: =IF(D36="PENDIENTE",C36,0) -> 104000
A37: 45211 | B37: balancin eje balancin aceite y filtro | C37: 167000 | D37: PENDIENTE | F37: CESAR | I37: =IF(D37="PENDIENTE",C37,0) -> 167000
A38: 45217 | B38: EMP.TAPA VALILA ;2ATF;HORQUILLA;SEGURO HORQUILLA | C38: 42500 | D38: PENDIENTE | F38: CESAR | I38: =IF(D38="PENDIENTE",C38,0) -> 42500
B39: electroventilador | C39: 110000 | D39: PENDIENTE | I39: =IF(D39="PENDIENTE",C39,0) -> 110000
B40: presupuesto 5938 | C40: 266000 | D40: PENDIENTE | I40: =IF(D40="PENDIENTE",C40,0) -> 266000
A41: 45328 | B41: bomba bencina y bujias | C41: 45000 | D41: PENDIENTE | I41: =IF(D41="PENDIENTE",C41,0) -> 45000
I42: =IF(D42="PENDIENTE",C42,0) -> 0
I43: =IF(D43="PENDIENTE",C43,0) -> 0
I44: =IF(D44="PENDIENTE",C44,0) -> 0
I45: =IF(D45="PENDIENTE",C45,0) -> 0
I46: =IF(D46="PENDIENTE",C46,0) -> 0
I47: =IF(D47="PENDIENTE",C47,0) -> 0
I48: =IF(D48="PENDIENTE",C48,0) -> 0
I49: =IF(D49="PENDIENTE",C49,0) -> 0
I50: =IF(D50="PENDIENTE",C50,0) -> 0
I51: =IF(D51="PENDIENTE",C51,0) -> 0
I52: =IF(D52="PENDIENTE",C52,0) -> 0
I53: =IF(D53="PENDIENTE",C53,0) -> 0
... I71: =IF(D71="PENDIENTE",C71,0) -> 0

Sheet PEREZ SADY
B1: REPUESTO | C1: PRECIO | D1: CONDICION | E1: FACTURA | F1: VENDEDOR | H1: FACTURA | I1: DEUDA | J1: TOTAL DEUDA
A2: 44197 | B2: LIBRO | D2: PENDIENTE | H2: =IF(E:E="NO FACTURADO","PENDIENTE","AL DIA") -> AL DIA | I2: =IF(D2="PENDIENTE",C2,0) -> 0 | J2: =SUM(I:I) -> 40000 | K2: MENU
A3: 44207 | B3: JUEGO DE BUJIAS YARIS PATRICIO MARDONES | C3: 8000 | D3: PAGADO | E3: FACTURADO | F3: OMAR | H3: =IF(E:E="NO FACTURADO","PENDIENTE","AL DIA") -> AL DIA | I3: =IF(D3="PENDIENTE",C3,0) -> 0
A4: 44207 | B4: BATERIA YARIS | C4: 60000 | D4: PAGADO | E4: FACTURADO | F4: DELIS | H4: =IF(E:E="NO FACTURADO","PENDIENTE","AL DIA") -> AL DIA | I4: =IF(D4="PENDIENTE",C4,0) -> 0
A5: 44207 | B5: MULTIPLE ADMISION YARIS | C5: 275000 | D5: PAGADO | E5: FACTURADO | F5: DELIS | H5: =IF(E:E="NO FACTURADO","PENDIENTE","AL DIA") -> AL DIA | I5: =IF(D5="PENDIENTE",C5,0) -> 0
A6: 44207 | B6: EMPAQUETADURA MULTIPLE YARIS | C6: 5000 | D6: PAGADO | E6: FACTURADO | F6: DELIS | H6: =IF(E:E="NO FACTURADO","PENDIENTE","AL DIA") -> AL DIA | I6: =IF(D6="PENDIENTE",C6,0) -> 0
A7: 44208 | B7: ELECTROVENTILADOR YARIS | C7: 60000 | D7: PAGADO | E7: FACTURADO | F7: DELIS | H7: =IF(E:E="NO FACTURADO","PENDIENTE","AL DIA") -> AL DIA | I7: =IF(D7="PENDIENTE",C7,0) -> 0
A8: 44211 | B8: LIQUIDO FRENO YARIS | C8: 4000 | D8: PAGADO | E8: FACTURADO | F8: DELIS | H8: =IF(E:E="NO FACTURADO","PENDIENTE","AL DIA") -> AL DIA | I8: =IF(D8="PENDIENTE",C8,0) -> 0
A9: 44211 | B9: RADIADOR YARIS | C9: 49500 | D9: PAGADO | E9: FACTURADO | F9: DELIS | H9: =IF(E:E="NO FACTURADO","PENDIENTE","AL DIA") -> AL DIA | I9: =IF(D9="PENDIENTE",C9,0) -> 0
A10: 44211 | B10: PARACHOQUE DEL YARIS | C10: 65000 | D10: PAGADO | E10: FACTURADO | F10: DELIS | H10: =IF(E:E="NO FACTURADO","PENDIENTE","AL DIA") -> AL DIA | I10: =IF(D10="PENDIENTE",C10,0) -> 0
A11: 44211 | B11: 2 OPTICO YARIS | C11: 103000 | D11: PAGADO | E11: FACTURADO | F11: DELIS | H11: =IF(E:E="NO FACTURADO","PENDIENTE","AL DIA") -> AL DIA | I11: =IF(D11="PENDIENTE",C11,0) -> 0
A12: 44224 | B12: 2 LIQUIDO FRENO | C12: 8000 | D12: PAGADO | E12: FACTURADO | F12: DELIS | H12: =IF(E:E="NO FACTURADO","PENDIENTE","AL DIA") -> AL DIA | I12: =IF(D12="PENDIENTE",C12,0) -> 0
A13: 44224 | B13: BOMBA FRENO YARIS | C13: 74000 | D13: PAGADO | E13: FACTURADO | F13: DELIS | H13: =IF(E:E="NO FACTURADO","PENDIENTE","AL DIA") -> AL DIA | I13: =IF(D13="PENDIENTE",C13,0) -> 0
A14: 44224 | B14: FILTRO AIRE | C14: 5600 | D14: PAGADO | E14: FACTURADO | F14: DELIS | H14: =IF(E:E="NO FACTURADO","PENDIENTE","AL DIA") -> AL DIA | I14: =IF(D14="PENDIENTE",C14,0) -> 0
... A16: 44229 | B16: JUEGO PASTILLAS DEL | C16: 24500 | D16: PAGADO | E16: NO FACTURADO | F16: CESAR | H16: =IF(E:E="NO FACTURADO","PENDIENTE","AL DIA") -> PENDIENTE | I16: =IF(D16="PENDIENTE",C16,0) -> 0
A17: 44229 | B17: JUEGO PASTILLAS TRAS | C17: 20000 | D17: PAGADO | E17: NO FACTURADO | F17: CESAR | I17: =IF(D17="PENDIENTE",C17,0) -> 0
A18: 44230 | B18: BOMBA BENCINA LUV | C18: 18000 | D18: PAGADO | E18: NO FACTURADO | F18: DELIS | I18: =IF(D18="PENDIENTE",C18,0) -> 0
A19: 44306 | B19: kit embrague yaris jaime | C19: 89000 | D19: PAGADO | E19: FACTURADO | F19: DELIS | I19: =IF(D19="PENDIENTE",C19,0) -> 0
A20: 44445 | B20: saldo bateria | C20: 25000 | D20: PAGADO | E20: FACTURADO | F20: DELIS | I20: =IF(D20="PENDIENTE",C20,0) -> 0
A21: 44452 | B21: presupuesto | C21: 60000 | D21: PAGADO | E21: NO FACTURADO | F21: DELIS | I21: =IF(D21="PENDIENTE",C21,0) -> 0
A22: 44482 | B22: JGO EMP.MOTOR Y SILICONA (ROLA) | C22: 36500 | D22: PAGADO | E22: NO FACTURADO | F22: CESAR | I22: =IF(D22="PENDIENTE",C22,0) -> 0
A23: 44483 | B23: FILTRO ACEITE (ROLA) | C23: 4500 | D23: PAGADO | I23: =IF(D23="PENDIENTE",C23,0) -> 0
A24: 44488 | B24: FILTRO PETROLEO (ROLA) | C24: 6000 | D24: PAGADO | E24: NO FACTURADO | F24: CESAR | I24: =IF(D24="PENDIENTE",C24,0) -> 0
A25: 44606 | B25: presupuesto Nº4921 | C25: 27000 | D25: PAGADO | E25: NO FACTURADO | F25: OMAR | I25: =IF(D25="PENDIENTE",C25,0) -> 0
A26: 44641 | B26: presupuesto n 5001 | C26: 15500 | D26: PAGADO | F26: delis | I26: =IF(D26="PENDIENTE",C26,0) -> 0 | J26: 44642
A27: 44782 | B27: PRESUPUESTO N5260 | C27: 361500 | D27: PAGADO | F27: CESAR | I27: =IF(D27="PENDIENTE",C27,0) -> 0
A28: 44858 | B28: cruceta gum 91 x3 | C28: 45000 | D28: PAGADO | I28: =IF(D28="PENDIENTE",C28,0) -> 0
A29: 44893 | B29: bobina spark gt | C29: 30000 | D29: devolucion | F29: omar | I29: =IF(D29="PENDIENTE",C29,0) -> 0
A30: 45335 | B30: PRESUPUESTO 006075 | C30: 166000 | D30: PAGADO | E30: NO FACTURADO | I30: =IF(D30="PENDIENTE",C30,0) -> 0
A31: 45348 | B31: presupuesto 6085 | D31: PENDIENTE | I31: =IF(D31="PENDIENTE",C31,0) -> 0
A32: 45362 | B32: RODAMIENTO EMBRAGUE | C32: 40000 | D32: PENDIENTE | I32: =IF(D32="PENDIENTE",C32,0) -> 40000
I33: =IF(D33="PENDIENTE",C33,0) -> 0
I34: =IF(D34="PENDIENTE",C34,0) -> 0
I35: =IF(D35="PENDIENTE",C35,0) -> 0
I36: =IF(D36="PENDIENTE",C36,0) -> 0
I37: =IF(D37="PENDIENTE",C37,0) -> 0
I38: =IF(D38="PENDIENTE",C38,0) -> 0
I39: =IF(D39="PENDIENTE",C39,0) -> 0
I40: =IF(D40="PENDIENTE",C40,0) -> 0

Sheet PINGUINO MAURI
A1: FECHA | B1: REPUESTO | C1: PRECIO | D1: CONDICION | E1: FACTURA | F1: VENDEDOR | H1: FACTURA | I1: DEUDA | J1: TOTAL DEUDA
A2: 44215 | B2: BOBINA DE ALTA | C2: 9000 | D2: PAGDO | E2: NO | F2: OMAR | H2: =IF(E:E="NO FACTURADO","PENDIENTE","AL DIA") -> AL DIA | I2: =IF(D2="PENDIENTE",C2,0) -> 0 | J2: =SUM(I:I) -> 0 | K2: MENU
A3: 44215 | B3: ROST OFF | C3: 4500 | D3: PAGDO | E3: NO | F3: CESAR | I3: =IF(D3="PENDIENTE",C3,0) -> 0
A4: 44215 | B4: LIQUIDO DE FRENO | C4: 4000 | D4: PAGDO | E4: NO | F4: CESAR | I4: =IF(D4="PENDIENTE",C4,0) -> 0
B5: SALDO | C5: 15000 | D5: PAGADO | E5: NO | F5: CESAR | I5: =IF(D5="PENDIENTE",C5,0) -> 0
A6: 44613 | B6: bateria 55 rocker | C6: 75000 | D6: PAGADO | F6: omar | I6: =IF(D6="PENDIENTE",C6,0) -> 0
A7: 44742 | B7: anticongelante, rostof, liquido freno | C7: 34000 | D7: pagado | F7: cesar | I7: =IF(D7="PENDIENTE",C7,0) -> 0
I8: =IF(D8="PENDIENTE",C8,0) -> 0
I9: =IF(D9="PENDIENTE",C9,0) -> 0
I10: =IF(D10="PENDIENTE",C10,0) -> 0
I11: =IF(D11="PENDIENTE",C11,0) -> 0
I12: =IF(D12="PENDIENTE",C12,0) -> 0
I13: =IF(D13="PENDIENTE",C13,0) -> 0
I14: =IF(D14="PENDIENTE",C14,0) -> 0
I15: =IF(D15="PENDIENTE",C15,0) -> 0
I16: =IF(D16="PENDIENTE",C16,0) -> 0
I17: =IF(D17="PENDIENTE",C17,0) -> 0
I18: =IF(D18="PENDIENTE",C18,0) -> 0
I19: =IF(D19="PENDIENTE",C19,0) -> 0
... I40: =IF(D40="PENDIENTE",C40,0) -> 0

Sheet PORTALES CRISTIAN
A1: FECHA | B1: REPUESTO | C1: PRECIO | D1: CONDICION | E1: FACTURA | F1: VENDEDOR | H1: FACTURA | I1: DEUDA | J1: TOTAL DEUDA
B2: SALDO | D2: PENDIENTE | E2: NO | F2: OMAR | H2: =IF(E:E="NO FACTURADO","PENDIENTE","AL DIA") -> AL DIA | I2: =IF(D2="PENDIENTE",C2,0) -> 0 | J2: =SUM(I:I) -> 1244000 | K2: MENU
A3: 44232 | B3: KIT EMBRAGUE | C3: 100000 | D3: PAGADO | E3: NO FACTURADO | F3: OMAR | H3: =IF(E:E="NO FACTURADO","PENDIENTE","AL DIA") -> PENDIENTE | I3: =IF(D3="PENDIENTE",C3,0) -> 0
A4: 44232 | B4: FILTRO AIRE | C4: 8000 | D4: PAGADO | E4: NO FACTURADO | F4: CESAR | H4: =IF(E:E="NO FACTURADO","PENDIENTE","AL DIA") -> PENDIENTE | I4: =IF(D4="PENDIENTE",C4,0) -> 0
A5: 44237 | B5: PIOLA EMBRAGUE | C5: 10000 | D5: PAGADO | E5: NO FACTURADO | F5: OMAR | H5: =IF(E:E="NO FACTURADO","PENDIENTE","AL DIA") -> PENDIENTE | I5: =IF(D5="PENDIENTE",C5,0) -> 0
A6: 44239 | B6: ACEITE Y FILTRO | C6: 22000 | D6: PAGADO | E6: NO FACTURADO | F6: CESAR | H6: =IF(E:E="NO FACTURADO","PENDIENTE","AL DIA") -> PENDIENTE | I6: =IF(D6="PENDIENTE",C6,0) -> 0
A7: 44242 | B7: KIT EMBRAGUE CORSA | C7: 75000 | D7: PAGADO | E7: NO FACTURADO | F7: CESAR | H7: =IF(E:E="NO FACTURADO","PENDIENTE","AL DIA") -> PENDIENTE | I7: =IF(D7="PENDIENTE",C7,0) -> 0
A8: 44244 | B8: 3 75W90 | C8: 9500 | D8: PAGADO | E8: NO FACTURADO | F8: CESAR | H8: =IF(E:E="NO FACTURADO","PENDIENTE","AL DIA") -> PENDIENTE | I8: =IF(D8="PENDIENTE",C8,0) -> 0
A9: 44245 | B9: 1 L ACEITE 6W30 | C9: 16500 | D9: PAGADO | E9: NO FACTURADO | F9: CESAR | H9: =IF(E:E="NO FACTURADO","PENDIENTE","AL DIA") -> PENDIENTE | I9: =IF(D9="PENDIENTE",C9,0) -> 0
A10: 44253 | B10: BATERIA 62AMP | C10: 62000 | D10: PAGADO | E10: NO FACTURADO | F10: NATALIA | H10: =IF(E:E="NO FACTURADO","PENDIENTE","AL DIA") -> PENDIENTE | I10: =IF(D10="PENDIENTE",C10,0) -> 0
A11: 44260 | B11: BATERIA 90 AMP SOLITE +LH | C11: 44000 | D11: PAGADO | E11: NO FACTURADO | F11: NATALIA | H11: =IF(E:E="NO FACTURADO","PENDIENTE","AL DIA") -> PENDIENTE | I11: =IF(D11="PENDIENTE",C11,0) -> 0
A12: 44271 | B12: SILICONA | C12: 5900 | D12: PAGADO | E12: NO FACTURADO | F12: OMAR | H12: =IF(E:E="NO FACTURADO","PENDIENTE","AL DIA") -> PENDIENTE | I12: =IF(D12="PENDIENTE",C12,0) -> 0
A13: 44274 | B13: JUEGO DE TERMINALES | C13: 24000 | D13: PAGADO | E13: NO FACTURADO | F13: CESAR | H13: =IF(E:E="NO FACTURADO","PENDIENTE","AL DIA") -> PENDIENTE | I13: =IF(D13="PENDIENTE",C13,0) -> 0
A14: 44279 | B14: CULATA MOTOR D4BH | C14: 220000 | D14: PAGADO | E14: NO FACTURADO | F14: CESAR | H14: =IF(E:E="NO FACTURADO","PENDIENTE","AL DIA") -> PENDIENTE | I14: =IF(D14="PENDIENTE",C14,0) -> 0
... A22: 44313 | B22: MANTENCION MONTERO | C22: 50000 | D22: PAGADO | E22: NO FACTURADO | F22: CESAR | H22: =IF(E:E="NO FACTURADO","PENDIENTE","AL DIA") -> PENDIENTE | I22: =IF(D22="PENDIENTE",C22,0) -> 0
A23: 44315 | B23: KIT EMBRAGUE MONTERO 5 ACEITE 80/90 | C23: 110000 | D23: PAGADO | E23: NO FACTURADO | F23: DELIS | H23: PENDIENTE | I23: =IF(D23="PENDIENTE",C23,0) -> 0
A24: 44324 | B24: aceite + filtro ignis | C24: 24000 | D24: PAGADO | E24: NO FACTURADO | F24: CESAR | H24: =IF(E:E="NO FACTURADO","PENDIENTE","AL DIA") -> PENDIENTE | I24: =IF(D24="PENDIENTE",C24,0) -> 0
A25: 44335 | B25: aceite 75w90 tercel | C25: 19500 | D25: PAGADO | E25: NO FACTURADO | F25: CESAR | H25: =IF(E:E="NO FACTURADO","PENDIENTE","AL DIA") -> PENDIENTE | I25: =IF(D25="PENDIENTE",C25,0) -> 0
A26: 44335 | B26: nissan d21 | C26: 9000 | D26: PAGADO | E26: NO FACTURADO | F26: CESAR | H26: =IF(E:E="NO FACTURADO","PENDIENTE","AL DIA") -> PENDIENTE | I26: =IF(D26="PENDIENTE",C26,0) -> 0
A27: 44342 | B27: PRESUPUESTO 4512 | C27: 22500 | D27: PAGADO | E27: FACTURADO | F27: OMAR | H27: =IF(E:E="NO FACTURADO","PENDIENTE","AL DIA") -> AL DIA | I27: =IF(D27="PENDIENTE",C27,0) -> 0
A28: 44347 | B28: CORREA 4PK-935 TERCEL | C28: 5000 | D28: pagado | E28: FACTURADO | F28: DELIS | H28: =IF(E:E="NO FACTURADO","PENDIENTE","AL DIA") -> AL DIA | I28: =IF(D28="PENDIENTE",C28,0) -> 0
A29: 44351 | B29: aceite 75w90 l200 año 2014 | C29: 19500 | D29: PAGADO | E29: NO FACTURADO | F29: delis | H29: =IF(E:E="NO FACTURADO","PENDIENTE","AL DIA") -> PENDIENTE | I29: =IF(D29="PENDIENTE",C29,0) -> 0
A30: 44359 | B30: HOMOSINETICA PARA EL SUEGRO | C30: 40000 | D30: PAGADO | E30: FACTURADO | F30: CESAR | H30: =IF(E:E="NO FACTURADO","PENDIENTE","AL DIA") -> AL DIA | I30: =IF(D30="PENDIENTE",C30,0) -> 0
A31: 44363 | B31: brazo auxiliar d22 4wd | C31: 36000 | D31: PAGADO | E31: FACTURADO | F31: omar | H31: =IF(E:E="NO FACTURADO","PENDIENTE","AL DIA") -> AL DIA | I31: =IF(D31="PENDIENTE",C31,0) -> 0
A32: 44371 | B32: FILTRO ACEITE JEEP PATHFINDER | C32: 4000 | D32: PAGADO | E32: FACTURADO | F32: CESAR | H32: =IF(E:E="NO FACTURADO","PENDIENTE","AL DIA") -> AL DIA | I32: =IF(D32="PENDIENTE",C32,0) -> 0
A33: 44383 | B33: SILICONA | C33: 6500 | D33: PAGADO | E33: NO FACTURADO | F33: omar | H33: =IF(E:E="NO FACTURADO","PENDIENTE","AL DIA") -> PENDIENTE | I33: =IF(D33="PENDIENTE",C33,0) -> 0
A34: 44385 | B34: GASKET | C34: 2500 | D34: PAGADO | E34: NO FACTURADO | F34: OMAR | H34: =IF(E:E="NO FACTURADO","PENDIENTE","AL DIA") -> PENDIENTE | I34: =IF(D34="PENDIENTE",C34,0) -> 0
A35: 44397 | B35: EMP. MOTOR CORSA + EJE LEVA (CORSA) | C35: 105000 | D35: PAGADO | E35: NO FACTURADO | F35: CESAR | H35: =IF(E:E="NO FACTURADO","PENDIENTE","AL DIA") -> PENDIENTE | I35: =IF(D35="PENDIENTE",C35,0) -> 0
... A37: 44399 | B37: BUJIAS CABLES YALE | C37: 20000 | D37: PAGADO | E37: NO FACTURADO | F37: CESAR | H37: =IF(E:E="NO FACTURADO","PENDIENTE","AL DIA") -> PENDIENTE | I37: =IF(D37="PENDIENTE",C37,0) -> 0
A38: 44399 | B38: KIT CORSA DISTRIBUCION | C38: 24000 | D38: PAGADO | E38: NO FACTURADO | F38: CESAR | I38: =IF(D38="PENDIENTE",C38,0) -> 0
A39: 44404 | B39: 4 litros 75w90 gl5 | C39: 34000 | D39: PAGADO | E39: NO FACTURADO | F39: CESAR | I39: =IF(D39="PENDIENTE",C39,0) -> 0
A40: 44406 | B40: ACEITE +FILTRO+CORREA+PICARON+3LTS 75W90 | C40: 58500 | D40: PAGADO | E40: NO FACTURADO | F40: CESAR | I40: =IF(D40="PENDIENTE",C40,0) -> 0
A41: 44414 | B41: CABLE BUJIA CORSA | C41: 15000 | D41: PAGADO | E41: NO FACTURADO | F41: CESAR | I41: =IF(D41="PENDIENTE",C41,0) -> 0
A42: 44417 | B42: JGO TAQUIET CORSA | C42: 78000 | D42: PAGADO | E42: NO FACTURADO | F42: CESAR | I42: =IF(D42="PENDIENTE",C42,0) -> 0
A43: 44431 | B43: aceite + filtro + bba emb. Terrano | C43: 50000 | D43: PAGADO | E43: NO FACTURADO | F43: CESAR | I43: =IF(D43="PENDIENTE",C43,0) -> 0
A44: 44440 | B44: KIT EMBREGUE + EMP. + 80W90 | C44: 67000 | D44: PAGADO | E44: BOLETA | F44: CESAR | I44: =IF(D44="PENDIENTE",C44,0) -> 0
A45: 44448 | B45: atf corsa | C45: 5000 | D45: PAGADO | E45: BOLETA | F45: CESAR | I45: =IF(D45="PENDIENTE",C45,0) -> 0
A46: 44463 | B46: emp. Culata + poncho valvula | C46: 16000 | D46: PAGADO | E46: BOLETA | F46: CESAR | I46: =IF(D46="PENDIENTE",C46,0) -> 0
A47: 44481 | B47: CORREA + FUELLES + TERMOS. SUBARU | C47: 58500 | D47: PAGADO | E47: NO FACTURADO | F47: CESAR | I47: =IF(D47="PENDIENTE",C47,0) -> 0
A48: 44487 | B48: JGO CHAPA SUBARU | C48: 14000 | D48: PAGADO | E48: NO FACTURADO | F48: CESAR | I48: =IF(D48="PENDIENTE",C48,0) -> 0
A49: 44495 | B49: ANILLOS + EMP. CULATA ORIGINAL D22 | C49: 220000 | D49: PAGADO | E49: NO FACTURADO | F49: CESAR | I49: =IF(D49="PENDIENTE",C49,0) -> 0
... A65: 44638 | B65: grasa grafitada | C65: 3500 | D65: PENDIENTE | E65: NO FACTURADO | F65: OMAR | I65: =IF(D65="PENDIENTE",C65,0) -> 3500
A66: 44662 | B66: EMPAQUETADURA CULATA | C66: 78000 | D66: PENDIENTE | F66: DELIS | I66: =IF(D66="PENDIENTE",C66,0) -> 78000
A67: 44663 | B67: CAMBIO ACEITE | C67: 49000 | D67: PENDIENTE | F67: CESAR | I67: =IF(D67="PENDIENTE",C67,0) -> 49000
A68: 44685 | B68: bateria buenarda pal papá | C68: 68000 | D68: PAGADO | F68: CESAR | I68: =IF(D68="PENDIENTE",C68,0) -> 0
A69: 44692 | B69: servicio montana | C69: 83500 | D69: PENDIENTE | F69: CESAR | I69: =IF(D69="PENDIENTE",C69,0) -> 83500
A70: 44692 | B70: termostato subaru | C70: 22000 | D70: PENDIENTE | F70: CESAR | I70: =IF(D70="PENDIENTE",C70,0) -> 22000
A71: 44693 | B71: plumilla | C71: 13000 | D71: PENDIENTE | F71: omar | I71: =IF(D71="PENDIENTE",C71,0) -> 13000
A72: 44699 | B72: bateria | C72: 65000 | D72: PAGADO | F72: cesar | I72: =IF(D72="PENDIENTE",C72,0) -> 0
A73: 44700 | B73: liquido freno | C73: 4500 | D73: PENDIENTE | F73: omar | I73: =IF(D73="PENDIENTE",C73,0) -> 4500
A74: 44706 | B74: enchufe carro | C74: 16000 | D74: PENDIENTE | F74: cesar | I74: =IF(D74="PENDIENTE",C74,0) -> 16000
A75: 44721 | B75: termostato 22r | C75: 23000 | D75: pagado | F75: OMAR | I75: =IF(D75="PENDIENTE",C75,0) -> 0
A76: 44722 | B76: rodamiento embrague 22r | C76: 14000 | D76: pagado | F76: OMAR | I76: =IF(D76="PENDIENTE",C76,0) -> 0
A77: 44726 | B77: filtro y aceite 22rr | C77: 18000 | D77: pagado | F77: OMAR | I77: =IF(D77="PENDIENTE",C77,0) -> 0
... A80: 44760 | B80: silicona loctite | C80: 7000 | D80: PENDIENTE | F80: OMAR | I80: =IF(D80="PENDIENTE",C80,0) -> 7000
A81: 44767 | B81: aceite 20w50 + filtro (hilux 22r) | C81: 16000 | D81: PAGADO | E81: FACTURADO | F81: OMAR | I81: =IF(D81="PENDIENTE",C81,0) -> 0
A82: 44777 | B82: AFINAMIENTO TERRANO TOSCO | C82: 74500 | D82: PENDIENTE | F82: DELIS | I82: =IF(D82="PENDIENTE",C82,0) -> 74500
A83: 44777 | B83: PRESUPUESTO N 5180 RAV 4 | C83: 113500 | D83: pagado | F83: DELIS | I83: =IF(D83="PENDIENTE",C83,0) -> 0
A84: 04/0872022 | B84: PRESUPUSETO N 5180 CELERIO | C84: 44500 | D84: pagado | F84: DELIS | I84: =IF(D84="PENDIENTE",C84,0) -> 0
A85: 44778 | B85: 1 litro aceite shell 10w40 | C85: 10000 | D85: PAGADO | F85: OMAR | I85: =IF(D85="PENDIENTE",C85,0) -> 0
A86: 44781 | B86: loctite | C86: 7000 | D86: PENDIENTE | F86: CESAR | I86: =IF(D86="PENDIENTE",C86,0) -> 7000
A87: 44802 | B87: ampolleta y pino | C87: 6500 | D87: PENDIENTE | F87: CESAR | I87: =IF(D87="PENDIENTE",C87,0) -> 6500
A88: 44833 | B88: filtro aire | C88: 6000 | D88: PENDIENTE | F88: CESAR | I88: =IF(D88="PENDIENTE",C88,0) -> 6000
A89: 44852 | B89: aceite 5w/30 suegro | C89: 10000 | D89: PENDIENTE | F89: DELIS | I89: =IF(D89="PENDIENTE",C89,0) -> 10000
A90: 44896 | B90: correa a-34 | C90: 6500 | D90: PAGADO | F90: DELIS | I90: =IF(D90="PENDIENTE",C90,0) -> 0 | J90: abono | K90: 150000 | L90: 44945
A91: 44904 | B91: filtro aceite terrano $10000 blindao | C91: 15000 | D91: PAGADO | F91: cesar | I91: =IF(D91="PENDIENTE",C91,0) -> 0 | K91: 150000 | L91: 45021
A92: 44910 | B92: bomba embrague d21 (hija) | C92: 28000 | D92: PENDIENTE | F92: CESAR | I92: =IF(D92="PENDIENTE",C92,0) -> 28000 | K92: 100000 | L92: 45198
A93: 45037 | B93: presupuesto 5663 | C93: 70000 | D93: PENDIENTE | F93: CESAR | I93: =IF(D93="PENDIENTE",C93,0) -> 70000 | K93: 48500 | L93: 45310 | M93: factura 8062
A94: 45040 | B94: AMPOLLETA | C94: 25000 | D94: PENDIENTE | F94: CESAR | I94: =IF(D94="PENDIENTE",C94,0) -> 25000
A95: 45055 | B95: jgo pastilla d22 | C95: 22000 | D95: PENDIENTE | F95: cesar | I95: =IF(D95="PENDIENTE",C95,0) -> 22000
A96: 45175 | B96: PRESUPUESTO 5902 | C96: 23000 | D96: PENDIENTE | F96: DELIS | I96: =IF(D96="PENDIENTE",C96,0) -> 23000
A97: 45202 | B97: CAMBIO DE ACEITE TERRANO TOSCO | C97: 85000 | D97: PENDIENTE | F97: DELIS | I97: =IF(D97="PENDIENTE",C97,0) -> 85000
A98: 45217 | B98: PLUMILLA 20" AMPOLLETA H4 COOL BLUE | C98: 26500 | D98: PENDIENTE | F98: DELIS | I98: =IF(D98="PENDIENTE",C98,0) -> 26500
A99: 45229 | B99: jgo empaquetadura celerio | C99: 56500 | D99: PAGADO | F99: DELIS | I99: =IF(D99="PENDIENTE",C99,0) -> 0
A100: 45229 | B100: termostato celerio | C100: 14000 | D100: PAGADO | F100: DELIS | I100: =IF(D100="PENDIENTE",C100,0) -> 0
A101: 45239 | B101: liquido freno dot 4 celerio | C101: 8000 | D101: PAGADO | F101: DELIS | I101: =IF(D101="PENDIENTE",C101,0) -> 0
A102: 45257 | B102: filtro aceite agua celerio | C102: 39500 | D102: PAGADO | I102: =IF(D102="PENDIENTE",C102,0) -> 0
A103: 45259 | B103: pastilla y bujias | C103: 42000 | D103: PAGADO | I103: =IF(D103="PENDIENTE",C103,0) -> 0
A104: 45259 | B104: aceite y agua roja fiat ram | C104: 40000 | D104: PAGADO | I104: =IF(D104="PENDIENTE",C104,0) -> 0
A105: 45260 | B105: CREMALLERA +TERMINALES +ATF KB4 | C105: 50000 | D105: PAGADO | F105: CESAR | I105: =IF(D105="PENDIENTE",C105,0) -> 0
A106: 45267 | B106: BOMBA EMBRAGUE YD25 | C106: 22500 | D106: PENDIENTE | I106: =IF(D106="PENDIENTE",C106,0) -> 22500
A107: 45315 | B107: h1 ampo. Amarilo cola pescado | C107: 12000 | D107: PENDIENTE | I107: =IF(D107="PENDIENTE",C107,0) -> 12000
A108: 45317 | B108: GASKET | C108: 5000 | D108: PENDIENTE | I108: =IF(D108="PENDIENTE",C108,0) -> 5000
A109: 45345 | B109: empaquetadura multiple | C109: 12000 | D109: PENDIENTE | I109: =IF(D109="PENDIENTE",C109,0) -> 12000
A110: 45349 | B110: aceite 5w/30 edge | C110: 18000 | D110: PENDIENTE | I110: =IF(D110="PENDIENTE",C110,0) -> 18000
A111: 45350 | B111: aceite 15w/40 filtro cambio extendido | C111: 56000 | D111: PENDIENTE | I111: =IF(D111="PENDIENTE",C111,0) -> 56000
A112: 45365 | B112: JGO BUJIAS SAMURAI + REFRIGERANTE+ACEITE | C112: 22000 | D112: PENDIENTE | I112: =IF(D112="PENDIENTE",C112,0) -> 22000
A113: 45365 | B113: ROTULA SUPERIOR HILUX | C113: 16000 | D113: PENDIENTE | I113: =IF(D113="PENDIENTE",C113,0) -> 16000
B114: aceite 10w/40 y filtro | C114: 37000 | D114: PENDIENTE | I114: =IF(D114="PENDIENTE",C114,0) -> 37000
B115: fltro aceite + 1 litro cambio extendido | C115: 18000 | D115: PENDIENTE | I115: =IF(D115="PENDIENTE",C115,0) -> 18000
A116: 45439 | B116: BARRA CENTRAL JGO TERMINALES D22 4X4 | C116: 105000 | D116: PENDIENTE | I116: =IF(D116="PENDIENTE",C116,0) -> 105000
A117: 45464 | B117: cooper | C117: 24000 | D117: PENDIENTE | I117: =IF(D117="PENDIENTE",C117,0) -> 24000
A118: 45477 | B118: ATF | C118: 7000 | D118: PENDIENTE | I118: =IF(D118="PENDIENTE",C118,0) -> 7000
A119: 45506 | B119: CAMBIO VECTON CON FILTRO | C119: 40000 | D119: PENDIENTE | I119: =IF(D119="PENDIENTE",C119,0) -> 40000
A120: 45544 | B120: correa a27 | C120: 7500 | D120: PENDIENTE | I120: =IF(D120="PENDIENTE",C120,0) -> 7500
A121: 45548 | B121: PRESUPUESTO 6339 | C121: 42000 | D121: PENDIENTE | I121: =IF(D121="PENDIENTE",C121,0) -> 42000
A122: 45548 | B122: liquido freno | C122: 4500 | D122: PENDIENTE | I122: =IF(D122="PENDIENTE",C122,0) -> 4500
B123: refrigerante | C123: 4500 | D123: PENDIENTE | I123: =IF(D123="PENDIENTE",C123,0) -> 4500
A124: 45587 | B124: bomba embrague liquido freno | C124: 60000 | D124: PENDIENTE | I124: =IF(D124="PENDIENTE",C124,0) -> 60000
A125: 45673 | B125: presupuesto 6529 | C125: 28000 | D125: PENDIENTE | I125: =IF(D125="PENDIENTE",C125,0) -> 28000
...

Sheet QUEZADA RICHARD
A1: FECHA | B1: REPUESTO | C1: PRECIO | D1: CONDICION | E1: FACTURA | F1: VENDEDOR | H1: FACTURA | I1: DEUDA | J1: TOTAL DEUDA
A2: 44204 | B2: JUEGO TERMINALES | C2: 18000 | D2: PAGADO | E2: NO FACTURADO | F2: OMAR | I2: =IF(D2="PENDIENTE",C2,0) -> 0 | J2: =SUM(I:I) -> 0 | K2: MENU
A3: 44204 | B3: JUEGO AXIALES | C3: 17000 | D3: PAGADO | E3: NO FACTURADO | F3: CESAR | I3: =IF(D3="PENDIENTE",C3,0) -> 0
A4: 44204 | B4: JUEGO BIELETA TRAS | C4: 16000 | D4: PAGADO | E4: NO FACTURADO | F4: CESAR | I4: =IF(D4="PENDIENTE",C4,0) -> 0
A5: 44204 | B5: JUEGO BUJE BARRA | C5: 7000 | D5: PAGADO | E5: NO FACTURADO | F5: CESAR | I5: =IF(D5="PENDIENTE",C5,0) -> 0
A6: 44204 | B6: JUEGO BIELETA DEL | C6: 22000 | D6: PAGADO | E6: NO FACTURADO | F6: CESAR | I6: =IF(D6="PENDIENTE",C6,0) -> 0
A7: 44204 | B7: JUEGO CORREAS | C7: 7000 | D7: PAGADO | E7: NO FACTURADO | F7: CESAR | I7: =IF(D7="PENDIENTE",C7,0) -> 0
A8: 44204 | B8: JUEGO PASTILLAS | C8: 16000 | D8: PAGADO | E8: NO FACTURADO | F8: CESAR | I8: =IF(D8="PENDIENTE",C8,0) -> 0
A9: 44204 | B9: JUEGO ROTULAS | C9: 38000 | D9: PAGADO | E9: NO FACTURADO | F9: CESAR | I9: =IF(D9="PENDIENTE",C9,0) -> 0
A10: 44204 | B10: JUEGO H7 | C10: 7000 | D10: PAGADO | E10: NO FACTURADO | F10: CESAR | I10: =IF(D10="PENDIENTE",C10,0) -> 0
A11: 44438 | B11: ACEITE + FILTRO | C11: 73000 | D11: PAGADO | E11: NO FACTURADO | F11: CESAR | I11: =IF(D11="PENDIENTE",C11,0) -> 0
A12: 44743 | B12: farol trasero | C12: 65000 | D12: PAGADO | E12: NO FACTURADO | F12: CESAR | I12: =IF(D12="PENDIENTE",C12,0) -> 0
A13: 44746 | B13: rotula | C13: 25000 | D13: PAGADO | E13: NO FACTURADO | F13: CESAR | I13: =IF(D13="PENDIENTE",C13,0) -> 0
A14: 44762 | B14: BANDEJAS | C14: 305000 | D14: PAGADO | E14: NO FACTURADO | F14: CESAR | I14: =IF(D14="PENDIENTE",C14,0) -> 0
... A16: 44923 | B16: kit embrague | C16: 250000 | D16: PAGADO | E16: NO FACTURADO | F16: CESAR | I16: =IF(D16="PENDIENTE",C16,0) -> 0
A17: 45155 | B17: rotula | C17: 40000 | D17: PAGADO | F17: CESAR | I17: =IF(D17="PENDIENTE",C17,0) -> 0
A18: 45279 | B18: PASTILLA Y 2 H7 | C18: 42000 | D18: PAGADO | F18: CESAR | I18: =IF(D18="PENDIENTE",C18,0) -> 0
I19: =IF(D19="PENDIENTE",C19,0) -> 0
I20: =IF(D20="PENDIENTE",C20,0) -> 0
I21: =IF(D21="PENDIENTE",C21,0) -> 0
I22: =IF(D22="PENDIENTE",C22,0) -> 0
I23: =IF(D23="PENDIENTE",C23,0) -> 0
I24: =IF(D24="PENDIENTE",C24,0) -> 0
I25: =IF(D25="PENDIENTE",C25,0) -> 0
I26: =IF(D26="PENDIENTE",C26,0) -> 0
I27: =IF(D27="PENDIENTE",C27,0) -> 0
I28: =IF(D28="PENDIENTE",C28,0) -> 0
I29: =IF(D29="PENDIENTE",C29,0) -> 0
I30: =IF(D30="PENDIENTE",C30,0) -> 0
... I40: =IF(D40="PENDIENTE",C40,0) -> 0

Sheet REYES ANDRES (PIRLO)
A1: FECHA | B1: REPUESTO | C1: PRECIO | D1: CONDICION | E1: FACTURA | F1: VENDEDOR | H1: FACTURA | I1: DEUDA | J1: TOTAL DEUDA | M1: abono
A2: 44212 | B2: LIQUIDO FRENO | C2: 4000 | D2: PAGADO | E2: NO FACTURA | F2: OMAR | H2: =IF(E:E="NO FACTURADO","PENDIENTE","AL DIA") -> AL DIA | I2: =IF(D2="PENDIENTE",C2,0) -> 0 | J2: =SUM(I:I) -> 0 | K2: MENU
A3: 44212 | B3: RODAMIENTO EMBRAGUE | C3: 20000 | D3: PAGADO | E3: NO FACTURA | F3: CESAR | I3: =IF(D3="PENDIENTE",C3,0) -> 0
A4: 44212 | B4: BATERIA 90 AMP *CAMBIO DE POSITIVO (115 K)(PENDIENTE DESPUES DE ABONO) | C4: 20000 | D4: PAGADO | E4: NO FACTURA | F4: CESAR | I4: =IF(D4="PENDIENTE",C4,0) -> 0
A5: 44284 | B5: ABONO | C5: 95000 | D5: PAGADO | E5: NO FACTURA | F5: NATALIA | I5: =IF(D5="PENDIENTE",C5,0) -> 0
A6: 44355 | B6: BARRA DE DIRECCION | C6: 81500 | D6: PAGADO | E6: NO FACTURA | F6: CESAR | I6: =IF(D6="PENDIENTE",C6,0) -> 0
A7: 44438 | B7: MANTENCION TERRANO | C7: 25000 | D7: PAGADO | E7: NO FACTURA | F7: CESAR | I7: =IF(D7="PENDIENTE",C7,0) -> 0
A8: 44446 | B8: TURBO SALDO | C8: 160000 | D8: PAGADO | E8: NO FACTURA | F8: CESAR | I8: =IF(D8="PENDIENTE",C8,0) -> 0
A9: 44790 | B9: PRESUPUESTO 5267 | C9: 276000 | D9: PAGADO | E9: BOLETA | F9: DELIS | I9: =IF(D9="PENDIENTE",C9,0) -> 0 | M9: 200000 | N9: 44834 | O9: transferencia
B10: saldo del pressupuesto 5267 | C10: 76000 | D10: pagado | I10: =IF(D10="PENDIENTE",C10,0) -> 0
I11: =IF(D11="PENDIENTE",C11,0) -> 0
I12: =IF(D12="PENDIENTE",C12,0) -> 0
I13: =IF(D13="PENDIENTE",C13,0) -> 0
I14: =IF(D14="PENDIENTE",C14,0) -> 0
I15: =IF(D15="PENDIENTE",C15,0) -> 0
I16: =IF(D16="PENDIENTE",C16,0) -> 0
I17: =IF(D17="PENDIENTE",C17,0) -> 0
I18: =IF(D18="PENDIENTE",C18,0) -> 0
I19: =IF(D19="PENDIENTE",C19,0) -> 0
I20: =IF(D20="PENDIENTE",C20,0) -> 0
I21: =IF(D21="PENDIENTE",C21,0) -> 0
I22: =IF(D22="PENDIENTE",C22,0) -> 0
... I38: =IF(D38="PENDIENTE",C38,0) -> 0

Sheet ROA JULIAN
A1: FECHA | B1: REPUESTO | C1: PRECIO | D1: CONDICION | E1: FACTURA | F1: VENDEDOR | H1: FACTURA | I1: DEUDA | J1: TOTAL DEUDA
B2: SALDO | C2: 9000 | D2: pagado | E2: NO | F2: OMAR | H2: =IF(E:E="NO FACTURADO","PENDIENTE","AL DIA") -> AL DIA | I2: =IF(D2="PENDIENTE",C2,0) -> 0 | J2: =SUM(I:I) -> 0 | K2: MENU
A3: 44268 | B3: BOMBA DE BENCINA BOSCH | C3: 33000 | D3: pagado | E3: NO | F3: CESAR | I3: =IF(D3="PENDIENTE",C3,0) -> 0
A4: 44268 | B4: AGUA 711 | C4: 8000 | D4: pagado | E4: NO | F4: DELIS | H4: pagadp | I4: =IF(D4="PENDIENTE",C4,0) -> 0
A5: 44660 | B5: BATERIA 55AMPERES | C5: 32000 | D5: pagado | F5: DELIS | I5: =IF(D5="PENDIENTE",C5,0) -> 0
A6: 44884 | B6: correa 6pk-1460 | C6: 12000 | D6: pagado | F6: DELIS | I6: =IF(D6="PENDIENTE",C6,0) -> 0
A7: 44910 | B7: kit distribucion | C7: 19000 | D7: pagado | F7: DELIS | I7: =IF(D7="PENDIENTE",C7,0) -> 0
A8: 44910 | B8: reten distribucion (2) | C8: 10000 | D8: pagado | F8: DELIS | I8: =IF(D8="PENDIENTE",C8,0) -> 0
A9: 45106 | B9: saldo | C9: 20000 | D9: pagado | F9: DELIS | I9: =IF(D9="PENDIENTE",C9,0) -> 0
A10: 45177 | B10: CAZOLETA X2 | C10: 24000 | D10: pagado | F10: DELIS | I10: =IF(D10="PENDIENTE",C10,0) -> 0
A11: 45177 | B11: AMORTIGUADORES DELANTERO | C11: 50000 | D11: pagado | F11: DELIS | I11: =IF(D11="PENDIENTE",C11,0) -> 0
A12: 45181 | B12: manilla puerta lh | C12: 8000 | D12: pagado | F12: DELIS | I12: =IF(D12="PENDIENTE",C12,0) -> 0
A13: 45232 | B13: BANDEJA CORSA | C13: 24000 | D13: pagado | F13: DELIS | I13: =IF(D13="PENDIENTE",C13,0) -> 0
A14: 45481 | B14: homocinetica y rodamiento | C14: 35000 | D14: pagado | F14: DELIS | I14: =IF(D14="PENDIENTE",C14,0) -> 0
A15: 45485 | B15: acero liquido | C15: 5000 | D15: pagado | F15: DELIS | I15: =IF(E15="PENDIENTE",C15,0) -> 0
A16: 45516 | B16: SALDO EXTREMO HOMOCINETICA | C16: 30000 | D16: pagado | I16: =IF(D16="PENDIENTE",C16,0) -> 0
A17: 45532 | B17: correa y bomba | C17: 30000 | D17: pagado | I17: =IF(D17="PENDIENTE",C17,0) -> 0
A18: 45507 | B18: CAJA DIRECCION | C18: 100000 | D18: pagado | I18: =IF(D18="PENDIENTE",C18,0) -> 0
I19: =IF(D19="PENDIENTE",C19,0) -> 0
I20: =IF(D20="PENDIENTE",C20,0) -> 0
I21: =IF(D21="PENDIENTE",C21,0) -> 0
I22: =IF(D22="PENDIENTE",C22,0) -> 0
I23: =IF(D23="PENDIENTE",C23,0) -> 0
I24: =IF(D24="PENDIENTE",C24,0) -> 0
I25: =IF(D25="PENDIENTE",C25,0) -> 0
I26: =IF(D26="PENDIENTE",C26,0) -> 0
I27: =IF(D27="PENDIENTE",C27,0) -> 0
I28: =IF(D28="PENDIENTE",C28,0) -> 0
I29: =IF(D29="PENDIENTE",C29,0) -> 0
I30: =IF(D30="PENDIENTE",C30,0) -> 0
... I40: =IF(D40="PENDIENTE",C40,0) -> 0

Sheet ROGEL MARCOS
A1: FECHA | B1: REPUESTO | C1: PRECIO | D1: CONDICION | E1: FACTURA | F1: VENDEDOR | H1: FACTURA | I1: DEUDA | J1: TOTAL DEUDA
B2: SALDO | C2: 303500 | D2: PENDIENTE | E2: NO | F2: OMAR | H2: =IF(E:E="NO FACTURADO","PENDIENTE","AL DIA") -> AL DIA | I2: =IF(D2="PENDIENTE",C2,0) -> 303500 | J2: =SUM(I:I) -> 393500 | K2: MENU
A3: 44235 | B3: PRESUPUESTO ED33 N 4308 | C3: 101000 | D3: PAGADO | E3: NO FACTURADO | F3: CESAR | H3: =IF(E:E="NO FACTURADO","PENDIENTE","AL DIA") -> PENDIENTE | I3: =IF(D3="PENDIENTE",C3,0) -> 0
A4: 44239 | B4: BOMBA ACEITE ORIGINAL | C4: 240000 | D4: PAGADO | E4: NO FACTURADO | F4: CESAR | H4: =IF(E:E="NO FACTURADO","PENDIENTE","AL DIA") -> PENDIENTE | I4: =IF(D4="PENDIENTE",C4,0) -> 0
A5: 44277 | C5: 60000 | D5: PAGADO | E5: NO FACTURADO | F5: CESAR | H5: =IF(E:E="NO FACTURADO","PENDIENTE","AL DIA") -> PENDIENTE | I5: =IF(D5="PENDIENTE",C5,0) -> 0
A6: 44280 | B6: D22: EMP MOTOR, JGO BUJIA, SILICONA | C6: 7000 | D6: PENDIENTE | E6: NO FACTURADO | F6: CESAR | H6: =IF(E:E="NO FACTURADO","PENDIENTE","AL DIA") -> PENDIENTE | I6: =IF(D6="PENDIENTE",C6,0) -> 7000
A7: 44280 | B7: YD25:JGO EMP MOTOR, JGO VALVULA ADM/ESC | C7: 262000 | D7: PAGADO | E7: NO FACTURADO | F7: CESAR | H7: =IF(E:E="NO FACTURADO","PENDIENTE","AL DIA") -> PENDIENTE | I7: =IF(D7="PENDIENTE",C7,0) -> 0
A8: 44327 | B8: SELLOS VALVULA EGI | C8: 12000 | D8: PAGADO | E8: NO FACTURADO | F8: CESAR | H8: =IF(E:E="NO FACTURADO","PENDIENTE","AL DIA") -> PENDIENTE | I8: =IF(D8="PENDIENTE",C8,0) -> 0
A9: 44351 | B9: EMPAQUETADURA + PONCHOS | C9: 14000 | D9: PAGADO | E9: NO FACTURADO | F9: CESAR | H9: =IF(E:E="NO FACTURADO","PENDIENTE","AL DIA") -> PENDIENTE | I9: =IF(D9="PENDIENTE",C9,0) -> 0
A10: 44418 | B10: SELLOS VALVULA | C10: 8000 | D10: PAGADO | E10: NO FACTURADO | F10: CESAR | H10: =IF(E:E="NO FACTURADO","PENDIENTE","AL DIA") -> PENDIENTE | I10: =IF(D10="PENDIENTE",C10,0) -> 0
A11: 44495 | B11: SELLO DE VALVULA | C11: 20000 | D11: PAGADO | E11: NO FACTURADO | F11: CESAR | H11: =IF(E:E="NO FACTURADO","PENDIENTE","AL DIA") -> PENDIENTE | I11: =IF(D11="PENDIENTE",C11,0) -> 0
A12: 44495 | B12: EMPAQUEATDURA CULATA | C12: 95000 | D12: devuelta | E12: NO FACTURADO | F12: CESAR | H12: =IF(E:E="NO FACTURADO","PENDIENTE","AL DIA") -> PENDIENTE | I12: =IF(D12="PENDIENTE",C12,0) -> 0
A13: 44495 | B13: METALES BANCADA | C13: 35000 | D13: PAGADO | E13: NO FACTURADO | F13: CESAR | H13: =IF(E:E="NO FACTURADO","PENDIENTE","AL DIA") -> PENDIENTE | I13: =IF(D13="PENDIENTE",C13,0) -> 0
A14: 44518 | B14: PONCHO SPARK | C14: 8000 | D14: PENDIENTE | E14: NO FACTURADO | F14: CESAR | H14: =IF(E:E="NO FACTURADO","PENDIENTE","AL DIA") -> PENDIENTE | I14: =IF(D14="PENDIENTE",C14,0) -> 8000
A15: 44529 | B15: repuestos cerato | C15: 138000 | D15: pagado | E15: no facturado | F15: cesar | H15: =IF(E:E="NO FACTURADO","PENDIENTE","AL DIA") -> PENDIENTE | I15: =IF(D15="PENDIENTE",C15,0) -> 0
A16: 44537 | B16: REPUESTOS SUNNY | C16: 37000 | D16: Pagado | F16: CESAR | H16: PENDIENTE | I16: =IF(D16="PENDIENTE",C16,0) -> 0
A17: 44546 | B17: PISTOLA IMPACTO CUATRO CUOTAS | C17: 75000 | D17: PENDIENTE | F17: CESAR | H17: =IF(E:E="NO FACTURADO","PENDIENTE","AL DIA") -> AL DIA | I17: =IF(D17="PENDIENTE",C17,0) -> 75000
A18: 44817 | B18: nota venta 575 | C18: 52000 | D18: PAGADO | F18: CESAR | H18: =IF(E:E="NO FACTURADO","PENDIENTE","AL DIA") -> AL DIA | I18: =IF(D18="PENDIENTE",C18,0) -> 0
A19: 44826 | B19: KIA POP | C19: 56000 | D19: PAGADO | F19: CESAR | H19: =IF(E:E="NO FACTURADO","PENDIENTE","AL DIA") -> AL DIA | I19: =IF(D19="PENDIENTE",C19,0) -> 0
A20: 44972 | B20: bujias | C20: 0 | D20: PAGADO | F20: CESAR | H20: =IF(E:E="NO FACTURADO","PENDIENTE","AL DIA") -> AL DIA | I20: =IF(D20="PENDIENTE",C20,0) -> 0
H21: =IF(E:E="NO FACTURADO","PENDIENTE","AL DIA") -> AL DIA | I21: =IF(D21="PENDIENTE",C21,0) -> 0
H22: =IF(E:E="NO FACTURADO","PENDIENTE","AL DIA") -> AL DIA | I22: =IF(D22="PENDIENTE",C22,0) -> 0
H23: =IF(E:E="NO FACTURADO","PENDIENTE","AL DIA") -> AL DIA | I23: =IF(D23="PENDIENTE",C23,0) -> 0
H24: =IF(E:E="NO FACTURADO","PENDIENTE","AL DIA") -> AL DIA | I24: =IF(D24="PENDIENTE",C24,0) -> 0
I25: =IF(D25="PENDIENTE",C25,0) -> 0
I26: =IF(D26="PENDIENTE",C26,0) -> 0
I27: =IF(D27="PENDIENTE",C27,0) -> 0
I28: =IF(D28="PENDIENTE",C28,0) -> 0
I29: =IF(D29="PENDIENTE",C29,0) -> 0
I30: =IF(D30="PENDIENTE",C30,0) -> 0
I31: =IF(D31="PENDIENTE",C31,0) -> 0
I32: =IF(D32="PENDIENTE",C32,0) -> 0
I33: =IF(D33="PENDIENTE",C33,0) -> 0
I34: =IF(D34="PENDIENTE",C34,0) -> 0
I35: =IF(D35="PENDIENTE",C35,0) -> 0
I36: =IF(D36="PENDIENTE",C36,0) -> 0
... I39: =IF(D39="PENDIENTE",C39,0) -> 0

Sheet ROSAS ALVARO
A1: FECHA | B1: REPUESTO | C1: PRECIO | D1: CONDICION | E1: FACTURA | F1: VENDEDOR | H1: FACTURA | I1: DEUDA | J1: TOTAL DEUDA
A2: 44265 | C2: 90000 | D2: PAGADO | F2: OMAR | I2: =IF(D2="PENDIENTE",C2,0) -> 0 | K2: MENU
A3: 44267 | B3: AXIAL KUN | C3: 13000 | D3: PAGADO | E3: FACTURADO | F3: CESAR | H3: AL DIA | I3: =IF(D3="PENDIENTE",C3,0) -> 0
A4: 44412 | B4: TERMOSTATO Y AGUA COROLLA | C4: 15000 | D4: PAGADO | E4: FACTURADO | F4: DELIS | I4: =IF(D4="PENDIENTE",C4,0) -> 0
A5: 44438 | B5: 4 SELLOS DE AGUA | C5: 8000 | D5: PAGADO | E5: FACTURADO | F5: CESAR | I5: =IF(D5="PENDIENTE",C5,0) -> 0
A6: 44476 | B6: rotulas maxus | C6: 57000 | D6: PAGADO | E6: no facturado | F6: CESAR | I6: =IF(D6="PENDIENTE",C6,0) -> 0
A7: 44518 | B7: repuestos dmax | C7: 53000 | D7: pagado | E7: no facturado | F7: OMAR | I7: =IF(D7="PENDIENTE",C7,0) -> 0
A8: 44536 | B8: cambio aceite | C8: 22000 | D8: PAGADO | F8: CESAR | I8: =IF(D8="PENDIENTE",C8,0) -> 0
A9: 44536 | B9: atf x2 joven | C9: 15000 | D9: pagado | F9: CESAR | I9: =IF(D9="PENDIENTE",C9,0) -> 0
A10: 15712/2021 | B10: filtro aire c-23107 | C10: 10000 | D10: PAGADO | F10: CESAR | I10: =IF(D10="PENDIENTE",C10,0) -> 0
A11: 44551 | B11: jgo bujias | C11: 16000 | D11: pagado | F11: CESAR | I11: =IF(D11="PENDIENTE",C11,0) -> 0
A12: 44734 | C12: 205000 | D12: pagado | I12: =IF(D12="PENDIENTE",C12,0) -> 0
B13: correa | C13: 5000 | D13: pagado | I13: =IF(D13="PENDIENTE",C13,0) -> 0
A14: 44755 | B14: aceite filtro | C14: 32000 | D14: PAGADO | F14: omar | I14: =IF(D14="PENDIENTE",C14,0) -> 0
A15: 44790 | B15: jgo bornes + termostato | C15: 6000 | D15: pagado | F15: cesar | I15: =IF(D15="PENDIENTE",C15,0) -> 0
B16: jgo bujias | C16: 10000 | D16: PAGADO | F16: omar | I16: =IF(D16="PENDIENTE",C16,0) -> 0
B17: fuellle kia | C17: 7500 | D17: PAGADO | F17: delis | I17: =IF(D17="PENDIENTE",C17,0) -> 0
A18: 44971 | B18: 3 80W90 | C18: 21000 | D18: PAGADO | F18: CESAR | I18: =IF(D18="PENDIENTE",C18,0) -> 0
A19: 44993 | B19: CRUCETA | C19: 23000 | D19: PAGADO | F19: cesar | I19: =IF(D19="PENDIENTE",C19,0) -> 0 | L19: 44994 | M19: abono
A20: 45058 | B20: aceite y filtro | C20: 28000 | D20: pagado | F20: cesar | I20: =IF(D20="PENDIENTE",C20,0) -> 0 | L20: 45072 | M20: pagado
A21: 45203 | B21: bateria 55 amperes | C21: 30000 | D21: PAGADO | F21: cesar | I21: =IF(D21="PENDIENTE",C21,0) -> 0 | K21: 20000 | L21: abono 16/10
A22: 45233 | B22: aceite y filtros | C22: 53000 | D22: PAGADO | F22: cesar | I22: =IF(D22="PENDIENTE",C22,0) -> 0
A23: 45233 | B23: rodamiento maza dahiatsu | C23: 40000 | D23: PAGADO | F23: cesar | I23: =IF(D23="PENDIENTE",C23,0) -> 0
B24: alzaespiral | C24: 25000 | D24: pagado | E24: efectivo16-02-2024 | I24: =IF(D24="PENDIENTE",C24,0) -> 0
A25: 45371 | B25: fuelle yaris | C25: 12000 | D25: pagado | I25: =IF(D25="PENDIENTE",C25,0) -> 0
A26: 45638 | B26: empaquetadura culata | C26: 12000 | D26: pendiente | I26: =IF(D26="PENDIENTE",C26,0) -> 12000
A27: 45642 | B27: filtro aceite | C27: 5000 | D27: pendiente | I27: =IF(D27="PENDIENTE",C27,0) -> 5000
A28: 45642 | B28: jgo bujias | C28: 10000 | D28: pendiente | I28: =IF(D28="PENDIENTE",C28,0) -> 10000
A29: 45638 | B29: jgo bujias filtro | C29: 85000 | D29: pendiente | I29: =IF(D29="PENDIENTE",C29,0) -> 85000
I30: =IF(D30="PENDIENTE",C30,0) -> 0
I31: =IF(D31="PENDIENTE",C31,0) -> 0
I32: =IF(D32="PENDIENTE",C32,0) -> 0
I33: =IF(D33="PENDIENTE",C33,0) -> 0
I34: =IF(D34="PENDIENTE",C34,0) -> 0
I35: =IF(D35="PENDIENTE",C35,0) -> 0
I36: =IF(D36="PENDIENTE",C36,0) -> 0
I37: =IF(D37="PENDIENTE",C37,0) -> 0
I38: =IF(D38="PENDIENTE",C38,0) -> 0
I39: =IF(D39="PENDIENTE",C39,0) -> 0

Sheet ROSAS SERGIO (DON CHECHO)
A1: FECHA | B1: REPUESTO | C1: PRECIO | D1: CONDICION | E1: FACTURA | F1: VENDEDOR | H1: FACTURA | I1: DEUDA | J1: TOTAL DEUDA
B2: SALDO | D2: PAGADO | E2: NO | F2: OMAR | H2: =IF(E:E="NO FACTURADO","PENDIENTE","AL DIA") -> AL DIA | I2: =IF(D2="PENDIENTE",C2,0) -> 0 | J2: =SUM(I:I) -> 0 | K2: MENU
A3: 44614 | B3: fuelle y grasa | C3: 17000 | D3: PAGADO | F3: OMAR | I3: =IF(D3="PENDIENTE",C3,0) -> 0
A4: 44615 | B4: 3 correa y jgo bujias | C4: 25000 | D4: PAGADO | F4: cesar | I4: =IF(D4="PENDIENTE",C4,0) -> 0
A5: 44690 | B5: presupuesto nº 5036 | C5: 81000 | D5: PAGADO | I5: =IF(D5="PENDIENTE",C5,0) -> 0
A6: 44714 | B6: repuestos tercel | C6: 48000 | D6: PAGADO | F6: cesar | I6: =IF(D6="PENDIENTE",C6,0) -> 0
A7: 44873 | B7: empaquetadura culata multiple picaron | C7: 20000 | D7: Pagado | F7: delis | I7: =IF(D7="PENDIENTE",C7,0) -> 0
A8: 44915 | B8: rodamiento | C8: 12000 | D8: PAGADO | F8: omar | I8: =IF(D8="PENDIENTE",C8,0) -> 0
A9: 44935 | B9: EMPAQUETADURA TAPA VALVULA AVEO | C9: 8000 | D9: PAGADO | F9: cesar | I9: =IF(D9="PENDIENTE",C9,0) -> 0
A10: 44936 | B10: 2 LITRO 80/90 LS | C10: 20000 | D10: PAGADO | F10: delis | I10: =IF(D10="PENDIENTE",C10,0) -> 0
B11: platino condensador | C11: 9000 | D11: PAGADO | I11: =IF(D11="PENDIENTE",C11,0) -> 0
B12: bujias | C12: 12000 | D12: PAGADO | I12: =IF(D12="PENDIENTE",C12,0) -> 0
B13: ABRAZADERAS | C13: 7000 | D13: PAGADO | I13: =IF(D13="PENDIENTE",C13,0) -> 0
A14: 45358 | B14: plumillas suzuki | C14: 25000 | D14: PAGADO | I14: =IF(D14="PENDIENTE",C14,0) -> 0
A15: 45359 | B15: plumilla trasera suzuki | C15: 7500 | D15: PAGADO | I15: =IF(D15="PENDIENTE",C15,0) -> 0
I16: =IF(D16="PENDIENTE",C16,0) -> 0
I17: =IF(D17="PENDIENTE",C17,0) -> 0
I18: =IF(D18="PENDIENTE",C18,0) -> 0
I19: =IF(D19="PENDIENTE",C19,0) -> 0
I20: =IF(D20="PENDIENTE",C20,0) -> 0
I21: =IF(D21="PENDIENTE",C21,0) -> 0
I22: =IF(D22="PENDIENTE",C22,0) -> 0
I23: =IF(D23="PENDIENTE",C23,0) -> 0
I24: =IF(D24="PENDIENTE",C24,0) -> 0
I25: =IF(D25="PENDIENTE",C25,0) -> 0
I26: =IF(D26="PENDIENTE",C26,0) -> 0
I27: =IF(D27="PENDIENTE",C27,0) -> 0
... I40: =IF(D40="PENDIENTE",C40,0) -> 0

Sheet RUIZ JOAQUIN (CHISPA)
A1: FECHA | B1: REPUESTO | C1: PRECIO | D1: CONDICION | E1: FACTURA | F1: VENDEDOR | H1: FACTURA | I1: DEUDA | J1: TOTAL DEUDA | L1: presupuesto
B2: SALDO | D2: PENDIENTE | E2: NO | F2: OMAR | H2: =IF(E:E="NO FACTURADO","PENDIENTE","AL DIA") -> AL DIA | I2: =IF(D2="PENDIENTE",C2,0) -> 0 | J2: =SUM(I:I) -> 5500 | K2: MENU
A3: 44230 | B3: 2 BATERIA 90 AMP | C3: 180000 | D3: pagado | E3: facturado | F3: CESAR | H3: =IF(E:E="NO FACTURADO","PENDIENTE","AL DIA") -> AL DIA | I3: =IF(D3="PENDIENTE",C3,0) -> 0
A4: 44230 | B4: AXIAL | C4: 14500 | D4: pagado | E4: facturado | F4: CESAR | H4: =IF(E:E="NO FACTURADO","PENDIENTE","AL DIA") -> AL DIA | I4: =IF(D4="PENDIENTE",C4,0) -> 0
A5: 44230 | B5: JUEGO TERMINAL | C5: 13000 | D5: pagado | E5: facturado | F5: CESAR | H5: =IF(E:E="NO FACTURADO","PENDIENTE","AL DIA") -> AL DIA | I5: =IF(D5="PENDIENTE",C5,0) -> 0
A6: 44230 | B6: 75W90 | C6: 11000 | D6: pagado | E6: facturado | F6: CESAR | H6: =IF(E:E="NO FACTURADO","PENDIENTE","AL DIA") -> AL DIA | I6: =IF(D6="PENDIENTE",C6,0) -> 0
A7: 44230 | B7: JUEGO BUJIA | C7: 10000 | D7: pagado | E7: facturado | F7: CESAR | H7: =IF(E:E="NO FACTURADO","PENDIENTE","AL DIA") -> AL DIA | I7: =IF(D7="PENDIENTE",C7,0) -> 0
A8: 44264 | B8: FILTRO ACEITE Y ROST OFF | C8: 10000 | D8: pagado | E8: facturado | F8: DELIS | H8: =IF(E:E="NO FACTURADO","PENDIENTE","AL DIA") -> AL DIA | I8: =IF(D8="PENDIENTE",C8,0) -> 0
A9: 44266 | B9: ACEITE 10W 40 PENZOIL | C9: 19000 | D9: pagado | E9: facturado | F9: CESAR | H9: =IF(E:E="NO FACTURADO","PENDIENTE","AL DIA") -> AL DIA | I9: =IF(D9="PENDIENTE",C9,0) -> 0
A10: 44266 | B10: GRASA LIQUIDO | C10: 5500 | D10: pagado | E10: facturado | F10: CESAR | H10: =IF(E:E="NO FACTURADO","PENDIENTE","AL DIA") -> AL DIA | I10: 5500
A11: 44267 | B11: ANTICONGELANTE | C11: 4000 | D11: pagado | E11: facturado | F11: CESAR | H11: =IF(E:E="NO FACTURADO","PENDIENTE","AL DIA") -> AL DIA | I11: =IF(D11="PENDIENTE",C11,0) -> 0
A12: 44268 | B12: ANTICONGELANTE | C12: 4000 | D12: pagado | E12: facturado | F12: CESAR | H12: =IF(E:E="NO FACTURADO","PENDIENTE","AL DIA") -> AL DIA | I12: =IF(D12="PENDIENTE",C12,0) -> 0
A13: 44270 | B13: 2 JUEGO DE BUJIAS | C13: 15000 | D13: pagado | E13: facturado | F13: CESAR | H13: =IF(E:E="NO FACTURADO","PENDIENTE","AL DIA") -> AL DIA | I13: =IF(D13="PENDIENTE",C13,0) -> 0
A14: 44281 | B14: JUEGO BUJIA | C14: 8000 | D14: pagado | E14: facturado | F14: OMAR | H14: =IF(E:E="NO FACTURADO","PENDIENTE","AL DIA") -> AL DIA | I14: =IF(D14="PENDIENTE",C14,0) -> 0
A15: 44279 | B15: 2 COOLANT 911 (DON SADY) | C15: 18000 | D15: pagado | E15: facturado | F15: CESAR | H15: =IF(E:E="NO FACTURADO","PENDIENTE","AL DIA") -> AL DIA | I15: =IF(D15="PENDIENTE",C15,0) -> 0
A16: 44281 | B16: EMPAQUETADURA TAPA VALVULA (DON SADY) | C16: 8000 | D16: pagado | E16: facturado | F16: OMAR | H16: =IF(E:E="NO FACTURADO","PENDIENTE","AL DIA") -> AL DIA | I16: =IF(D16="PENDIENTE",C16,0) -> 0
A17: 44284 | B17: 10W40 PENNZOIL | C17: 17000 | D17: pagado | E17: facturado | F17: NATALIA | H17: =IF(E:E="NO FACTURADO","PENDIENTE","AL DIA") -> AL DIA | I17: =IF(D17="PENDIENTE",C17,0) -> 0
A18: 44287 | B18: 2 LIQUIDO 711 | C18: 8000 | D18: pagado | E18: facturado | F18: DELIS | H18: =IF(E:E="NO FACTURADO","PENDIENTE","AL DIA") -> AL DIA | I18: =IF(D18="PENDIENTE",C18,0) -> 0
A19: 44292 | B19: BUJIAS | C19: 8000 | D19: pagado | E19: facturado | F19: CESAR | H19: =IF(E:E="NO FACTURADO","PENDIENTE","AL DIA") -> AL DIA | I19: =IF(D19="PENDIENTE",C19,0) -> 0
A20: 44294 | B20: SOP.CARDAN Y CRUCETA | C20: 30000 | D20: pagado | E20: facturado | F20: DELIS | H20: =IF(E:E="NO FACTURADO","PENDIENTE","AL DIA") -> AL DIA | I20: =IF(D20="PENDIENTE",C20,0) -> 0
A21: 44300 | B21: PRESUPUEST0 N· 4472 | C21: 50000 | D21: pagado | E21: NO | F21: OMAR | H21: =IF(E:E="NO FACTURADO","PENDIENTE","AL DIA") -> AL DIA | I21: =IF(D21="PENDIENTE",C21,0) -> 0 | L21: 4472
C22: 6500 | D22: pagado | E22: no | F22: OMAR | H22: =IF(E:E="NO FACTURADO","PENDIENTE","AL DIA") -> AL DIA | I22: =IF(D22="PENDIENTE",C22,0) -> 0
I23: =IF(D23="PENDIENTE",C23,0) -> 0
I24: =IF(D24="PENDIENTE",C24,0) -> 0
I25: =IF(D25="PENDIENTE",C25,0) -> 0
I26: =IF(D26="PENDIENTE",C26,0) -> 0
I27: =IF(D27="PENDIENTE",C27,0) -> 0
I28: =IF(D28="PENDIENTE",C28,0) -> 0
I29: =IF(D29="PENDIENTE",C29,0) -> 0
I30: =IF(D30="PENDIENTE",C30,0) -> 0
I31: =IF(D31="PENDIENTE",C31,0) -> 0
I32: =IF(D32="PENDIENTE",C32,0) -> 0
I33: =IF(D33="PENDIENTE",C33,0) -> 0
I34: =IF(D34="PENDIENTE",C34,0) -> 0
... I40: =IF(D40="PENDIENTE",C40,0) -> 0

Sheet T Y P
A1: FECHA | B1: REPUESTO | C1: PRECIO | D1: CONDICION | E1: FACTURA | F1: VENDEDOR | H1: FACTURA | I1: DEUDA | J1: TOTAL DEUDA
B2: SALDO | D2: PENDIENTE | E2: NO | F2: OMAR | H2: =IF(E:E="NO FACTURADO","PENDIENTE","AL DIA") -> AL DIA | I2: =IF(D2="PENDIENTE",C2,0) -> 0 | J2: =SUM(I:I) -> 0 | K2: MENU
A3: 44245 | B3: METAL EJE COMPENSADOR | D3: PAGADO | E3: NO | F3: CESAR | I3: =IF(D3="PENDIENTE",C3,0) -> 0
A4: 44249 | B4: METAL BIELA 0.25 | C4: 16500 | D4: PAGADO | F4: CESAR | I4: =IF(D4="PENDIENTE",C4,0) -> 0
A5: 44267 | B5: RETEN VALVULA | C5: 16000 | D5: PAGADO | E5: NO | F5: CESAR | I5: =IF(D5="PENDIENTE",C5,0) -> 0
A6: 44335 | B6: METAL MARUTI AMPOLLETA H4 | C6: 13500 | D6: PAGADO | E6: NO | I6: =IF(D6="PENDIENTE",C6,0) -> 0
A7: 44418 | B7: JGO SELLOS VALVULA | C7: 8000 | D7: PAGADO | E7: NO | F7: CESAR | I7: =IF(D7="PENDIENTE",C7,0) -> 0
I8: =IF(D8="PENDIENTE",C8,0) -> 0
I9: =IF(D9="PENDIENTE",C9,0) -> 0
I10: =IF(D10="PENDIENTE",C10,0) -> 0
I11: =IF(D11="PENDIENTE",C11,0) -> 0
I12: =IF(D12="PENDIENTE",C12,0) -> 0
I13: =IF(D13="PENDIENTE",C13,0) -> 0
I14: =IF(D14="PENDIENTE",C14,0) -> 0
I15: =IF(D15="PENDIENTE",C15,0) -> 0
I16: =IF(D16="PENDIENTE",C16,0) -> 0
I17: =IF(D17="PENDIENTE",C17,0) -> 0
I18: =IF(D18="PENDIENTE",C18,0) -> 0
I19: =IF(D19="PENDIENTE",C19,0) -> 0
... I40: =IF(D40="PENDIENTE",C40,0) -> 0

Sheet TOLEDO IVAN (EL TERRIBLE)
A1: FECHA | B1: REPUESTO | C1: PRECIO | D1: CONDICION | E1: FACTURA | F1: VENDEDOR | H1: FACTURA | I1: DEUDA | J1: TOTAL DEUDA
B2: SALDO | D2: PENDIENTE | E2: NO | F2: OMAR | H2: =IF(E:E="NO FACTURADO","PENDIENTE","AL DIA") -> AL DIA | I2: =IF(D2="PENDIENTE",C2,0) -> 0 | J2: =SUM(I:I) -> 0 | K2: MENU
A3: 45099 | B3: SALDO BATERIA | C3: 55000 | D3: pagado | F3: DELIS | I3: =IF(D3="PENDIENTE",C3,0) -> 0
A4: 45216 | B4: PASTILLA FRENO BANDEJA X2 | C4: 48000 | D4: pagado | F4: DELIS | I4: =IF(D4="PENDIENTE",C4,0) -> 0
I5: =IF(D5="PENDIENTE",C5,0) -> 0
I6: =IF(D6="PENDIENTE",C6,0) -> 0
I7: =IF(D7="PENDIENTE",C7,0) -> 0
I8: =IF(D8="PENDIENTE",C8,0) -> 0
I9: =IF(D9="PENDIENTE",C9,0) -> 0
I10: =IF(D10="PENDIENTE",C10,0) -> 0
I11: =IF(D11="PENDIENTE",C11,0) -> 0
I12: =IF(D12="PENDIENTE",C12,0) -> 0
I13: =IF(D13="PENDIENTE",C13,0) -> 0
I14: =IF(D14="PENDIENTE",C14,0) -> 0
I15: =IF(D15="PENDIENTE",C15,0) -> 0
I16: =IF(D16="PENDIENTE",C16,0) -> 0
... I39: =IF(D39="PENDIENTE",C39,0) -> 0

Sheet VERA LUIS (ELECTROVERA)
A1: FECHA | B1: REPUESTO | C1: PRECIO | D1: CONDICION | E1: FACTURA | F1: VENDEDOR | H1: FACTURA | I1: DEUDA | J1: TOTAL DEUDA
B2: SALDO | D2: PAGADO | E2: NO | F2: OMAR | H2: =IF(E2:E="NO FACTURADO","PENDIENTE","AL DIA") -> #NAME? | I2: =IF(D2="PENDIENTE",C2,0) -> 0 | J2: =SUM(I:I) -> 47000 | K2: MENU
A3: 44239 | B3: ACEITE 10W40 SHELL HELIX | C3: 25000 | D3: PAGADO | E3: NO FACTURADO | F3: DELIS | I3: =IF(D3="PENDIENTE",C3,0) -> 0
